Workbook

Sheet Rules
A1: STOCK ACTION SPEC — two new columns: "Company Type" and "Action"
B2: Purpose: score each stock from one day's screener row. Everything below is implemented as live formulas on the "Scored Data" sheet, with every threshold on the "Parameters" sheet. Column header comments on Scored Data explain each helper column. Output values for Action: Sell Immediately | Avoid | Hold | Buy with Risk | Buy | Strong Buy. A "Flags" column explains any override that changed the result.
A3: STEP 1 — Company Type (ETF / Established / Early)
B4: 1a ETF | C4: Portfolios contains "ETF", OR both Quality and Forward P/E are blank → "ETF". ETFs get technical scoring only.
B5: 1b Establishment score (0–7) | C5: Market Cap ≥ mc_big → +2 (≥ mc_mid → +1). Net Income TTM > 0 AND Profit Margin ≥ pm_est → +2 (Net Income > 0 alone → +1). FCF TTM > 0 AND FCF Margin ≥ fm_est → +1. 0 < Forward P/E ≤ pe_max → +1. Quality ≥ q_est → +1.
B6: 1c Classification | C6: Market Cap ≥ mc_override → "Established" (size override). Else score ≥ est_min → "Established", else "Early". Early = valued on future growth / not yet consistently profitable (SG, JOBY, CAVA, CRWV, SNOW, CRWD...). Established = large, profitable, sanely valued (AAPL, JPM, MU...).
A7: STEP 2 — Technical Score (all types, −10 … +10)
B8: T1 MA Cross | C8: Golden* → +2, Death* → −2, blank → 0 (LEFT() match, so "Golden (8d)" counts as Golden).
B9: T2 vs 200D MA % | C9: > v200_hi → +2; > 0 → +1; ≥ v200_lo → −1; < v200_lo → −2.
B10: T3 vs 50D MA % | C10: v50_lo ≤ x ≤ v50_hi → +1 (pullback/base). x > v50_ext (extended) or x < v50_wk (weak) → −1.
B11: T4 RSI | C11: rsi_lo ≤ RSI ≤ rsi_hi → +1. RSI > rsi_ob or RSI < rsi_os → −1.
B12: T5 Momentum Delta (2w) | C12: > md_up → +1; < md_dn → −1.
B13: T6 Momentum score | C13: ≥ mo_hi → +1; ≤ mo_lo → −1.
B14: T7 Volume confirmation | C14: Vol Trend % > vt_hi: if 1M % < 0 → −1 (distribution), if 1M % > 0 → +1 (accumulation).
B15: T8 % from 52W High | C15: > fh_near → +1; < fh_deep → −1.
A16: STEP 3 — Fundamental Score (rule set depends on Company Type)
B17: Established (FE1–FE6) | C17: Quality ≥ q_hi → +2 / ≥ q_mid → +1 / ≤ q_low → −1. Earnings Growth > eg_est → +1, < 0 → −1. Revenue Growth > rg_est → +1, < 0 → −1. 0 < PEG ≤ peg_ok → +1, PEG > peg_bad → −1. FCF Margin > fm_hi → +1, < 0 → −1. Net Cash > 0 → +1.
B18: Early (EA1–EA6) | C18: Revenue Growth > rg_e2 → +2 / > rg_e1 → +1 / < rg_e_lo → −1 / < 0 → −2. Gross Margin > gm_hi → +1, < gm_lo → −1. FCF TTM > 0 → +1, else FCF Margin < fm_neg → −1. Net Income TTM > 0 → +1. Short % Float > sf_vhi → −2, > sf_hi → −1. Quality ≥ q_e_hi → +1, ≤ q_e_lo → −1. (Early companies are judged on growth, gross margin and cash burn — not on P/E, PEG or earnings growth, which are meaningless for them.)
B19: ETF | C19: Fund Score = 0.
A20: STEP 4 — Composite and base tier
B21: Composite | C21: Established: Tech + Fund. Early: Tech + early_fund_wt × Fund (technicals carry more weight because Early fundamentals are noisy). ETF: Tech.
B22: Established tiers | C22: ≥ est_sb Strong Buy | ≥ est_b Buy | ≥ est_bwr Buy with Risk | ≥ est_h Hold | ≥ est_av Avoid | else Sell Immediately.
B23: Early tiers | C23: ≥ early_b Buy | ≥ early_bwr Buy with Risk | ≥ early_h Hold | ≥ early_av Avoid | else Sell Immediately. Early can never be Strong Buy.
B24: ETF tiers | C24: ≥ etf_sb Strong Buy | ≥ etf_b Buy | ≥ etf_bwr Buy with Risk | ≥ etf_h Hold | ≥ etf_av Avoid | else Sell Immediately.
A25: STEP 5 — Overrides (the loss-avoidance layer; ranks 1=Sell Immediately … 6=Strong Buy)
B26: OV Hard Sell (→ rank 1, always wins) | C26: Established: MA Cross = Death AND vs 200D < hs_est_v200 AND (1M % < hs_est_m1 OR 3M % < hs_est_m3). Early: MA Cross = Death AND vs 200D < hs_early_v200 AND 1M % < hs_early_m1 (Early gets a shorter leash).
B27: OV Below 200D (cap) | C27: vs 200D < 0 and no hard sell: Established capped at Hold (rank below200_cap_est); Early capped at Avoid (rank below200_cap_early). A stock under its 200D is never a buy.
B28: OV Insufficient history (cap Hold) | C28: History Days < hist_min.
B29: OV Extended (cap Hold) | C29: 1M % > ext_m1 OR vs 50D > ext_v50 OR RSI > ext_rsi → don't chase; wait for a pullback.
B30: OV Earnings (cap Hold) | C30: 0 ≤ Days to Earnings ≤ earn_days → no new entries into an earnings print.
B31: Final | C31: Final Rank = 1 if hard sell, else MIN(Base Rank, all active caps). Action = tier label for Final Rank. Flags lists the overrides that fired.
A32: NOTES FOR IMPLEMENTATION
B33: • Blank numeric cells must be treated as "no information" (0 points), never as 0 or as a large number — every formula wraps comparisons in ISNUMBER(). • MA Cross is matched on prefix ("Golden", "Death"). • Days to Earnings that are negative mean a stale date and are ignored. • The Parameters sheet values are starting points chosen so today's file gives a sensible spread; they are meant to be tuned by backtesting against the Fwd +1M/+3M/+6M % columns in the historical files. • Type is recomputed daily, so a company can migrate from Early to Established (e.g. once it turns profitable).

Sheet Parameters
A1: Parameter | B1: Value | C1: Meaning | E1: Tier rank | F1: Action label
A2: COMPANY TYPE (Established vs Early) | E2: 1 | F2: Sell Immediately
A3: mc_big | B3: 100000000000 | C3: Market Cap >= this → +2 establishment pts | E3: 2 | F3: Avoid
A4: mc_mid | B4: 20000000000 | C4: Market Cap >= this (but < mc_big) → +1 | E4: 3 | F4: Hold
A5: pm_est | B5: 5 | C5: Profit Margin % >= this (with positive Net Income) → +2; positive Net Income alone → +1 | E5: 4 | F5: Buy with Risk
A6: fm_est | B6: 5 | C6: FCF Margin % >= this (with positive FCF) → +1 | E6: 5 | F6: Buy
A7: pe_max | B7: 40 | C7: Forward P/E between 0 and this → +1 | E7: 6 | F7: Strong Buy
A8: q_est | B8: 7 | C8: Quality >= this → +1
A9: est_min | B9: 5 | C9: Establishment score >= this → Established, else Early (max score = 7) | E9: Blue/yellow cells are the editable thresholds. Every formula on the Scored Data sheet references these cells, so changing a value here re-scores every stock.
A10: mc_override | B10: 200000000000 | C10: Market Cap >= this → always Established regardless of score (e.g. TSLA)
A11: TECHNICAL SCORE (all types, range -10..+10)
A12: v200_hi | B12: 10 | C12: vs 200D MA % > this → +2; > 0 → +1
A13: v200_lo | B13: -10 | C13: vs 200D MA % < 0 and >= this → -1; < this → -2
A14: v50_lo | B14: -3 | C14: vs 50D MA % between v50_lo and v50_hi → +1 (healthy pullback / base)
A15: v50_hi | B15: 8
A16: v50_ext | B16: 15 | C16: vs 50D MA % > this → -1 (extended)
A17: v50_wk | B17: -8 | C17: vs 50D MA % < this → -1 (weak)
A18: rsi_lo | B18: 45 | C18: RSI between rsi_lo and rsi_hi → +1
A19: rsi_hi | B19: 65
A20: rsi_ob | B20: 72 | C20: RSI > this → -1 (overbought)
A21: rsi_os | B21: 35 | C21: RSI < this → -1 (oversold / broken)
A22: md_up | B22: 3 | C22: Momentum Delta (2 weeks) > this → +1
A23: md_dn | B23: -5 | C23: Momentum Delta (2 weeks) < this → -1
A24: mo_hi | B24: 7 | C24: Momentum score >= this → +1
A25: mo_lo | B25: 3 | C25: Momentum score <= this → -1
A26: vt_hi | B26: 10 | C26: Vol Trend % > this: +1 if 1M % > 0 (accumulation), -1 if 1M % < 0 (distribution)
A27: fh_near | B27: -10 | C27: % from 52W High > this → +1
A28: fh_deep | B28: -30 | C28: % from 52W High < this → -1
A29: FUNDAMENTAL SCORE – ESTABLISHED (range -5..+7)
A30: q_hi | B30: 8 | C30: Quality >= this → +2
A31: q_mid | B31: 6 | C31: Quality >= this → +1
A32: q_low | B32: 4 | C32: Quality <= this → -1
A33: eg_est | B33: 15 | C33: Earnings Growth % > this → +1; < 0 → -1
A34: rg_est | B34: 10 | C34: Revenue Growth % > this → +1; < 0 → -1
A35: peg_ok | B35: 1.5 | C35: PEG between 0 and this → +1
A36: peg_bad | B36: 3 | C36: PEG > this → -1 (negative PEG = 0 pts)
A37: fm_hi | B37: 10 | C37: FCF Margin % > this → +1; < 0 → -1
A38: FUNDAMENTAL SCORE – EARLY (range -7..+6)
A39: rg_e2 | B39: 30 | C39: Revenue Growth % > this → +2
A40: rg_e1 | B40: 15 | C40: Revenue Growth % > this → +1
A41: rg_e_lo | B41: 5 | C41: Revenue Growth % < this → -1; < 0 → -2
A42: gm_hi | B42: 50 | C42: Gross Margin % > this → +1
A43: gm_lo | B43: 25 | C43: Gross Margin % < this → -1
A44: fm_neg | B44: -20 | C44: FCF TTM > 0 → +1; else FCF Margin % < this → -1
A45: sf_hi | B45: 15 | C45: Short % Float > this → -1
A46: sf_vhi | B46: 25 | C46: Short % Float > this → -2
A47: q_e_hi | B47: 6 | C47: Quality >= this → +1
A48: q_e_lo | B48: 3 | C48: Quality <= this → -1
A49: COMPOSITE & TIERS
A50: early_fund_wt | B50: 0.5 | C50: Early: Composite = Tech + this × Fund (technicals dominate). Established: Tech + Fund. ETF: Tech only
A51: est_sb | B51: 13 | C51: Established: Composite >= this → Strong Buy
A52: est_b | B52: 9 | C52: Established: >= this → Buy
A53: est_bwr | B53: 5 | C53: Established: >= this → Buy with Risk
A54: est_h | B54: 0 | C54: Established: >= this → Hold
A55: est_av | B55: -5 | C55: Established: >= this → Avoid; below → Sell Immediately
A56: early_b | B56: 9 | C56: Early: >= this → Buy (Early is never Strong Buy)
A57: early_bwr | B57: 5 | C57: Early: >= this → Buy with Risk
A58: early_h | B58: 1 | C58: Early: >= this → Hold
A59: early_av | B59: -4 | C59: Early: >= this → Avoid; below → Sell Immediately
A60: etf_sb | B60: 8 | C60: ETF: Tech >= this → Strong Buy
A61: etf_b | B61: 5 | C61: ETF: >= this → Buy
... A64: etf_av | B64: -5 | C64: ETF: >= this → Avoid; below → Sell Immediately
A65: OVERRIDES (applied after base tier, in this order)
A66: hist_min | B66: 100 | C66: History Days < this → cap at Hold (not enough data to judge)
A67: hs_est_v200 | B67: -10 | C67: Established HARD SELL: Death cross AND vs 200D < this AND (1M % < hs_est_m1 OR 3M % < hs_est_m3)
A68: hs_est_m1 | B68: -8
A69: hs_est_m3 | B69: -15
A70: hs_early_v200 | B70: -5 | C70: Early HARD SELL: Death cross AND vs 200D < this AND 1M % < hs_early_m1
A71: hs_early_m1 | B71: -5
A72: below200_cap_est | B72: 3 | C72: vs 200D < 0 (no hard sell): Established capped at tier rank 3 (Hold)
A73: below200_cap_early | B73: 2 | C73: vs 200D < 0 (no hard sell): Early capped at tier rank 2 (Avoid)
A74: ext_m1 | B74: 25 | C74: EXTENDED: 1M % > this OR vs 50D > ext_v50 OR RSI > ext_rsi → cap at Hold (wait for pullback)
A75: ext_v50 | B75: 15
A76: ext_rsi | B76: 72
A77: earn_days | B77: 7 | C77: Next Earnings within this many calendar days → cap at Hold (no new entries into earnings)

Sheet Scored Data
A1: Symbol | B1: Overall | C1: Momentum | D1: Past Momentum (2 weeks) | E1: Momentum Delta (2 weeks) | F1: Quality | G1: Name | H1: Portfolios | I1: Price | J1: Currency | K1: Sector | L1: Market Cap | M1: Last Earnings | N1: Last Surprise % | O1: Next Earnings | P1: Next Est? | Q1: Today % | R1: Yesterday % | S1: 1W % | T1: 2W % | U1: 1M % | V1: 3M % | W1: 6M % | X1: 1Y % | Y1: Fwd +1M % | Z1: Fwd +3M % | AA1: Fwd +6M % | AB1: Fwd Since % | AC1: RS vs S&P % | AD1: % from 52W High | AE1: RSI | AF1: vs 50D MA % | AG1: vs 200D MA % | AH1: MA Cross | AI1: MACD Hist | AJ1: Vol Trend % | AK1: Earnings Growth % | AL1: Revenue Growth % | AM1: Profit Margin % | AN1: ROE % | AO1: Forward P/E | AP1: PEG | AQ1: Short % Float | AR1: History Days | AS1: Latest Data | AT1: Revenue TTM | AU1: Gross Profit TTM | AV1: Gross Margin % | AW1: Net Income TTM | AX1: FCF TTM | AY1: FCF Margin % | AZ1: Net Cash | BA1: % from 52W Low | BB1: 52W Range Pos % | BC1: Days to Earnings | BD1: Is ETF | BE1: Est Score | BF1: Company Type | BG1: T1 MA Cross | BH1: T2 vs 200D | BI1: T3 vs 50D | BJ1: T4 RSI | BK1: T5 Mom Delta | BL1: T6 Momentum | BM1: T7 Volume | BN1: T8 52W High | BO1: Tech Score | BP1: FE1 Quality | BQ1: FE2 Earn Growth | BR1: FE3 Rev Growth | BS1: FE4 PEG | BT1: FE5 FCF Margin | BU1: FE6 Net Cash | BV1: EA1 Rev Growth | BW1: EA2 Gross Margin | BX1: EA3 FCF | BY1: EA4 Profitable | BZ1: EA5 Short Float | CA1: EA6 Quality | CB1: Fund Score | CC1: Composite | CD1: Base Rank | CE1: OV Hist | CF1: OV Hard Sell | CG1: OV Below 200D | CH1: OV Extended | CI1: OV Earnings | CJ1: Final Rank | CK1: Action | CL1: Flags
A2: SKHY | B2: 10 | F2: 10 | G2: SK hynix Inc. American Depositary Receipt | H2: Memory | I2: 190.67 | J2: USD | K2: Technology | L2: 1409984769993 | M2: 46232 | N2: 86.04 | O2: 46323 | P2: estimated | Q2: -4.01 | R2: 7.05 | S2: 15.57 | T2: 20.66 | U2: 34.61 | AD2: -4.6 | AE2: 62.55 | AI2: 3.69 | AJ2: -0.65 | AK2: 1240.8 | AL2: 256.8 | AM2: 85.62 | AN2: 354.06 | AO2: 5.56 | AP2: 0.01 | AQ2: 0.4 | AR2: 44 | AS2: 46275 | AT2: 140924537488 | AU2: 107480027316 | AV2: 76.27 | AW2: 120657742722 | AX2: 41545003272 | AY2: 29.48 | AZ2: 26468371611 | BA2: 52.78 | BB2: 87.74 | BC2: =IF(AND(ISNUMBER(O2),ISNUMBER(AS2)),O2-AS2,"") -> 48 | BD2: =IF(OR(ISNUMBER(SEARCH("ETF",H2)),AND(F2="",AO2="")),1,0) -> 0 | BE2: =IF(ISNUMBER(L2),IF(L2>=Parameters!$B$3,2,IF(L2>=Parameters!$B$4,1,0)),0)+IF(ISNUMBER(AW2),IF(AW2>0,IF(AND(ISNUMBER(AM2),AM2>=Parameters!$B$5),2,1),0),0)+IF(ISNUMBER(AX2),IF(AND(AX2>0,ISNUMBER(AY2),AY2>=Parameters!$B$6),1,0),0)+IF(ISNUMBER(AO2),IF(AND(AO2>0,AO2<=Parameters!$B$7),1,0),0)+IF(ISNUMBER(F2),IF(F2>=Parameters!$B$8,1,0),0) -> 7 | BF2: =IF(BD2=1,"ETF",IF(OR(AND(ISNUMBER(L2),L2>=Parameters!$B$10),BE2>=Parameters!$B$9),"Established","Early")) -> Established | BG2: =IF(LEFT(AH2,6)="Golden",2,IF(LEFT(AH2,5)="Death",-2,0)) -> 0 | BH2: =IF(ISNUMBER(AG2),IF(AG2>Parameters!$B$12,2,IF(AG2>0,1,IF(AG2>=Parameters!$B$13,-1,-2))),0) -> 0 | BI2: =IF(ISNUMBER(AF2),IF(AND(AF2>=Parameters!$B$14,AF2<=Parameters!$B$15),1,IF(OR(AF2>Parameters!$B$16,AF2<Parameters!$B$17),-1,0)),0) -> 0 | BJ2: =IF(ISNUMBER(AE2),IF(AND(AE2>=Parameters!$B$18,AE2<=Parameters!$B$19),1,IF(OR(AE2>Parameters!$B$20,AE2<Parameters!$B$21),-1,0)),0) -> 1 | BK2: =IF(ISNUMBER(E2),IF(E2>Parameters!$B$22,1,IF(E2<Parameters!$B$23,-1,0)),0) -> 0 | BL2: =IF(ISNUMBER(C2),IF(C2>=Parameters!$B$24,1,IF(C2<=Parameters!$B$25,-1,0)),0) -> 0 | BM2: =IF(ISNUMBER(AJ2),IF(AND(AJ2>Parameters!$B$26,ISNUMBER(U2)),IF(U2<0,-1,1),0),0) -> 0 | BN2: =IF(ISNUMBER(AD2),IF(AD2>Parameters!$B$27,1,IF(AD2<Parameters!$B$28,-1,0)),0) -> 1 | BO2: =BG2+BH2+BI2+BJ2+BK2+BL2+BM2+BN2 -> 2 | BP2: =IF(ISNUMBER(F2),IF(F2>=Parameters!$B$30,2,IF(F2>=Parameters!$B$31,1,IF(F2<=Parameters!$B$32,-1,0))),0) -> 2 | BQ2: =IF(ISNUMBER(AK2),IF(AK2>Parameters!$B$33,1,IF(AK2<0,-1,0)),0) -> 1 | BR2: =IF(ISNUMBER(AL2),IF(AL2>Parameters!$B$34,1,IF(AL2<0,-1,0)),0) -> 1 | BS2: =IF(ISNUMBER(AP2),IF(AND(AP2>0,AP2<=Parameters!$B$35),1,IF(AP2>Parameters!$B$36,-1,0)),0) -> 1 | BT2: =IF(ISNUMBER(AY2),IF(AY2>Parameters!$B$37,1,IF(AY2<0,-1,0)),0) -> 1 | BU2: =IF(ISNUMBER(AZ2),IF(AZ2>0,1,0),0) -> 1 | BV2: =IF(ISNUMBER(AL2),IF(AL2>Parameters!$B$39,2,IF(AL2>Parameters!$B$40,1,IF(AL2<0,-2,IF(AL2<Parameters!$B$41,-1,0)))),0) -> 2 | BW2: =IF(ISNUMBER(AV2),IF(AV2>Parameters!$B$42,1,IF(AV2<Parameters!$B$43,-1,0)),0) -> 1 | BX2: =IF(AND(ISNUMBER(AX2),AX2>0),1,IF(AND(ISNUMBER(AY2),AY2<Parameters!$B$44),-1,0)) -> 1 | BY2: =IF(ISNUMBER(AW2),IF(AW2>0,1,0),0) -> 1 | BZ2: =IF(ISNUMBER(AQ2),IF(AQ2>Parameters!$B$46,-2,IF(AQ2>Parameters!$B$45,-1,0)),0) -> 0 | CA2: =IF(ISNUMBER(F2),IF(F2>=Parameters!$B$47,1,IF(F2<=Parameters!$B$48,-1,0)),0) -> 1 | CB2: =IF(BF2="Established",BP2+BQ2+BR2+BS2+BT2+BU2,IF(BF2="Early",BV2+BW2+BX2+BY2+BZ2+CA2,0)) -> 7 | CC2: =IF(BF2="Established",BO2+CB2,IF(BF2="Early",BO2+Parameters!$B$50*CB2,BO2)) -> 9 | CD2: =IF(BF2="Established",IF(CC2>=Parameters!$B$51,6,IF(CC2>=Parameters!$B$52,5,IF(CC2>=Parameters!$B$53,4,IF(CC2>=Parameters!$B$54,3,IF(CC2>=Parameters!$B$55,2,1))))),IF(BF2="Early",IF(CC2>=Parameters!$B$56,5,IF(CC2>=Parameters!$B$57,4,IF(CC2>=Parameters!$B$58,3,IF(CC2>=Parameters!$B$59,2,1)))),IF(CC2>=Parameters!$B$60,6,IF(CC2>=Parameters!$B$61,5,IF(CC2>=Parameters!$B$62,4,IF(CC2>=Parameters!$B$63,3,IF(CC2>=Parameters!$B$64,2,1))))))) -> 5 | CE2: =IF(AND(ISNUMBER(AR2),AR2<Parameters!$B$66),1,0) -> 1 | CF2: =IF(AND(LEFT(AH2,5)="Death",ISNUMBER(AG2)),IF(BF2="Early",IF(AND(AG2<Parameters!$B$70,ISNUMBER(U2),U2<Parameters!$B$71),1,0),IF(AND(AG2<Parameters!$B$67,OR(AND(ISNUMBER(U2),U2<Parameters!$B$68),AND(ISNUMBER(V2),V2<Parameters!$B$69))),1,0)),0) -> 0 | CG2: =IF(AND(ISNUMBER(AG2),AG2<0),1,0) -> 0 | CH2: =IF(OR(AND(ISNUMBER(U2),U2>Parameters!$B$74),AND(ISNUMBER(AF2),AF2>Parameters!$B$75),AND(ISNUMBER(AE2),AE2>Parameters!$B$76)),1,0) -> 1 | CI2: =IF(AND(ISNUMBER(BC2),BC2>=0,BC2<=Parameters!$B$77),1,0) -> 0 | CJ2: =IF(CF2=1,1,MIN(CD2,IF(CE2=1,3,6),IF(CG2=1,IF(BF2="Early",Parameters!$B$73,Parameters!$B$72),6),IF(CH2=1,3,6),IF(CI2=1,3,6))) -> 3 | CK2: =INDEX(Parameters!$F$2:$F$7,CJ2) -> Hold | CL2: =IF(CF2=1,"Hard sell: breakdown; ","")&IF(CE2=1,"Insufficient history; ","")&IF(AND(CF2=0,CG2=1),"Below 200D; ","")&IF(CH2=1,"Extended - wait for pullback; ","")&IF(CI2=1,"Earnings within "&Parameters!$B$77&"d; ","") -> Insufficient history; Extended - wait for pullback;
A3: MU | B3: 8 | C3: 7 | D3: 67.2 | E3: 3.7 | F3: 10 | G3: Micron Technology, Inc. | H3: Chips; Memory | I3: 979.59 | J3: USD | K3: Technology | L3: 1160756421391 | M3: 46197 | N3: 21.36 | O3: 46288 | P3: estimated | Q3: -4.69 | R3: 2.75 | S3: 2.46 | T3: 4.39 | U3: 12.79 | V3: 9.83 | W3: 133.97 | X3: 624.33 | AC3: 5.19 | AD3: -21.95 | AE3: 53.57 | AF3: 5.36 | AG3: 58.45 | AH3: Golden | AI3: 6.23 | AJ3: -13.69 | AK3: 1398.3 | AL3: 345.7 | AM3: 55.91 | AN3: 66.64 | AO3: 6.62 | AP3: 0.02 | AQ3: 2.67 | AR3: 300 | AS3: 46275 | AT3: 90273996800 | AU3: 65510998016 | AV3: 72.57 | AW3: 50468999168 | AX3: 7639499776 | AY3: 8.46 | AZ3: 19646000640 | BA3: 608.1 | BB3: 75.34 | BC3: =IF(AND(ISNUMBER(O3),ISNUMBER(AS3)),O3-AS3,"") -> 13 | BD3: =IF(OR(ISNUMBER(SEARCH("ETF",H3)),AND(F3="",AO3="")),1,0) -> 0 | BE3: =IF(ISNUMBER(L3),IF(L3>=Parameters!$B$3,2,IF(L3>=Parameters!$B$4,1,0)),0)+IF(ISNUMBER(AW3),IF(AW3>0,IF(AND(ISNUMBER(AM3),AM3>=Parameters!$B$5),2,1),0),0)+IF(ISNUMBER(AX3),IF(AND(AX3>0,ISNUMBER(AY3),AY3>=Parameters!$B$6),1,0),0)+IF(ISNUMBER(AO3),IF(AND(AO3>0,AO3<=Parameters!$B$7),1,0),0)+IF(ISNUMBER(F3),IF(F3>=Parameters!$B$8,1,0),0) -> 7 | BF3: =IF(BD3=1,"ETF",IF(OR(AND(ISNUMBER(L3),L3>=Parameters!$B$10),BE3>=Parameters!$B$9),"Established","Early")) -> Established | BG3: =IF(LEFT(AH3,6)="Golden",2,IF(LEFT(AH3,5)="Death",-2,0)) -> 2 | BH3: =IF(ISNUMBER(AG3),IF(AG3>Parameters!$B$12,2,IF(AG3>0,1,IF(AG3>=Parameters!$B$13,-1,-2))),0) -> 2 | BI3: =IF(ISNUMBER(AF3),IF(AND(AF3>=Parameters!$B$14,AF3<=Parameters!$B$15),1,IF(OR(AF3>Parameters!$B$16,AF3<Parameters!$B$17),-1,0)),0) -> 1 | BJ3: =IF(ISNUMBER(AE3),IF(AND(AE3>=Parameters!$B$18,AE3<=Parameters!$B$19),1,IF(OR(AE3>Parameters!$B$20,AE3<Parameters!$B$21),-1,0)),0) -> 1 | BK3: =IF(ISNUMBER(E3),IF(E3>Parameters!$B$22,1,IF(E3<Parameters!$B$23,-1,0)),0) -> 1 | BL3: =IF(ISNUMBER(C3),IF(C3>=Parameters!$B$24,1,IF(C3<=Parameters!$B$25,-1,0)),0) -> 1 | BM3: =IF(ISNUMBER(AJ3),IF(AND(AJ3>Parameters!$B$26,ISNUMBER(U3)),IF(U3<0,-1,1),0),0) -> 0 | BN3: =IF(ISNUMBER(AD3),IF(AD3>Parameters!$B$27,1,IF(AD3<Parameters!$B$28,-1,0)),0) -> 0 | BO3: =BG3+BH3+BI3+BJ3+BK3+BL3+BM3+BN3 -> 8 | BP3: =IF(ISNUMBER(F3),IF(F3>=Parameters!$B$30,2,IF(F3>=Parameters!$B$31,1,IF(F3<=Parameters!$B$32,-1,0))),0) -> 2 | BQ3: =IF(ISNUMBER(AK3),IF(AK3>Parameters!$B$33,1,IF(AK3<0,-1,0)),0) -> 1 | BR3: =IF(ISNUMBER(AL3),IF(AL3>Parameters!$B$34,1,IF(AL3<0,-1,0)),0) -> 1 | BS3: =IF(ISNUMBER(AP3),IF(AND(AP3>0,AP3<=Parameters!$B$35),1,IF(AP3>Parameters!$B$36,-1,0)),0) -> 1 | BT3: =IF(ISNUMBER(AY3),IF(AY3>Parameters!$B$37,1,IF(AY3<0,-1,0)),0) -> 0 | BU3: =IF(ISNUMBER(AZ3),IF(AZ3>0,1,0),0) -> 1 | BV3: =IF(ISNUMBER(AL3),IF(AL3>Parameters!$B$39,2,IF(AL3>Parameters!$B$40,1,IF(AL3<0,-2,IF(AL3<Parameters!$B$41,-1,0)))),0) -> 2 | BW3: =IF(ISNUMBER(AV3),IF(AV3>Parameters!$B$42,1,IF(AV3<Parameters!$B$43,-1,0)),0) -> 1 | BX3: =IF(AND(ISNUMBER(AX3),AX3>0),1,IF(AND(ISNUMBER(AY3),AY3<Parameters!$B$44),-1,0)) -> 1 | BY3: =IF(ISNUMBER(AW3),IF(AW3>0,1,0),0) -> 1 | BZ3: =IF(ISNUMBER(AQ3),IF(AQ3>Parameters!$B$46,-2,IF(AQ3>Parameters!$B$45,-1,0)),0) -> 0 | CA3: =IF(ISNUMBER(F3),IF(F3>=Parameters!$B$47,1,IF(F3<=Parameters!$B$48,-1,0)),0) -> 1 | CB3: =IF(BF3="Established",BP3+BQ3+BR3+BS3+BT3+BU3,IF(BF3="Early",BV3+BW3+BX3+BY3+BZ3+CA3,0)) -> 6 | CC3: =IF(BF3="Established",BO3+CB3,IF(BF3="Early",BO3+Parameters!$B$50*CB3,BO3)) -> 14 | CD3: =IF(BF3="Established",IF(CC3>=Parameters!$B$51,6,IF(CC3>=Parameters!$B$52,5,IF(CC3>=Parameters!$B$53,4,IF(CC3>=Parameters!$B$54,3,IF(CC3>=Parameters!$B$55,2,1))))),IF(BF3="Early",IF(CC3>=Parameters!$B$56,5,IF(CC3>=Parameters!$B$57,4,IF(CC3>=Parameters!$B$58,3,IF(CC3>=Parameters!$B$59,2,1)))),IF(CC3>=Parameters!$B$60,6,IF(CC3>=Parameters!$B$61,5,IF(CC3>=Parameters!$B$62,4,IF(CC3>=Parameters!$B$63,3,IF(CC3>=Parameters!$B$64,2,1))))))) -> 6 | CE3: =IF(AND(ISNUMBER(AR3),AR3<Parameters!$B$66),1,0) -> 0 | CF3: =IF(AND(LEFT(AH3,5)="Death",ISNUMBER(AG3)),IF(BF3="Early",IF(AND(AG3<Parameters!$B$70,ISNUMBER(U3),U3<Parameters!$B$71),1,0),IF(AND(AG3<Parameters!$B$67,OR(AND(ISNUMBER(U3),U3<Parameters!$B$68),AND(ISNUMBER(V3),V3<Parameters!$B$69))),1,0)),0) -> 0 | CG3: =IF(AND(ISNUMBER(AG3),AG3<0),1,0) -> 0 | CH3: =IF(OR(AND(ISNUMBER(U3),U3>Parameters!$B$74),AND(ISNUMBER(AF3),AF3>Parameters!$B$75),AND(ISNUMBER(AE3),AE3>Parameters!$B$76)),1,0) -> 0 | CI3: =IF(AND(ISNUMBER(BC3),BC3>=0,BC3<=Parameters!$B$77),1,0) -> 0 | CJ3: =IF(CF3=1,1,MIN(CD3,IF(CE3=1,3,6),IF(CG3=1,IF(BF3="Early",Parameters!$B$73,Parameters!$B$72),6),IF(CH3=1,3,6),IF(CI3=1,3,6))) -> 6 | CK3: =INDEX(Parameters!$F$2:$F$7,CJ3) -> Strong Buy | CL3: =IF(CF3=1,"Hard sell: breakdown; ","")&IF(CE3=1,"Insufficient history; ","")&IF(AND(CF3=0,CG3=1),"Below 200D; ","")&IF(CH3=1,"Extended - wait for pullback; ","")&IF(CI3=1,"Earnings within "&Parameters!$B$77&"d; ","")
A4: JPM | B4: 8 | C4: 8 | D4: 68.5 | E4: 4.2 | F4: 10 | G4: JPMorgan Chase & Co. | H4: Fin | I4: 352.78 | J4: USD | K4: Financial Services | L4: 942885198646 | M4: 46226 | N4: 6.02 | O4: 46307 | Q4: -0.54 | R4: 0.34 | S4: -0.97 | T4: -1.04 | U4: -2.56 | V4: 14.12 | W4: 22.7 | X4: 18.44 | AC4: 9.48 | AD4: -3.74 | AE4: 47.2 | AF4: 0.43 | AG4: 10.54 | AH4: Golden (62d) | AI4: -1.01 | AJ4: -16.54 | AK4: 41.2 | AL4: 30.4 | AM4: 34.15 | AN4: 17.79 | AO4: 14.25 | AP4: 0.33 | AQ4: 0.96 | AR4: 300 | AS4: 46275 | AT4: 186328006656 | AU4: 186328006656 | AV4: 100 | AW4: 63634001920 | AX4: 55681000000 | AY4: 29.88 | AZ4: 183112040448 | BA4: 26.4 | BB4: 84.3 | BC4: =IF(AND(ISNUMBER(O4),ISNUMBER(AS4)),O4-AS4,"") -> 32 | BD4: =IF(OR(ISNUMBER(SEARCH("ETF",H4)),AND(F4="",AO4="")),1,0) -> 0 | BE4: =IF(ISNUMBER(L4),IF(L4>=Parameters!$B$3,2,IF(L4>=Parameters!$B$4,1,0)),0)+IF(ISNUMBER(AW4),IF(AW4>0,IF(AND(ISNUMBER(AM4),AM4>=Parameters!$B$5),2,1),0),0)+IF(ISNUMBER(AX4),IF(AND(AX4>0,ISNUMBER(AY4),AY4>=Parameters!$B$6),1,0),0)+IF(ISNUMBER(AO4),IF(AND(AO4>0,AO4<=Parameters!$B$7),1,0),0)+IF(ISNUMBER(F4),IF(F4>=Parameters!$B$8,1,0),0) -> 7 | BF4: =IF(BD4=1,"ETF",IF(OR(AND(ISNUMBER(L4),L4>=Parameters!$B$10),BE4>=Parameters!$B$9),"Established","Early")) -> Established | BG4: =IF(LEFT(AH4,6)="Golden",2,IF(LEFT(AH4,5)="Death",-2,0)) -> 2 | BH4: =IF(ISNUMBER(AG4),IF(AG4>Parameters!$B$12,2,IF(AG4>0,1,IF(AG4>=Parameters!$B$13,-1,-2))),0) -> 2 | BI4: =IF(ISNUMBER(AF4),IF(AND(AF4>=Parameters!$B$14,AF4<=Parameters!$B$15),1,IF(OR(AF4>Parameters!$B$16,AF4<Parameters!$B$17),-1,0)),0) -> 1 | BJ4: =IF(ISNUMBER(AE4),IF(AND(AE4>=Parameters!$B$18,AE4<=Parameters!$B$19),1,IF(OR(AE4>Parameters!$B$20,AE4<Parameters!$B$21),-1,0)),0) -> 1 | BK4: =IF(ISNUMBER(E4),IF(E4>Parameters!$B$22,1,IF(E4<Parameters!$B$23,-1,0)),0) -> 1 | BL4: =IF(ISNUMBER(C4),IF(C4>=Parameters!$B$24,1,IF(C4<=Parameters!$B$25,-1,0)),0) -> 1 | BM4: =IF(ISNUMBER(AJ4),IF(AND(AJ4>Parameters!$B$26,ISNUMBER(U4)),IF(U4<0,-1,1),0),0) -> 0 | BN4: =IF(ISNUMBER(AD4),IF(AD4>Parameters!$B$27,1,IF(AD4<Parameters!$B$28,-1,0)),0) -> 1 | BO4: =BG4+BH4+BI4+BJ4+BK4+BL4+BM4+BN4 -> 9 | BP4: =IF(ISNUMBER(F4),IF(F4>=Parameters!$B$30,2,IF(F4>=Parameters!$B$31,1,IF(F4<=Parameters!$B$32,-1,0))),0) -> 2 | BQ4: =IF(ISNUMBER(AK4),IF(AK4>Parameters!$B$33,1,IF(AK4<0,-1,0)),0) -> 1 | BR4: =IF(ISNUMBER(AL4),IF(AL4>Parameters!$B$34,1,IF(AL4<0,-1,0)),0) -> 1 | BS4: =IF(ISNUMBER(AP4),IF(AND(AP4>0,AP4<=Parameters!$B$35),1,IF(AP4>Parameters!$B$36,-1,0)),0) -> 1 | BT4: =IF(ISNUMBER(AY4),IF(AY4>Parameters!$B$37,1,IF(AY4<0,-1,0)),0) -> 1 | BU4: =IF(ISNUMBER(AZ4),IF(AZ4>0,1,0),0) -> 1 | BV4: =IF(ISNUMBER(AL4),IF(AL4>Parameters!$B$39,2,IF(AL4>Parameters!$B$40,1,IF(AL4<0,-2,IF(AL4<Parameters!$B$41,-1,0)))),0) -> 2 | BW4: =IF(ISNUMBER(AV4),IF(AV4>Parameters!$B$42,1,IF(AV4<Parameters!$B$43,-1,0)),0) -> 1 | BX4: =IF(AND(ISNUMBER(AX4),AX4>0),1,IF(AND(ISNUMBER(AY4),AY4<Parameters!$B$44),-1,0)) -> 1 | BY4: =IF(ISNUMBER(AW4),IF(AW4>0,1,0),0) -> 1 | BZ4: =IF(ISNUMBER(AQ4),IF(AQ4>Parameters!$B$46,-2,IF(AQ4>Parameters!$B$45,-1,0)),0) -> 0 | CA4: =IF(ISNUMBER(F4),IF(F4>=Parameters!$B$47,1,IF(F4<=Parameters!$B$48,-1,0)),0) -> 1 | CB4: =IF(BF4="Established",BP4+BQ4+BR4+BS4+BT4+BU4,IF(BF4="Early",BV4+BW4+BX4+BY4+BZ4+CA4,0)) -> 7 | CC4: =IF(BF4="Established",BO4+CB4,IF(BF4="Early",BO4+Parameters!$B$50*CB4,BO4)) -> 16 | CD4: =IF(BF4="Established",IF(CC4>=Parameters!$B$51,6,IF(CC4>=Parameters!$B$52,5,IF(CC4>=Parameters!$B$53,4,IF(CC4>=Parameters!$B$54,3,IF(CC4>=Parameters!$B$55,2,1))))),IF(BF4="Early",IF(CC4>=Parameters!$B$56,5,IF(CC4>=Parameters!$B$57,4,IF(CC4>=Parameters!$B$58,3,IF(CC4>=Parameters!$B$59,2,1)))),IF(CC4>=Parameters!$B$60,6,IF(CC4>=Parameters!$B$61,5,IF(CC4>=Parameters!$B$62,4,IF(CC4>=Parameters!$B$63,3,IF(CC4>=Parameters!$B$64,2,1))))))) -> 6 | CE4: =IF(AND(ISNUMBER(AR4),AR4<Parameters!$B$66),1,0) -> 0 | CF4: =IF(AND(LEFT(AH4,5)="Death",ISNUMBER(AG4)),IF(BF4="Early",IF(AND(AG4<Parameters!$B$70,ISNUMBER(U4),U4<Parameters!$B$71),1,0),IF(AND(AG4<Parameters!$B$67,OR(AND(ISNUMBER(U4),U4<Parameters!$B$68),AND(ISNUMBER(V4),V4<Parameters!$B$69))),1,0)),0) -> 0 | CG4: =IF(AND(ISNUMBER(AG4),AG4<0),1,0) -> 0 | CH4: =IF(OR(AND(ISNUMBER(U4),U4>Parameters!$B$74),AND(ISNUMBER(AF4),AF4>Parameters!$B$75),AND(ISNUMBER(AE4),AE4>Parameters!$B$76)),1,0) -> 0 | CI4: =IF(AND(ISNUMBER(BC4),BC4>=0,BC4<=Parameters!$B$77),1,0) -> 0 | CJ4: =IF(CF4=1,1,MIN(CD4,IF(CE4=1,3,6),IF(CG4=1,IF(BF4="Early",Parameters!$B$73,Parameters!$B$72),6),IF(CH4=1,3,6),IF(CI4=1,3,6))) -> 6 | CK4: =INDEX(Parameters!$F$2:$F$7,CJ4) -> Strong Buy | CL4: =IF(CF4=1,"Hard sell: breakdown; ","")&IF(CE4=1,"Insufficient history; ","")&IF(AND(CF4=0,CG4=1),"Below 200D; ","")&IF(CH4=1,"Extended - wait for pullback; ","")&IF(CI4=1,"Earnings within "&Parameters!$B$77&"d; ","")
A5: DELL | B5: 8 | C5: 8 | D5: 81.6 | E5: 0.5 | F5: 8 | G5: Dell Technologies Inc. Class C Common Stock | H5: Hardware | I5: 515.23 | J5: USD | K5: Technology | L5: 345847734587 | M5: 46266 | N5: 43.09 | O5: 46357 | P5: estimated | Q5: -3.74 | R5: 0.26 | S5: 4.68 | T5: 11.08 | U5: 16.84 | V5: 39.31 | W5: 249.61 | X5: 324.79 | AC5: 34.67 | AD5: -8.48 | AE5: 59.76 | AF5: 15.46 | AG5: 98.49 | AH5: Golden | AI5: 6.27 | AJ5: 10.66 | AK5: 255.1 | AL5: 57.7 | AM5: 7.53 | AN5: -240.32 | AO5: 18.38 | AP5: 0.11 | AQ5: 4.65 | AR5: 300 | AS5: 46275 | AT5: 151197007872 | AU5: 30076999680 | AV5: 19.89 | AW5: 11377999872 | AX5: 173500000 | AY5: 0.11 | AZ5: -22897000448 | BA5: 367.45 | BB5: 89.45 | BC5: =IF(AND(ISNUMBER(O5),ISNUMBER(AS5)),O5-AS5,"") -> 82 | BD5: =IF(OR(ISNUMBER(SEARCH("ETF",H5)),AND(F5="",AO5="")),1,0) -> 0 | BE5: =IF(ISNUMBER(L5),IF(L5>=Parameters!$B$3,2,IF(L5>=Parameters!$B$4,1,0)),0)+IF(ISNUMBER(AW5),IF(AW5>0,IF(AND(ISNUMBER(AM5),AM5>=Parameters!$B$5),2,1),0),0)+IF(ISNUMBER(AX5),IF(AND(AX5>0,ISNUMBER(AY5),AY5>=Parameters!$B$6),1,0),0)+IF(ISNUMBER(AO5),IF(AND(AO5>0,AO5<=Parameters!$B$7),1,0),0)+IF(ISNUMBER(F5),IF(F5>=Parameters!$B$8,1,0),0) -> 6 | BF5: =IF(BD5=1,"ETF",IF(OR(AND(ISNUMBER(L5),L5>=Parameters!$B$10),BE5>=Parameters!$B$9),"Established","Early")) -> Established | BG5: =IF(LEFT(AH5,6)="Golden",2,IF(LEFT(AH5,5)="Death",-2,0)) -> 2 | BH5: =IF(ISNUMBER(AG5),IF(AG5>Parameters!$B$12,2,IF(AG5>0,1,IF(AG5>=Parameters!$B$13,-1,-2))),0) -> 2 | BI5: =IF(ISNUMBER(AF5),IF(AND(AF5>=Parameters!$B$14,AF5<=Parameters!$B$15),1,IF(OR(AF5>Parameters!$B$16,AF5<Parameters!$B$17),-1,0)),0) -> -1 | BJ5: =IF(ISNUMBER(AE5),IF(AND(AE5>=Parameters!$B$18,AE5<=Parameters!$B$19),1,IF(OR(AE5>Parameters!$B$20,AE5<Parameters!$B$21),-1,0)),0) -> 1 | BK5: =IF(ISNUMBER(E5),IF(E5>Parameters!$B$22,1,IF(E5<Parameters!$B$23,-1,0)),0) -> 0 | BL5: =IF(ISNUMBER(C5),IF(C5>=Parameters!$B$24,1,IF(C5<=Parameters!$B$25,-1,0)),0) -> 1 | BM5: =IF(ISNUMBER(AJ5),IF(AND(AJ5>Parameters!$B$26,ISNUMBER(U5)),IF(U5<0,-1,1),0),0) -> 1 | BN5: =IF(ISNUMBER(AD5),IF(AD5>Parameters!$B$27,1,IF(AD5<Parameters!$B$28,-1,0)),0) -> 1 | BO5: =BG5+BH5+BI5+BJ5+BK5+BL5+BM5+BN5 -> 7 | BP5: =IF(ISNUMBER(F5),IF(F5>=Parameters!$B$30,2,IF(F5>=Parameters!$B$31,1,IF(F5<=Parameters!$B$32,-1,0))),0) -> 2 | BQ5: =IF(ISNUMBER(AK5),IF(AK5>Parameters!$B$33,1,IF(AK5<0,-1,0)),0) -> 1 | BR5: =IF(ISNUMBER(AL5),IF(AL5>Parameters!$B$34,1,IF(AL5<0,-1,0)),0) -> 1 | BS5: =IF(ISNUMBER(AP5),IF(AND(AP5>0,AP5<=Parameters!$B$35),1,IF(AP5>Parameters!$B$36,-1,0)),0) -> 1 | BT5: =IF(ISNUMBER(AY5),IF(AY5>Parameters!$B$37,1,IF(AY5<0,-1,0)),0) -> 0 | BU5: =IF(ISNUMBER(AZ5),IF(AZ5>0,1,0),0) -> 0 | BV5: =IF(ISNUMBER(AL5),IF(AL5>Parameters!$B$39,2,IF(AL5>Parameters!$B$40,1,IF(AL5<0,-2,IF(AL5<Parameters!$B$41,-1,0)))),0) -> 2 | BW5: =IF(ISNUMBER(AV5),IF(AV5>Parameters!$B$42,1,IF(AV5<Parameters!$B$43,-1,0)),0) -> -1 | BX5: =IF(AND(ISNUMBER(AX5),AX5>0),1,IF(AND(ISNUMBER(AY5),AY5<Parameters!$B$44),-1,0)) -> 1 | BY5: =IF(ISNUMBER(AW5),IF(AW5>0,1,0),0) -> 1 | BZ5: =IF(ISNUMBER(AQ5),IF(AQ5>Parameters!$B$46,-2,IF(AQ5>Parameters!$B$45,-1,0)),0) -> 0 | CA5: =IF(ISNUMBER(F5),IF(F5>=Parameters!$B$47,1,IF(F5<=Parameters!$B$48,-1,0)),0) -> 1 | CB5: =IF(BF5="Established",BP5+BQ5+BR5+BS5+BT5+BU5,IF(BF5="Early",BV5+BW5+BX5+BY5+BZ5+CA5,0)) -> 5 | CC5: =IF(BF5="Established",BO5+CB5,IF(BF5="Early",BO5+Parameters!$B$50*CB5,BO5)) -> 12 | CD5: =IF(BF5="Established",IF(CC5>=Parameters!$B$51,6,IF(CC5>=Parameters!$B$52,5,IF(CC5>=Parameters!$B$53,4,IF(CC5>=Parameters!$B$54,3,IF(CC5>=Parameters!$B$55,2,1))))),IF(BF5="Early",IF(CC5>=Parameters!$B$56,5,IF(CC5>=Parameters!$B$57,4,IF(CC5>=Parameters!$B$58,3,IF(CC5>=Parameters!$B$59,2,1)))),IF(CC5>=Parameters!$B$60,6,IF(CC5>=Parameters!$B$61,5,IF(CC5>=Parameters!$B$62,4,IF(CC5>=Parameters!$B$63,3,IF(CC5>=Parameters!$B$64,2,1))))))) -> 5 | CE5: =IF(AND(ISNUMBER(AR5),AR5<Parameters!$B$66),1,0) -> 0 | CF5: =IF(AND(LEFT(AH5,5)="Death",ISNUMBER(AG5)),IF(BF5="Early",IF(AND(AG5<Parameters!$B$70,ISNUMBER(U5),U5<Parameters!$B$71),1,0),IF(AND(AG5<Parameters!$B$67,OR(AND(ISNUMBER(U5),U5<Parameters!$B$68),AND(ISNUMBER(V5),V5<Parameters!$B$69))),1,0)),0) -> 0 | CG5: =IF(AND(ISNUMBER(AG5),AG5<0),1,0) -> 0 | CH5: =IF(OR(AND(ISNUMBER(U5),U5>Parameters!$B$74),AND(ISNUMBER(AF5),AF5>Parameters!$B$75),AND(ISNUMBER(AE5),AE5>Parameters!$B$76)),1,0) -> 1 | CI5: =IF(AND(ISNUMBER(BC5),BC5>=0,BC5<=Parameters!$B$77),1,0) -> 0 | CJ5: =IF(CF5=1,1,MIN(CD5,IF(CE5=1,3,6),IF(CG5=1,IF(BF5="Early",Parameters!$B$73,Parameters!$B$72),6),IF(CH5=1,3,6),IF(CI5=1,3,6))) -> 3 | CK5: =INDEX(Parameters!$F$2:$F$7,CJ5) -> Hold | CL5: =IF(CF5=1,"Hard sell: breakdown; ","")&IF(CE5=1,"Insufficient history; ","")&IF(AND(CF5=0,CG5=1),"Below 200D; ","")&IF(CH5=1,"Extended - wait for pullback; ","")&IF(CI5=1,"Earnings within "&Parameters!$B$77&"d; ","") -> Extended - wait for pullback;
A6: STX | B6: 8 | C6: 7 | D6: 66.6 | E6: 3.4 | F6: 10 | G6: Seagate Technology Holdings plc | H6: Memory | I6: 854.39 | J6: USD | K6: Technology | L6: 200788906853 | M6: 46231 | N6: 2.3 | O6: 46322 | P6: estimated | Q6: -3.56 | R6: -2.04 | S6: 5.67 | T6: 0.95 | U6: 4.13 | V6: 4.71 | W6: 121.36 | X6: 345.95 | AC6: 0.06 | AD6: -25.38 | AE6: 50.35 | AF6: 0.55 | AG6: 41.72 | AH6: Golden | AI6: 4.37 | AJ6: -17.35 | AK6: 165.2 | AL6: 48.5 | AM6: 26.11 | AN6: 371.53 | AO6: 16.04 | AP6: 0.43 | AQ6: 3.61 | AR6: 300 | AS6: 46275 | AT6: 12195000320 | AU6: 5558000128 | AV6: 45.58 | AW6: 3184000000 | AX6: 1943750016 | AY6: 15.94 | AZ6: -2193999872 | BA6: 349.92 | BB6: 69.57 | BC6: =IF(AND(ISNUMBER(O6),ISNUMBER(AS6)),O6-AS6,"") -> 47 | BD6: =IF(OR(ISNUMBER(SEARCH("ETF",H6)),AND(F6="",AO6="")),1,0) -> 0 | BE6: =IF(ISNUMBER(L6),IF(L6>=Parameters!$B$3,2,IF(L6>=Parameters!$B$4,1,0)),0)+IF(ISNUMBER(AW6),IF(AW6>0,IF(AND(ISNUMBER(AM6),AM6>=Parameters!$B$5),2,1),0),0)+IF(ISNUMBER(AX6),IF(AND(AX6>0,ISNUMBER(AY6),AY6>=Parameters!$B$6),1,0),0)+IF(ISNUMBER(AO6),IF(AND(AO6>0,AO6<=Parameters!$B$7),1,0),0)+IF(ISNUMBER(F6),IF(F6>=Parameters!$B$8,1,0),0) -> 7 | BF6: =IF(BD6=1,"ETF",IF(OR(AND(ISNUMBER(L6),L6>=Parameters!$B$10),BE6>=Parameters!$B$9),"Established","Early")) -> Established | BG6: =IF(LEFT(AH6,6)="Golden",2,IF(LEFT(AH6,5)="Death",-2,0)) -> 2 | BH6: =IF(ISNUMBER(AG6),IF(AG6>Parameters!$B$12,2,IF(AG6>0,1,IF(AG6>=Parameters!$B$13,-1,-2))),0) -> 2 | BI6: =IF(ISNUMBER(AF6),IF(AND(AF6>=Parameters!$B$14,AF6<=Parameters!$B$15),1,IF(OR(AF6>Parameters!$B$16,AF6<Parameters!$B$17),-1,0)),0) -> 1 | BJ6: =IF(ISNUMBER(AE6),IF(AND(AE6>=Parameters!$B$18,AE6<=Parameters!$B$19),1,IF(OR(AE6>Parameters!$B$20,AE6<Parameters!$B$21),-1,0)),0) -> 1 | BK6: =IF(ISNUMBER(E6),IF(E6>Parameters!$B$22,1,IF(E6<Parameters!$B$23,-1,0)),0) -> 1 | BL6: =IF(ISNUMBER(C6),IF(C6>=Parameters!$B$24,1,IF(C6<=Parameters!$B$25,-1,0)),0) -> 1 | BM6: =IF(ISNUMBER(AJ6),IF(AND(AJ6>Parameters!$B$26,ISNUMBER(U6)),IF(U6<0,-1,1),0),0) -> 0 | BN6: =IF(ISNUMBER(AD6),IF(AD6>Parameters!$B$27,1,IF(AD6<Parameters!$B$28,-1,0)),0) -> 0 | BO6: =BG6+BH6+BI6+BJ6+BK6+BL6+BM6+BN6 -> 8 | BP6: =IF(ISNUMBER(F6),IF(F6>=Parameters!$B$30,2,IF(F6>=Parameters!$B$31,1,IF(F6<=Parameters!$B$32,-1,0))),0) -> 2 | BQ6: =IF(ISNUMBER(AK6),IF(AK6>Parameters!$B$33,1,IF(AK6<0,-1,0)),0) -> 1 | BR6: =IF(ISNUMBER(AL6),IF(AL6>Parameters!$B$34,1,IF(AL6<0,-1,0)),0) -> 1 | BS6: =IF(ISNUMBER(AP6),IF(AND(AP6>0,AP6<=Parameters!$B$35),1,IF(AP6>Parameters!$B$36,-1,0)),0) -> 1 | BT6: =IF(ISNUMBER(AY6),IF(AY6>Parameters!$B$37,1,IF(AY6<0,-1,0)),0) -> 1 | BU6: =IF(ISNUMBER(AZ6),IF(AZ6>0,1,0),0) -> 0 | BV6: =IF(ISNUMBER(AL6),IF(AL6>Parameters!$B$39,2,IF(AL6>Parameters!$B$40,1,IF(AL6<0,-2,IF(AL6<Parameters!$B$41,-1,0)))),0) -> 2 | BW6: =IF(ISNUMBER(AV6),IF(AV6>Parameters!$B$42,1,IF(AV6<Parameters!$B$43,-1,0)),0) -> 0 | BX6: =IF(AND(ISNUMBER(AX6),AX6>0),1,IF(AND(ISNUMBER(AY6),AY6<Parameters!$B$44),-1,0)) -> 1 | BY6: =IF(ISNUMBER(AW6),IF(AW6>0,1,0),0) -> 1 | BZ6: =IF(ISNUMBER(AQ6),IF(AQ6>Parameters!$B$46,-2,IF(AQ6>Parameters!$B$45,-1,0)),0) -> 0 | CA6: =IF(ISNUMBER(F6),IF(F6>=Parameters!$B$47,1,IF(F6<=Parameters!$B$48,-1,0)),0) -> 1 | CB6: =IF(BF6="Established",BP6+BQ6+BR6+BS6+BT6+BU6,IF(BF6="Early",BV6+BW6+BX6+BY6+BZ6+CA6,0)) -> 6 | CC6: =IF(BF6="Established",BO6+CB6,IF(BF6="Early",BO6+Parameters!$B$50*CB6,BO6)) -> 14 | CD6: =IF(BF6="Established",IF(CC6>=Parameters!$B$51,6,IF(CC6>=Parameters!$B$52,5,IF(CC6>=Parameters!$B$53,4,IF(CC6>=Parameters!$B$54,3,IF(CC6>=Parameters!$B$55,2,1))))),IF(BF6="Early",IF(CC6>=Parameters!$B$56,5,IF(CC6>=Parameters!$B$57,4,IF(CC6>=Parameters!$B$58,3,IF(CC6>=Parameters!$B$59,2,1)))),IF(CC6>=Parameters!$B$60,6,IF(CC6>=Parameters!$B$61,5,IF(CC6>=Parameters!$B$62,4,IF(CC6>=Parameters!$B$63,3,IF(CC6>=Parameters!$B$64,2,1))))))) -> 6 | CE6: =IF(AND(ISNUMBER(AR6),AR6<Parameters!$B$66),1,0) -> 0 | CF6: =IF(AND(LEFT(AH6,5)="Death",ISNUMBER(AG6)),IF(BF6="Early",IF(AND(AG6<Parameters!$B$70,ISNUMBER(U6),U6<Parameters!$B$71),1,0),IF(AND(AG6<Parameters!$B$67,OR(AND(ISNUMBER(U6),U6<Parameters!$B$68),AND(ISNUMBER(V6),V6<Parameters!$B$69))),1,0)),0) -> 0 | CG6: =IF(AND(ISNUMBER(AG6),AG6<0),1,0) -> 0 | CH6: =IF(OR(AND(ISNUMBER(U6),U6>Parameters!$B$74),AND(ISNUMBER(AF6),AF6>Parameters!$B$75),AND(ISNUMBER(AE6),AE6>Parameters!$B$76)),1,0) -> 0 | CI6: =IF(AND(ISNUMBER(BC6),BC6>=0,BC6<=Parameters!$B$77),1,0) -> 0 | CJ6: =IF(CF6=1,1,MIN(CD6,IF(CE6=1,3,6),IF(CG6=1,IF(BF6="Early",Parameters!$B$73,Parameters!$B$72),6),IF(CH6=1,3,6),IF(CI6=1,3,6))) -> 6 | CK6: =INDEX(Parameters!$F$2:$F$7,CJ6) -> Strong Buy | CL6: =IF(CF6=1,"Hard sell: breakdown; ","")&IF(CE6=1,"Insufficient history; ","")&IF(AND(CF6=0,CG6=1),"Below 200D; ","")&IF(CH6=1,"Extended - wait for pullback; ","")&IF(CI6=1,"Earnings within "&Parameters!$B$77&"d; ","")
A7: TWLO | B7: 8 | C7: 8 | D7: 71 | E7: 5 | F7: 9 | G7: Twilio Inc. Class A Common Stock | H7: Software | I7: 233.16 | J7: USD | K7: Technology | L7: 34890754231 | M7: 46240 | N7: 11.36 | O7: 46331 | P7: estimated | Q7: 2.63 | R7: 0.58 | S7: 2.83 | T7: 2.06 | U7: -8.9 | V7: 12.59 | W7: 84.05 | X7: 117.91 | AC7: 7.95 | AD7: -9.75 | AE7: 54.36 | AF7: 7.28 | AG7: 41.42 | AH7: Golden | AI7: -1.23 | AJ7: -28.2 | AK7: 4659.4 | AL7: 22 | AM7: 20.62 | AN7: 13.5 | AO7: 32.82 | AP7: 0.01 | AQ7: 2.75 | AR7: 300 | AS7: 46275 | AT7: 5572327936 | AU7: 2706002944 | AV7: 48.56 | AW7: 1148742016 | AX7: 954675392 | AY7: 17.13 | AZ7: 1590811008 | BA7: 136.85 | BB7: 84.25 | BC7: =IF(AND(ISNUMBER(O7),ISNUMBER(AS7)),O7-AS7,"") -> 56 | BD7: =IF(OR(ISNUMBER(SEARCH("ETF",H7)),AND(F7="",AO7="")),1,0) -> 0 | BE7: =IF(ISNUMBER(L7),IF(L7>=Parameters!$B$3,2,IF(L7>=Parameters!$B$4,1,0)),0)+IF(ISNUMBER(AW7),IF(AW7>0,IF(AND(ISNUMBER(AM7),AM7>=Parameters!$B$5),2,1),0),0)+IF(ISNUMBER(AX7),IF(AND(AX7>0,ISNUMBER(AY7),AY7>=Parameters!$B$6),1,0),0)+IF(ISNUMBER(AO7),IF(AND(AO7>0,AO7<=Parameters!$B$7),1,0),0)+IF(ISNUMBER(F7),IF(F7>=Parameters!$B$8,1,0),0) -> 6 | BF7: =IF(BD7=1,"ETF",IF(OR(AND(ISNUMBER(L7),L7>=Parameters!$B$10),BE7>=Parameters!$B$9),"Established","Early")) -> Established | BG7: =IF(LEFT(AH7,6)="Golden",2,IF(LEFT(AH7,5)="Death",-2,0)) -> 2 | BH7: =IF(ISNUMBER(AG7),IF(AG7>Parameters!$B$12,2,IF(AG7>0,1,IF(AG7>=Parameters!$B$13,-1,-2))),0) -> 2 | BI7: =IF(ISNUMBER(AF7),IF(AND(AF7>=Parameters!$B$14,AF7<=Parameters!$B$15),1,IF(OR(AF7>Parameters!$B$16,AF7<Parameters!$B$17),-1,0)),0) -> 1 | BJ7: =IF(ISNUMBER(AE7),IF(AND(AE7>=Parameters!$B$18,AE7<=Parameters!$B$19),1,IF(OR(AE7>Parameters!$B$20,AE7<Parameters!$B$21),-1,0)),0) -> 1 | BK7: =IF(ISNUMBER(E7),IF(E7>Parameters!$B$22,1,IF(E7<Parameters!$B$23,-1,0)),0) -> 1 | BL7: =IF(ISNUMBER(C7),IF(C7>=Parameters!$B$24,1,IF(C7<=Parameters!$B$25,-1,0)),0) -> 1 | BM7: =IF(ISNUMBER(AJ7),IF(AND(AJ7>Parameters!$B$26,ISNUMBER(U7)),IF(U7<0,-1,1),0),0) -> 0 | BN7: =IF(ISNUMBER(AD7),IF(AD7>Parameters!$B$27,1,IF(AD7<Parameters!$B$28,-1,0)),0) -> 1 | BO7: =BG7+BH7+BI7+BJ7+BK7+BL7+BM7+BN7 -> 9 | BP7: =IF(ISNUMBER(F7),IF(F7>=Parameters!$B$30,2,IF(F7>=Parameters!$B$31,1,IF(F7<=Parameters!$B$32,-1,0))),0) -> 2 | BQ7: =IF(ISNUMBER(AK7),IF(AK7>Parameters!$B$33,1,IF(AK7<0,-1,0)),0) -> 1 | BR7: =IF(ISNUMBER(AL7),IF(AL7>Parameters!$B$34,1,IF(AL7<0,-1,0)),0) -> 1 | BS7: =IF(ISNUMBER(AP7),IF(AND(AP7>0,AP7<=Parameters!$B$35),1,IF(AP7>Parameters!$B$36,-1,0)),0) -> 1 | BT7: =IF(ISNUMBER(AY7),IF(AY7>Parameters!$B$37,1,IF(AY7<0,-1,0)),0) -> 1 | BU7: =IF(ISNUMBER(AZ7),IF(AZ7>0,1,0),0) -> 1 | BV7: =IF(ISNUMBER(AL7),IF(AL7>Parameters!$B$39,2,IF(AL7>Parameters!$B$40,1,IF(AL7<0,-2,IF(AL7<Parameters!$B$41,-1,0)))),0) -> 1 | BW7: =IF(ISNUMBER(AV7),IF(AV7>Parameters!$B$42,1,IF(AV7<Parameters!$B$43,-1,0)),0) -> 0 | BX7: =IF(AND(ISNUMBER(AX7),AX7>0),1,IF(AND(ISNUMBER(AY7),AY7<Parameters!$B$44),-1,0)) -> 1 | BY7: =IF(ISNUMBER(AW7),IF(AW7>0,1,0),0) -> 1 | BZ7: =IF(ISNUMBER(AQ7),IF(AQ7>Parameters!$B$46,-2,IF(AQ7>Parameters!$B$45,-1,0)),0) -> 0 | CA7: =IF(ISNUMBER(F7),IF(F7>=Parameters!$B$47,1,IF(F7<=Parameters!$B$48,-1,0)),0) -> 1 | CB7: =IF(BF7="Established",BP7+BQ7+BR7+BS7+BT7+BU7,IF(BF7="Early",BV7+BW7+BX7+BY7+BZ7+CA7,0)) -> 7 | CC7: =IF(BF7="Established",BO7+CB7,IF(BF7="Early",BO7+Parameters!$B$50*CB7,BO7)) -> 16 | CD7: =IF(BF7="Established",IF(CC7>=Parameters!$B$51,6,IF(CC7>=Parameters!$B$52,5,IF(CC7>=Parameters!$B$53,4,IF(CC7>=Parameters!$B$54,3,IF(CC7>=Parameters!$B$55,2,1))))),IF(BF7="Early",IF(CC7>=Parameters!$B$56,5,IF(CC7>=Parameters!$B$57,4,IF(CC7>=Parameters!$B$58,3,IF(CC7>=Parameters!$B$59,2,1)))),IF(CC7>=Parameters!$B$60,6,IF(CC7>=Parameters!$B$61,5,IF(CC7>=Parameters!$B$62,4,IF(CC7>=Parameters!$B$63,3,IF(CC7>=Parameters!$B$64,2,1))))))) -> 6 | CE7: =IF(AND(ISNUMBER(AR7),AR7<Parameters!$B$66),1,0) -> 0 | CF7: =IF(AND(LEFT(AH7,5)="Death",ISNUMBER(AG7)),IF(BF7="Early",IF(AND(AG7<Parameters!$B$70,ISNUMBER(U7),U7<Parameters!$B$71),1,0),IF(AND(AG7<Parameters!$B$67,OR(AND(ISNUMBER(U7),U7<Parameters!$B$68),AND(ISNUMBER(V7),V7<Parameters!$B$69))),1,0)),0) -> 0 | CG7: =IF(AND(ISNUMBER(AG7),AG7<0),1,0) -> 0 | CH7: =IF(OR(AND(ISNUMBER(U7),U7>Parameters!$B$74),AND(ISNUMBER(AF7),AF7>Parameters!$B$75),AND(ISNUMBER(AE7),AE7>Parameters!$B$76)),1,0) -> 0 | CI7: =IF(AND(ISNUMBER(BC7),BC7>=0,BC7<=Parameters!$B$77),1,0) -> 0 | CJ7: =IF(CF7=1,1,MIN(CD7,IF(CE7=1,3,6),IF(CG7=1,IF(BF7="Early",Parameters!$B$73,Parameters!$B$72),6),IF(CH7=1,3,6),IF(CI7=1,3,6))) -> 6 | CK7: =INDEX(Parameters!$F$2:$F$7,CJ7) -> Strong Buy | CL7: =IF(CF7=1,"Hard sell: breakdown; ","")&IF(CE7=1,"Insufficient history; ","")&IF(AND(CF7=0,CG7=1),"Below 200D; ","")&IF(CH7=1,"Extended - wait for pullback; ","")&IF(CI7=1,"Earnings within "&Parameters!$B$77&"d; ","")
A8: AMD | B8: 8 | C8: 7 | D8: 66.2 | E8: 5.7 | F8: 8 | G8: Advanced Micro Devices, Inc. | H8: Chips | I8: 505.95 | J8: USD | K8: Technology | L8: 850674534669 | M8: 46238 | N8: 3.11 | O8: 46329 | P8: estimated | Q8: -2.91 | R8: 3.04 | S8: 10.7 | T8: 5.2 | U8: 6.67 | V8: 11.84 | W8: 147.01 | X8: 224.7 | AC8: 7.2 | AD8: -13.47 | AE8: 55.75 | AF8: 1.78 | AG8: 46.5 | AH8: Golden | AI8: 5.94 | AJ8: -1.17 | AK8: 163.4 | AL8: 50.1 | AM8: 15.66 | AN8: 10.2 | AO8: 33.43 | AP8: 0.83 | AQ8: 2.47 | AR8: 300 | AS8: 46275 | AT8: 41305001984 | AU8: 23017000960 | AV8: 55.72 | AW8: 6469000192 | AX8: 8841499648 | AY8: 21.41 | AZ8: 8835000064 | BA8: 237.64 | BB8: 81.88 | BC8: =IF(AND(ISNUMBER(O8),ISNUMBER(AS8)),O8-AS8,"") -> 54 | BD8: =IF(OR(ISNUMBER(SEARCH("ETF",H8)),AND(F8="",AO8="")),1,0) -> 0 | BE8: =IF(ISNUMBER(L8),IF(L8>=Parameters!$B$3,2,IF(L8>=Parameters!$B$4,1,0)),0)+IF(ISNUMBER(AW8),IF(AW8>0,IF(AND(ISNUMBER(AM8),AM8>=Parameters!$B$5),2,1),0),0)+IF(ISNUMBER(AX8),IF(AND(AX8>0,ISNUMBER(AY8),AY8>=Parameters!$B$6),1,0),0)+IF(ISNUMBER(AO8),IF(AND(AO8>0,AO8<=Parameters!$B$7),1,0),0)+IF(ISNUMBER(F8),IF(F8>=Parameters!$B$8,1,0),0) -> 7 | BF8: =IF(BD8=1,"ETF",IF(OR(AND(ISNUMBER(L8),L8>=Parameters!$B$10),BE8>=Parameters!$B$9),"Established","Early")) -> Established | BG8: =IF(LEFT(AH8,6)="Golden",2,IF(LEFT(AH8,5)="Death",-2,0)) -> 2 | BH8: =IF(ISNUMBER(AG8),IF(AG8>Parameters!$B$12,2,IF(AG8>0,1,IF(AG8>=Parameters!$B$13,-1,-2))),0) -> 2 | BI8: =IF(ISNUMBER(AF8),IF(AND(AF8>=Parameters!$B$14,AF8<=Parameters!$B$15),1,IF(OR(AF8>Parameters!$B$16,AF8<Parameters!$B$17),-1,0)),0) -> 1 | BJ8: =IF(ISNUMBER(AE8),IF(AND(AE8>=Parameters!$B$18,AE8<=Parameters!$B$19),1,IF(OR(AE8>Parameters!$B$20,AE8<Parameters!$B$21),-1,0)),0) -> 1 | BK8: =IF(ISNUMBER(E8),IF(E8>Parameters!$B$22,1,IF(E8<Parameters!$B$23,-1,0)),0) -> 1 | BL8: =IF(ISNUMBER(C8),IF(C8>=Parameters!$B$24,1,IF(C8<=Parameters!$B$25,-1,0)),0) -> 1 | BM8: =IF(ISNUMBER(AJ8),IF(AND(AJ8>Parameters!$B$26,ISNUMBER(U8)),IF(U8<0,-1,1),0),0) -> 0 | BN8: =IF(ISNUMBER(AD8),IF(AD8>Parameters!$B$27,1,IF(AD8<Parameters!$B$28,-1,0)),0) -> 0 | BO8: =BG8+BH8+BI8+BJ8+BK8+BL8+BM8+BN8 -> 8 | BP8: =IF(ISNUMBER(F8),IF(F8>=Parameters!$B$30,2,IF(F8>=Parameters!$B$31,1,IF(F8<=Parameters!$B$32,-1,0))),0) -> 2 | BQ8: =IF(ISNUMBER(AK8),IF(AK8>Parameters!$B$33,1,IF(AK8<0,-1,0)),0) -> 1 | BR8: =IF(ISNUMBER(AL8),IF(AL8>Parameters!$B$34,1,IF(AL8<0,-1,0)),0) -> 1 | BS8: =IF(ISNUMBER(AP8),IF(AND(AP8>0,AP8<=Parameters!$B$35),1,IF(AP8>Parameters!$B$36,-1,0)),0) -> 1 | BT8: =IF(ISNUMBER(AY8),IF(AY8>Parameters!$B$37,1,IF(AY8<0,-1,0)),0) -> 1 | BU8: =IF(ISNUMBER(AZ8),IF(AZ8>0,1,0),0) -> 1 | BV8: =IF(ISNUMBER(AL8),IF(AL8>Parameters!$B$39,2,IF(AL8>Parameters!$B$40,1,IF(AL8<0,-2,IF(AL8<Parameters!$B$41,-1,0)))),0) -> 2 | BW8: =IF(ISNUMBER(AV8),IF(AV8>Parameters!$B$42,1,IF(AV8<Parameters!$B$43,-1,0)),0) -> 1 | BX8: =IF(AND(ISNUMBER(AX8),AX8>0),1,IF(AND(ISNUMBER(AY8),AY8<Parameters!$B$44),-1,0)) -> 1 | BY8: =IF(ISNUMBER(AW8),IF(AW8>0,1,0),0) -> 1 | BZ8: =IF(ISNUMBER(AQ8),IF(AQ8>Parameters!$B$46,-2,IF(AQ8>Parameters!$B$45,-1,0)),0) -> 0 | CA8: =IF(ISNUMBER(F8),IF(F8>=Parameters!$B$47,1,IF(F8<=Parameters!$B$48,-1,0)),0) -> 1 | CB8: =IF(BF8="Established",BP8+BQ8+BR8+BS8+BT8+BU8,IF(BF8="Early",BV8+BW8+BX8+BY8+BZ8+CA8,0)) -> 7 | CC8: =IF(BF8="Established",BO8+CB8,IF(BF8="Early",BO8+Parameters!$B$50*CB8,BO8)) -> 15 | CD8: =IF(BF8="Established",IF(CC8>=Parameters!$B$51,6,IF(CC8>=Parameters!$B$52,5,IF(CC8>=Parameters!$B$53,4,IF(CC8>=Parameters!$B$54,3,IF(CC8>=Parameters!$B$55,2,1))))),IF(BF8="Early",IF(CC8>=Parameters!$B$56,5,IF(CC8>=Parameters!$B$57,4,IF(CC8>=Parameters!$B$58,3,IF(CC8>=Parameters!$B$59,2,1)))),IF(CC8>=Parameters!$B$60,6,IF(CC8>=Parameters!$B$61,5,IF(CC8>=Parameters!$B$62,4,IF(CC8>=Parameters!$B$63,3,IF(CC8>=Parameters!$B$64,2,1))))))) -> 6 | CE8: =IF(AND(ISNUMBER(AR8),AR8<Parameters!$B$66),1,0) -> 0 | CF8: =IF(AND(LEFT(AH8,5)="Death",ISNUMBER(AG8)),IF(BF8="Early",IF(AND(AG8<Parameters!$B$70,ISNUMBER(U8),U8<Parameters!$B$71),1,0),IF(AND(AG8<Parameters!$B$67,OR(AND(ISNUMBER(U8),U8<Parameters!$B$68),AND(ISNUMBER(V8),V8<Parameters!$B$69))),1,0)),0) -> 0 | CG8: =IF(AND(ISNUMBER(AG8),AG8<0),1,0) -> 0 | CH8: =IF(OR(AND(ISNUMBER(U8),U8>Parameters!$B$74),AND(ISNUMBER(AF8),AF8>Parameters!$B$75),AND(ISNUMBER(AE8),AE8>Parameters!$B$76)),1,0) -> 0 | CI8: =IF(AND(ISNUMBER(BC8),BC8>=0,BC8<=Parameters!$B$77),1,0) -> 0 | CJ8: =IF(CF8=1,1,MIN(CD8,IF(CE8=1,3,6),IF(CG8=1,IF(BF8="Early",Parameters!$B$73,Parameters!$B$72),6),IF(CH8=1,3,6),IF(CI8=1,3,6))) -> 6 | CK8: =INDEX(Parameters!$F$2:$F$7,CJ8) -> Strong Buy | CL8: =IF(CF8=1,"Hard sell: breakdown; ","")&IF(CE8=1,"Insufficient history; ","")&IF(AND(CF8=0,CG8=1),"Below 200D; ","")&IF(CH8=1,"Extended - wait for pullback; ","")&IF(CI8=1,"Earnings within "&Parameters!$B$77&"d; ","")
A9: WDC | B9: 8 | C9: 7 | D9: 60.4 | E9: 0.7 | F9: 10 | G9: Western Digital Corp. | H9: Memory | I9: 459.51 | J9: USD | K9: Technology | L9: 173881686472 | M9: 46239 | N9: 7.88 | O9: 46330 | P9: estimated | Q9: -4.72 | R9: 1.04 | S9: 2.36 | T9: -2 | U9: 4.93 | V9: -6.24 | W9: 70.94 | X9: 386.05 | AC9: -10.88 | AD9: -42.55 | AE9: 46.45 | AF9: -7.7 | AG9: 21.67 | AH9: Golden | AI9: 4.07 | AJ9: -27.69 | AK9: 1033 | AL9: 43.8 | AM9: 71.88 | AN9: 130.85 | AO9: 14.91 | AP9: 0.02 | AQ9: 5.66 | AR9: 300 | AS9: 46275 | AT9: 12919000064 | AU9: 6311000064 | AV9: 48.85 | AW9: 9285999616 | AX9: 2268750080 | AY9: 17.56 | AZ9: 388000000 | BA9: 389.26 | BB9: 51.79 | BC9: =IF(AND(ISNUMBER(O9),ISNUMBER(AS9)),O9-AS9,"") -> 55 | BD9: =IF(OR(ISNUMBER(SEARCH("ETF",H9)),AND(F9="",AO9="")),1,0) -> 0 | BE9: =IF(ISNUMBER(L9),IF(L9>=Parameters!$B$3,2,IF(L9>=Parameters!$B$4,1,0)),0)+IF(ISNUMBER(AW9),IF(AW9>0,IF(AND(ISNUMBER(AM9),AM9>=Parameters!$B$5),2,1),0),0)+IF(ISNUMBER(AX9),IF(AND(AX9>0,ISNUMBER(AY9),AY9>=Parameters!$B$6),1,0),0)+IF(ISNUMBER(AO9),IF(AND(AO9>0,AO9<=Parameters!$B$7),1,0),0)+IF(ISNUMBER(F9),IF(F9>=Parameters!$B$8,1,0),0) -> 7 | BF9: =IF(BD9=1,"ETF",IF(OR(AND(ISNUMBER(L9),L9>=Parameters!$B$10),BE9>=Parameters!$B$9),"Established","Early")) -> Established | BG9: =IF(LEFT(AH9,6)="Golden",2,IF(LEFT(AH9,5)="Death",-2,0)) -> 2 | BH9: =IF(ISNUMBER(AG9),IF(AG9>Parameters!$B$12,2,IF(AG9>0,1,IF(AG9>=Parameters!$B$13,-1,-2))),0) -> 2 | BI9: =IF(ISNUMBER(AF9),IF(AND(AF9>=Parameters!$B$14,AF9<=Parameters!$B$15),1,IF(OR(AF9>Parameters!$B$16,AF9<Parameters!$B$17),-1,0)),0) -> 0 | BJ9: =IF(ISNUMBER(AE9),IF(AND(AE9>=Parameters!$B$18,AE9<=Parameters!$B$19),1,IF(OR(AE9>Parameters!$B$20,AE9<Parameters!$B$21),-1,0)),0) -> 1 | BK9: =IF(ISNUMBER(E9),IF(E9>Parameters!$B$22,1,IF(E9<Parameters!$B$23,-1,0)),0) -> 0 | BL9: =IF(ISNUMBER(C9),IF(C9>=Parameters!$B$24,1,IF(C9<=Parameters!$B$25,-1,0)),0) -> 1 | BM9: =IF(ISNUMBER(AJ9),IF(AND(AJ9>Parameters!$B$26,ISNUMBER(U9)),IF(U9<0,-1,1),0),0) -> 0 | BN9: =IF(ISNUMBER(AD9),IF(AD9>Parameters!$B$27,1,IF(AD9<Parameters!$B$28,-1,0)),0) -> -1 | BO9: =BG9+BH9+BI9+BJ9+BK9+BL9+BM9+BN9 -> 5 | BP9: =IF(ISNUMBER(F9),IF(F9>=Parameters!$B$30,2,IF(F9>=Parameters!$B$31,1,IF(F9<=Parameters!$B$32,-1,0))),0) -> 2 | BQ9: =IF(ISNUMBER(AK9),IF(AK9>Parameters!$B$33,1,IF(AK9<0,-1,0)),0) -> 1 | BR9: =IF(ISNUMBER(AL9),IF(AL9>Parameters!$B$34,1,IF(AL9<0,-1,0)),0) -> 1 | BS9: =IF(ISNUMBER(AP9),IF(AND(AP9>0,AP9<=Parameters!$B$35),1,IF(AP9>Parameters!$B$36,-1,0)),0) -> 1 | BT9: =IF(ISNUMBER(AY9),IF(AY9>Parameters!$B$37,1,IF(AY9<0,-1,0)),0) -> 1 | BU9: =IF(ISNUMBER(AZ9),IF(AZ9>0,1,0),0) -> 1 | BV9: =IF(ISNUMBER(AL9),IF(AL9>Parameters!$B$39,2,IF(AL9>Parameters!$B$40,1,IF(AL9<0,-2,IF(AL9<Parameters!$B$41,-1,0)))),0) -> 2 | BW9: =IF(ISNUMBER(AV9),IF(AV9>Parameters!$B$42,1,IF(AV9<Parameters!$B$43,-1,0)),0) -> 0 | BX9: =IF(AND(ISNUMBER(AX9),AX9>0),1,IF(AND(ISNUMBER(AY9),AY9<Parameters!$B$44),-1,0)) -> 1 | BY9: =IF(ISNUMBER(AW9),IF(AW9>0,1,0),0) -> 1 | BZ9: =IF(ISNUMBER(AQ9),IF(AQ9>Parameters!$B$46,-2,IF(AQ9>Parameters!$B$45,-1,0)),0) -> 0 | CA9: =IF(ISNUMBER(F9),IF(F9>=Parameters!$B$47,1,IF(F9<=Parameters!$B$48,-1,0)),0) -> 1 | CB9: =IF(BF9="Established",BP9+BQ9+BR9+BS9+BT9+BU9,IF(BF9="Early",BV9+BW9+BX9+BY9+BZ9+CA9,0)) -> 7 | CC9: =IF(BF9="Established",BO9+CB9,IF(BF9="Early",BO9+Parameters!$B$50*CB9,BO9)) -> 12 | CD9: =IF(BF9="Established",IF(CC9>=Parameters!$B$51,6,IF(CC9>=Parameters!$B$52,5,IF(CC9>=Parameters!$B$53,4,IF(CC9>=Parameters!$B$54,3,IF(CC9>=Parameters!$B$55,2,1))))),IF(BF9="Early",IF(CC9>=Parameters!$B$56,5,IF(CC9>=Parameters!$B$57,4,IF(CC9>=Parameters!$B$58,3,IF(CC9>=Parameters!$B$59,2,1)))),IF(CC9>=Parameters!$B$60,6,IF(CC9>=Parameters!$B$61,5,IF(CC9>=Parameters!$B$62,4,IF(CC9>=Parameters!$B$63,3,IF(CC9>=Parameters!$B$64,2,1))))))) -> 5 | CE9: =IF(AND(ISNUMBER(AR9),AR9<Parameters!$B$66),1,0) -> 0 | CF9: =IF(AND(LEFT(AH9,5)="Death",ISNUMBER(AG9)),IF(BF9="Early",IF(AND(AG9<Parameters!$B$70,ISNUMBER(U9),U9<Parameters!$B$71),1,0),IF(AND(AG9<Parameters!$B$67,OR(AND(ISNUMBER(U9),U9<Parameters!$B$68),AND(ISNUMBER(V9),V9<Parameters!$B$69))),1,0)),0) -> 0 | CG9: =IF(AND(ISNUMBER(AG9),AG9<0),1,0) -> 0 | CH9: =IF(OR(AND(ISNUMBER(U9),U9>Parameters!$B$74),AND(ISNUMBER(AF9),AF9>Parameters!$B$75),AND(ISNUMBER(AE9),AE9>Parameters!$B$76)),1,0) -> 0 | CI9: =IF(AND(ISNUMBER(BC9),BC9>=0,BC9<=Parameters!$B$77),1,0) -> 0 | CJ9: =IF(CF9=1,1,MIN(CD9,IF(CE9=1,3,6),IF(CG9=1,IF(BF9="Early",Parameters!$B$73,Parameters!$B$72),6),IF(CH9=1,3,6),IF(CI9=1,3,6))) -> 5 | CK9: =INDEX(Parameters!$F$2:$F$7,CJ9) -> Buy | CL9: =IF(CF9=1,"Hard sell: breakdown; ","")&IF(CE9=1,"Insufficient history; ","")&IF(AND(CF9=0,CG9=1),"Below 200D; ","")&IF(CH9=1,"Extended - wait for pullback; ","")&IF(CI9=1,"Earnings within "&Parameters!$B$77&"d; ","")
A10: SNDK | B10: 8 | C10: 7 | D10: 64.4 | E10: 4 | F10: 9 | G10: SanDisk Corporation | H10: Memory | I10: 1688.55 | J10: USD | K10: Technology | L10: 258308014850 | M10: 46239 | N10: 13.7 | O10: 46330 | P10: estimated | Q10: -4.29 | R10: 1.51 | S10: 8.7 | T10: 12.62 | U10: 32.85 | V10: 2.76 | W10: 157.62 | X10: 2294.77 | AC10: -1.88 | AD10: -28.28 | AE10: 57.08 | AF10: 10.67 | AG10: 64.5 | AH10: Golden | AI10: 24.58 | AJ10: -27.43 | AK10: 371.59 | AL10: 371.6 | AM10: 56.46 | AN10: 91.64 | AO10: 6.79 | AP10: 0 | AQ10: 5.32 | AR10: 300 | AS10: 46275 | AT10: 20248000512 | AU10: 14471999488 | AV10: 71.47 | AW10: 11432999936 | AX10: 7720875008 | AY10: 38.13 | AZ10: 4560999872 | BA10: 2244.23 | BB10: 70.83 | BC10: =IF(AND(ISNUMBER(O10),ISNUMBER(AS10)),O10-AS10,"") -> 55 | BD10: =IF(OR(ISNUMBER(SEARCH("ETF",H10)),AND(F10="",AO10="")),1,0) -> 0 | BE10: =IF(ISNUMBER(L10),IF(L10>=Parameters!$B$3,2,IF(L10>=Parameters!$B$4,1,0)),0)+IF(ISNUMBER(AW10),IF(AW10>0,IF(AND(ISNUMBER(AM10),AM10>=Parameters!$B$5),2,1),0),0)+IF(ISNUMBER(AX10),IF(AND(AX10>0,ISNUMBER(AY10),AY10>=Parameters!$B$6),1,0),0)+IF(ISNUMBER(AO10),IF(AND(AO10>0,AO10<=Parameters!$B$7),1,0),0)+IF(ISNUMBER(F10),IF(F10>=Parameters!$B$8,1,0),0) -> 7 | BF10: =IF(BD10=1,"ETF",IF(OR(AND(ISNUMBER(L10),L10>=Parameters!$B$10),BE10>=Parameters!$B$9),"Established","Early")) -> Established | BG10: =IF(LEFT(AH10,6)="Golden",2,IF(LEFT(AH10,5)="Death",-2,0)) -> 2 | BH10: =IF(ISNUMBER(AG10),IF(AG10>Parameters!$B$12,2,IF(AG10>0,1,IF(AG10>=Parameters!$B$13,-1,-2))),0) -> 2 | BI10: =IF(ISNUMBER(AF10),IF(AND(AF10>=Parameters!$B$14,AF10<=Parameters!$B$15),1,IF(OR(AF10>Parameters!$B$16,AF10<Parameters!$B$17),-1,0)),0) -> 0 | BJ10: =IF(ISNUMBER(AE10),IF(AND(AE10>=Parameters!$B$18,AE10<=Parameters!$B$19),1,IF(OR(AE10>Parameters!$B$20,AE10<Parameters!$B$21),-1,0)),0) -> 1 | BK10: =IF(ISNUMBER(E10),IF(E10>Parameters!$B$22,1,IF(E10<Parameters!$B$23,-1,0)),0) -> 1 | BL10: =IF(ISNUMBER(C10),IF(C10>=Parameters!$B$24,1,IF(C10<=Parameters!$B$25,-1,0)),0) -> 1 | BM10: =IF(ISNUMBER(AJ10),IF(AND(AJ10>Parameters!$B$26,ISNUMBER(U10)),IF(U10<0,-1,1),0),0) -> 0 | BN10: =IF(ISNUMBER(AD10),IF(AD10>Parameters!$B$27,1,IF(AD10<Parameters!$B$28,-1,0)),0) -> 0 | BO10: =BG10+BH10+BI10+BJ10+BK10+BL10+BM10+BN10 -> 7 | BP10: =IF(ISNUMBER(F10),IF(F10>=Parameters!$B$30,2,IF(F10>=Parameters!$B$31,1,IF(F10<=Parameters!$B$32,-1,0))),0) -> 2 | BQ10: =IF(ISNUMBER(AK10),IF(AK10>Parameters!$B$33,1,IF(AK10<0,-1,0)),0) -> 1 | BR10: =IF(ISNUMBER(AL10),IF(AL10>Parameters!$B$34,1,IF(AL10<0,-1,0)),0) -> 1 | BS10: =IF(ISNUMBER(AP10),IF(AND(AP10>0,AP10<=Parameters!$B$35),1,IF(AP10>Parameters!$B$36,-1,0)),0) -> 0 | BT10: =IF(ISNUMBER(AY10),IF(AY10>Parameters!$B$37,1,IF(AY10<0,-1,0)),0) -> 1 | BU10: =IF(ISNUMBER(AZ10),IF(AZ10>0,1,0),0) -> 1 | BV10: =IF(ISNUMBER(AL10),IF(AL10>Parameters!$B$39,2,IF(AL10>Parameters!$B$40,1,IF(AL10<0,-2,IF(AL10<Parameters!$B$41,-1,0)))),0) -> 2 | BW10: =IF(ISNUMBER(AV10),IF(AV10>Parameters!$B$42,1,IF(AV10<Parameters!$B$43,-1,0)),0) -> 1 | BX10: =IF(AND(ISNUMBER(AX10),AX10>0),1,IF(AND(ISNUMBER(AY10),AY10<Parameters!$B$44),-1,0)) -> 1 | BY10: =IF(ISNUMBER(AW10),IF(AW10>0,1,0),0) -> 1 | BZ10: =IF(ISNUMBER(AQ10),IF(AQ10>Parameters!$B$46,-2,IF(AQ10>Parameters!$B$45,-1,0)),0) -> 0 | CA10: =IF(ISNUMBER(F10),IF(F10>=Parameters!$B$47,1,IF(F10<=Parameters!$B$48,-1,0)),0) -> 1 | CB10: =IF(BF10="Established",BP10+BQ10+BR10+BS10+BT10+BU10,IF(BF10="Early",BV10+BW10+BX10+BY10+BZ10+CA10,0)) -> 6 | CC10: =IF(BF10="Established",BO10+CB10,IF(BF10="Early",BO10+Parameters!$B$50*CB10,BO10)) -> 13 | CD10: =IF(BF10="Established",IF(CC10>=Parameters!$B$51,6,IF(CC10>=Parameters!$B$52,5,IF(CC10>=Parameters!$B$53,4,IF(CC10>=Parameters!$B$54,3,IF(CC10>=Parameters!$B$55,2,1))))),IF(BF10="Early",IF(CC10>=Parameters!$B$56,5,IF(CC10>=Parameters!$B$57,4,IF(CC10>=Parameters!$B$58,3,IF(CC10>=Parameters!$B$59,2,1)))),IF(CC10>=Parameters!$B$60,6,IF(CC10>=Parameters!$B$61,5,IF(CC10>=Parameters!$B$62,4,IF(CC10>=Parameters!$B$63,3,IF(CC10>=Parameters!$B$64,2,1))))))) -> 6 | CE10: =IF(AND(ISNUMBER(AR10),AR10<Parameters!$B$66),1,0) -> 0 | CF10: =IF(AND(LEFT(AH10,5)="Death",ISNUMBER(AG10)),IF(BF10="Early",IF(AND(AG10<Parameters!$B$70,ISNUMBER(U10),U10<Parameters!$B$71),1,0),IF(AND(AG10<Parameters!$B$67,OR(AND(ISNUMBER(U10),U10<Parameters!$B$68),AND(ISNUMBER(V10),V10<Parameters!$B$69))),1,0)),0) -> 0 | CG10: =IF(AND(ISNUMBER(AG10),AG10<0),1,0) -> 0 | CH10: =IF(OR(AND(ISNUMBER(U10),U10>Parameters!$B$74),AND(ISNUMBER(AF10),AF10>Parameters!$B$75),AND(ISNUMBER(AE10),AE10>Parameters!$B$76)),1,0) -> 1 | CI10: =IF(AND(ISNUMBER(BC10),BC10>=0,BC10<=Parameters!$B$77),1,0) -> 0 | CJ10: =IF(CF10=1,1,MIN(CD10,IF(CE10=1,3,6),IF(CG10=1,IF(BF10="Early",Parameters!$B$73,Parameters!$B$72),6),IF(CH10=1,3,6),IF(CI10=1,3,6))) -> 3 | CK10: =INDEX(Parameters!$F$2:$F$7,CJ10) -> Hold | CL10: =IF(CF10=1,"Hard sell: breakdown; ","")&IF(CE10=1,"Insufficient history; ","")&IF(AND(CF10=0,CG10=1),"Below 200D; ","")&IF(CH10=1,"Extended - wait for pullback; ","")&IF(CI10=1,"Earnings within "&Parameters!$B$77&"d; ","") -> Extended - wait for pullback;
A11: TSM | B11: 8 | C11: 6 | D11: 50.6 | E11: 9.7 | F11: 10 | G11: Taiwan Semiconductor Manufacturing Company Ltd. ADR | H11: Chips | I11: 430.67 | J11: USD | K11: Technology | L11: 2257983274434 | M11: 46219 | N11: 10.8 | O11: 46310 | P11: estimated | Q11: -1.08 | R11: -0.83 | S11: 3.65 | T11: 3.11 | U11: 2.04 | V11: 5.36 | W11: 21.47 | X11: 71.64 | AC11: 0.72 | AD11: -10.09 | AE11: 55.79 | AF11: 2.73 | AG11: 14.79 | AH11: Golden | AI11: 1.91 | AJ11: -6.08 | AK11: 77.4 | AL11: 36 | AM11: 49.92 | AN11: 39.97 | AO11: 19.77 | AP11: 0.41 | AQ11: 0.08 | AR11: 300 | AS11: 46275 | AT11: 140865738606 | AU11: 90478306998 | AV11: 64.23 | AW11: 70323813356 | AX11: 23183993664 | AY11: 16.46 | AZ11: 77703956676 | BA11: 67.09 | BB11: 78.16 | BC11: =IF(AND(ISNUMBER(O11),ISNUMBER(AS11)),O11-AS11,"") -> 35 | BD11: =IF(OR(ISNUMBER(SEARCH("ETF",H11)),AND(F11="",AO11="")),1,0) -> 0 | BE11: =IF(ISNUMBER(L11),IF(L11>=Parameters!$B$3,2,IF(L11>=Parameters!$B$4,1,0)),0)+IF(ISNUMBER(AW11),IF(AW11>0,IF(AND(ISNUMBER(AM11),AM11>=Parameters!$B$5),2,1),0),0)+IF(ISNUMBER(AX11),IF(AND(AX11>0,ISNUMBER(AY11),AY11>=Parameters!$B$6),1,0),0)+IF(ISNUMBER(AO11),IF(AND(AO11>0,AO11<=Parameters!$B$7),1,0),0)+IF(ISNUMBER(F11),IF(F11>=Parameters!$B$8,1,0),0) -> 7 | BF11: =IF(BD11=1,"ETF",IF(OR(AND(ISNUMBER(L11),L11>=Parameters!$B$10),BE11>=Parameters!$B$9),"Established","Early")) -> Established | BG11: =IF(LEFT(AH11,6)="Golden",2,IF(LEFT(AH11,5)="Death",-2,0)) -> 2 | BH11: =IF(ISNUMBER(AG11),IF(AG11>Parameters!$B$12,2,IF(AG11>0,1,IF(AG11>=Parameters!$B$13,-1,-2))),0) -> 2 | BI11: =IF(ISNUMBER(AF11),IF(AND(AF11>=Parameters!$B$14,AF11<=Parameters!$B$15),1,IF(OR(AF11>Parameters!$B$16,AF11<Parameters!$B$17),-1,0)),0) -> 1 | BJ11: =IF(ISNUMBER(AE11),IF(AND(AE11>=Parameters!$B$18,AE11<=Parameters!$B$19),1,IF(OR(AE11>Parameters!$B$20,AE11<Parameters!$B$21),-1,0)),0) -> 1 | BK11: =IF(ISNUMBER(E11),IF(E11>Parameters!$B$22,1,IF(E11<Parameters!$B$23,-1,0)),0) -> 1 | BL11: =IF(ISNUMBER(C11),IF(C11>=Parameters!$B$24,1,IF(C11<=Parameters!$B$25,-1,0)),0) -> 0 | BM11: =IF(ISNUMBER(AJ11),IF(AND(AJ11>Parameters!$B$26,ISNUMBER(U11)),IF(U11<0,-1,1),0),0) -> 0 | BN11: =IF(ISNUMBER(AD11),IF(AD11>Parameters!$B$27,1,IF(AD11<Parameters!$B$28,-1,0)),0) -> 0 | BO11: =BG11+BH11+BI11+BJ11+BK11+BL11+BM11+BN11 -> 7 | BP11: =IF(ISNUMBER(F11),IF(F11>=Parameters!$B$30,2,IF(F11>=Parameters!$B$31,1,IF(F11<=Parameters!$B$32,-1,0))),0) -> 2 | BQ11: =IF(ISNUMBER(AK11),IF(AK11>Parameters!$B$33,1,IF(AK11<0,-1,0)),0) -> 1 | BR11: =IF(ISNUMBER(AL11),IF(AL11>Parameters!$B$34,1,IF(AL11<0,-1,0)),0) -> 1 | BS11: =IF(ISNUMBER(AP11),IF(AND(AP11>0,AP11<=Parameters!$B$35),1,IF(AP11>Parameters!$B$36,-1,0)),0) -> 1 | BT11: =IF(ISNUMBER(AY11),IF(AY11>Parameters!$B$37,1,IF(AY11<0,-1,0)),0) -> 1 | BU11: =IF(ISNUMBER(AZ11),IF(AZ11>0,1,0),0) -> 1 | BV11: =IF(ISNUMBER(AL11),IF(AL11>Parameters!$B$39,2,IF(AL11>Parameters!$B$40,1,IF(AL11<0,-2,IF(AL11<Parameters!$B$41,-1,0)))),0) -> 2 | BW11: =IF(ISNUMBER(AV11),IF(AV11>Parameters!$B$42,1,IF(AV11<Parameters!$B$43,-1,0)),0) -> 1 | BX11: =IF(AND(ISNUMBER(AX11),AX11>0),1,IF(AND(ISNUMBER(AY11),AY11<Parameters!$B$44),-1,0)) -> 1 | BY11: =IF(ISNUMBER(AW11),IF(AW11>0,1,0),0) -> 1 | BZ11: =IF(ISNUMBER(AQ11),IF(AQ11>Parameters!$B$46,-2,IF(AQ11>Parameters!$B$45,-1,0)),0) -> 0 | CA11: =IF(ISNUMBER(F11),IF(F11>=Parameters!$B$47,1,IF(F11<=Parameters!$B$48,-1,0)),0) -> 1 | CB11: =IF(BF11="Established",BP11+BQ11+BR11+BS11+BT11+BU11,IF(BF11="Early",BV11+BW11+BX11+BY11+BZ11+CA11,0)) -> 7 | CC11: =IF(BF11="Established",BO11+CB11,IF(BF11="Early",BO11+Parameters!$B$50*CB11,BO11)) -> 14 | CD11: =IF(BF11="Established",IF(CC11>=Parameters!$B$51,6,IF(CC11>=Parameters!$B$52,5,IF(CC11>=Parameters!$B$53,4,IF(CC11>=Parameters!$B$54,3,IF(CC11>=Parameters!$B$55,2,1))))),IF(BF11="Early",IF(CC11>=Parameters!$B$56,5,IF(CC11>=Parameters!$B$57,4,IF(CC11>=Parameters!$B$58,3,IF(CC11>=Parameters!$B$59,2,1)))),IF(CC11>=Parameters!$B$60,6,IF(CC11>=Parameters!$B$61,5,IF(CC11>=Parameters!$B$62,4,IF(CC11>=Parameters!$B$63,3,IF(CC11>=Parameters!$B$64,2,1))))))) -> 6 | CE11: =IF(AND(ISNUMBER(AR11),AR11<Parameters!$B$66),1,0) -> 0 | CF11: =IF(AND(LEFT(AH11,5)="Death",ISNUMBER(AG11)),IF(BF11="Early",IF(AND(AG11<Parameters!$B$70,ISNUMBER(U11),U11<Parameters!$B$71),1,0),IF(AND(AG11<Parameters!$B$67,OR(AND(ISNUMBER(U11),U11<Parameters!$B$68),AND(ISNUMBER(V11),V11<Parameters!$B$69))),1,0)),0) -> 0 | CG11: =IF(AND(ISNUMBER(AG11),AG11<0),1,0) -> 0 | CH11: =IF(OR(AND(ISNUMBER(U11),U11>Parameters!$B$74),AND(ISNUMBER(AF11),AF11>Parameters!$B$75),AND(ISNUMBER(AE11),AE11>Parameters!$B$76)),1,0) -> 0 | CI11: =IF(AND(ISNUMBER(BC11),BC11>=0,BC11<=Parameters!$B$77),1,0) -> 0 | CJ11: =IF(CF11=1,1,MIN(CD11,IF(CE11=1,3,6),IF(CG11=1,IF(BF11="Early",Parameters!$B$73,Parameters!$B$72),6),IF(CH11=1,3,6),IF(CI11=1,3,6))) -> 6 | CK11: =INDEX(Parameters!$F$2:$F$7,CJ11) -> Strong Buy | CL11: =IF(CF11=1,"Hard sell: breakdown; ","")&IF(CE11=1,"Insufficient history; ","")&IF(AND(CF11=0,CG11=1),"Below 200D; ","")&IF(CH11=1,"Extended - wait for pullback; ","")&IF(CI11=1,"Earnings within "&Parameters!$B$77&"d; ","")
A12: AMAT | B12: 7 | C12: 6 | D12: 56 | E12: 3 | F12: 10 | G12: Applied Materials Inc. | H12: Chips | I12: 457.48 | J12: USD | K12: Technology | L12: 372078169086 | M12: 46247 | N12: 3.24 | O12: 46338 | P12: estimated | Q12: -2.43 | R12: -0.83 | S12: 4.34 | T12: -4.64 | U12: -12.96 | V12: -7.95 | W12: 30.31 | X12: 179.8 | AC12: -12.59 | AD12: -38.15 | AE12: 41.59 | AF12: -12.16 | AG12: 11.4 | AH12: Golden | AI12: 0.83 | AJ12: -35.06 | AK12: 42.7 | AL12: 24.8 | AM12: 30.05 | AN12: 41.07 | AO12: 25.6 | AP12: 0.94 | AQ12: 1.5 | AR12: 300 | AS12: 46275 | AT12: 30837000192 | AU12: 15233000448 | AV12: 49.4 | AW12: 9267000320 | AX12: 3075375104 | AY12: 9.97 | AZ12: 1887000576 | BA12: 181.44 | BB12: 51.1 | BC12: =IF(AND(ISNUMBER(O12),ISNUMBER(AS12)),O12-AS12,"") -> 63 | BD12: =IF(OR(ISNUMBER(SEARCH("ETF",H12)),AND(F12="",AO12="")),1,0) -> 0 | BE12: =IF(ISNUMBER(L12),IF(L12>=Parameters!$B$3,2,IF(L12>=Parameters!$B$4,1,0)),0)+IF(ISNUMBER(AW12),IF(AW12>0,IF(AND(ISNUMBER(AM12),AM12>=Parameters!$B$5),2,1),0),0)+IF(ISNUMBER(AX12),IF(AND(AX12>0,ISNUMBER(AY12),AY12>=Parameters!$B$6),1,0),0)+IF(ISNUMBER(AO12),IF(AND(AO12>0,AO12<=Parameters!$B$7),1,0),0)+IF(ISNUMBER(F12),IF(F12>=Parameters!$B$8,1,0),0) -> 7 | BF12: =IF(BD12=1,"ETF",IF(OR(AND(ISNUMBER(L12),L12>=Parameters!$B$10),BE12>=Parameters!$B$9),"Established","Early")) -> Established | BG12: =IF(LEFT(AH12,6)="Golden",2,IF(LEFT(AH12,5)="Death",-2,0)) -> 2 | BH12: =IF(ISNUMBER(AG12),IF(AG12>Parameters!$B$12,2,IF(AG12>0,1,IF(AG12>=Parameters!$B$13,-1,-2))),0) -> 2 | BI12: =IF(ISNUMBER(AF12),IF(AND(AF12>=Parameters!$B$14,AF12<=Parameters!$B$15),1,IF(OR(AF12>Parameters!$B$16,AF12<Parameters!$B$17),-1,0)),0) -> -1 | BJ12: =IF(ISNUMBER(AE12),IF(AND(AE12>=Parameters!$B$18,AE12<=Parameters!$B$19),1,IF(OR(AE12>Parameters!$B$20,AE12<Parameters!$B$21),-1,0)),0) -> 0 | BK12: =IF(ISNUMBER(E12),IF(E12>Parameters!$B$22,1,IF(E12<Parameters!$B$23,-1,0)),0) -> 0 | BL12: =IF(ISNUMBER(C12),IF(C12>=Parameters!$B$24,1,IF(C12<=Parameters!$B$25,-1,0)),0) -> 0 | BM12: =IF(ISNUMBER(AJ12),IF(AND(AJ12>Parameters!$B$26,ISNUMBER(U12)),IF(U12<0,-1,1),0),0) -> 0 | BN12: =IF(ISNUMBER(AD12),IF(AD12>Parameters!$B$27,1,IF(AD12<Parameters!$B$28,-1,0)),0) -> -1 | BO12: =BG12+BH12+BI12+BJ12+BK12+BL12+BM12+BN12 -> 2 | BP12: =IF(ISNUMBER(F12),IF(F12>=Parameters!$B$30,2,IF(F12>=Parameters!$B$31,1,IF(F12<=Parameters!$B$32,-1,0))),0) -> 2 | BQ12: =IF(ISNUMBER(AK12),IF(AK12>Parameters!$B$33,1,IF(AK12<0,-1,0)),0) -> 1 | BR12: =IF(ISNUMBER(AL12),IF(AL12>Parameters!$B$34,1,IF(AL12<0,-1,0)),0) -> 1 | BS12: =IF(ISNUMBER(AP12),IF(AND(AP12>0,AP12<=Parameters!$B$35),1,IF(AP12>Parameters!$B$36,-1,0)),0) -> 1 | BT12: =IF(ISNUMBER(AY12),IF(AY12>Parameters!$B$37,1,IF(AY12<0,-1,0)),0) -> 0 | BU12: =IF(ISNUMBER(AZ12),IF(AZ12>0,1,0),0) -> 1 | BV12: =IF(ISNUMBER(AL12),IF(AL12>Parameters!$B$39,2,IF(AL12>Parameters!$B$40,1,IF(AL12<0,-2,IF(AL12<Parameters!$B$41,-1,0)))),0) -> 1 | BW12: =IF(ISNUMBER(AV12),IF(AV12>Parameters!$B$42,1,IF(AV12<Parameters!$B$43,-1,0)),0) -> 0 | BX12: =IF(AND(ISNUMBER(AX12),AX12>0),1,IF(AND(ISNUMBER(AY12),AY12<Parameters!$B$44),-1,0)) -> 1 | BY12: =IF(ISNUMBER(AW12),IF(AW12>0,1,0),0) -> 1 | BZ12: =IF(ISNUMBER(AQ12),IF(AQ12>Parameters!$B$46,-2,IF(AQ12>Parameters!$B$45,-1,0)),0) -> 0 | CA12: =IF(ISNUMBER(F12),IF(F12>=Parameters!$B$47,1,IF(F12<=Parameters!$B$48,-1,0)),0) -> 1 | CB12: =IF(BF12="Established",BP12+BQ12+BR12+BS12+BT12+BU12,IF(BF12="Early",BV12+BW12+BX12+BY12+BZ12+CA12,0)) -> 6 | CC12: =IF(BF12="Established",BO12+CB12,IF(BF12="Early",BO12+Parameters!$B$50*CB12,BO12)) -> 8 | CD12: =IF(BF12="Established",IF(CC12>=Parameters!$B$51,6,IF(CC12>=Parameters!$B$52,5,IF(CC12>=Parameters!$B$53,4,IF(CC12>=Parameters!$B$54,3,IF(CC12>=Parameters!$B$55,2,1))))),IF(BF12="Early",IF(CC12>=Parameters!$B$56,5,IF(CC12>=Parameters!$B$57,4,IF(CC12>=Parameters!$B$58,3,IF(CC12>=Parameters!$B$59,2,1)))),IF(CC12>=Parameters!$B$60,6,IF(CC12>=Parameters!$B$61,5,IF(CC12>=Parameters!$B$62,4,IF(CC12>=Parameters!$B$63,3,IF(CC12>=Parameters!$B$64,2,1))))))) -> 4 | CE12: =IF(AND(ISNUMBER(AR12),AR12<Parameters!$B$66),1,0) -> 0 | CF12: =IF(AND(LEFT(AH12,5)="Death",ISNUMBER(AG12)),IF(BF12="Early",IF(AND(AG12<Parameters!$B$70,ISNUMBER(U12),U12<Parameters!$B$71),1,0),IF(AND(AG12<Parameters!$B$67,OR(AND(ISNUMBER(U12),U12<Parameters!$B$68),AND(ISNUMBER(V12),V12<Parameters!$B$69))),1,0)),0) -> 0 | CG12: =IF(AND(ISNUMBER(AG12),AG12<0),1,0) -> 0 | CH12: =IF(OR(AND(ISNUMBER(U12),U12>Parameters!$B$74),AND(ISNUMBER(AF12),AF12>Parameters!$B$75),AND(ISNUMBER(AE12),AE12>Parameters!$B$76)),1,0) -> 0 | CI12: =IF(AND(ISNUMBER(BC12),BC12>=0,BC12<=Parameters!$B$77),1,0) -> 0 | CJ12: =IF(CF12=1,1,MIN(CD12,IF(CE12=1,3,6),IF(CG12=1,IF(BF12="Early",Parameters!$B$73,Parameters!$B$72),6),IF(CH12=1,3,6),IF(CI12=1,3,6))) -> 4 | CK12: =INDEX(Parameters!$F$2:$F$7,CJ12) -> Buy with Risk | CL12: =IF(CF12=1,"Hard sell: breakdown; ","")&IF(CE12=1,"Insufficient history; ","")&IF(AND(CF12=0,CG12=1),"Below 200D; ","")&IF(CH12=1,"Extended - wait for pullback; ","")&IF(CI12=1,"Earnings within "&Parameters!$B$77&"d; ","")
A13: AAPL | B13: 7 | C13: 7 | D13: 61.6 | E13: 1.3 | F13: 9 | G13: Apple Inc. | H13: Mag 7 | I13: 323.55 | J13: USD | K13: Technology | L13: 4602128721200 | M13: 46233 | N13: 6.88 | O13: 46324 | P13: estimated | Q13: 2.6 | R13: -0.28 | S13: -0.43 | T13: 3.22 | U13: 6.11 | V13: 10.96 | W13: 24.06 | X13: 38.06 | AC13: 6.32 | AD13: -6.1 | AE13: 56.73 | AF13: 2.02 | AG13: 13.67 | AH13: Golden | AI13: 0.6 | AJ13: -7.18 | AK13: 27.1 | AL13: 16.4 | AM13: 27.62 | AN13: 148.75 | AO13: 32.92 | AP13: 1.23 | AQ13: 0.8 | AR13: 300 | AS13: 46275 | AT13: 466822987776 | AU13: 227123003392 | AV13: 48.65 | AW13: 128929996800 | AX13: 107721875456 | AY13: 23.08 | AZ13: -21944995840 | BA13: 43.2 | BB13: 82.28 | BC13: =IF(AND(ISNUMBER(O13),ISNUMBER(AS13)),O13-AS13,"") -> 49 | BD13: =IF(OR(ISNUMBER(SEARCH("ETF",H13)),AND(F13="",AO13="")),1,0) -> 0 | BE13: =IF(ISNUMBER(L13),IF(L13>=Parameters!$B$3,2,IF(L13>=Parameters!$B$4,1,0)),0)+IF(ISNUMBER(AW13),IF(AW13>0,IF(AND(ISNUMBER(AM13),AM13>=Parameters!$B$5),2,1),0),0)+IF(ISNUMBER(AX13),IF(AND(AX13>0,ISNUMBER(AY13),AY13>=Parameters!$B$6),1,0),0)+IF(ISNUMBER(AO13),IF(AND(AO13>0,AO13<=Parameters!$B$7),1,0),0)+IF(ISNUMBER(F13),IF(F13>=Parameters!$B$8,1,0),0) -> 7 | BF13: =IF(BD13=1,"ETF",IF(OR(AND(ISNUMBER(L13),L13>=Parameters!$B$10),BE13>=Parameters!$B$9),"Established","Early")) -> Established | BG13: =IF(LEFT(AH13,6)="Golden",2,IF(LEFT(AH13,5)="Death",-2,0)) -> 2 | BH13: =IF(ISNUMBER(AG13),IF(AG13>Parameters!$B$12,2,IF(AG13>0,1,IF(AG13>=Parameters!$B$13,-1,-2))),0) -> 2 | BI13: =IF(ISNUMBER(AF13),IF(AND(AF13>=Parameters!$B$14,AF13<=Parameters!$B$15),1,IF(OR(AF13>Parameters!$B$16,AF13<Parameters!$B$17),-1,0)),0) -> 1 | BJ13: =IF(ISNUMBER(AE13),IF(AND(AE13>=Parameters!$B$18,AE13<=Parameters!$B$19),1,IF(OR(AE13>Parameters!$B$20,AE13<Parameters!$B$21),-1,0)),0) -> 1 | BK13: =IF(ISNUMBER(E13),IF(E13>Parameters!$B$22,1,IF(E13<Parameters!$B$23,-1,0)),0) -> 0 | BL13: =IF(ISNUMBER(C13),IF(C13>=Parameters!$B$24,1,IF(C13<=Parameters!$B$25,-1,0)),0) -> 1 | BM13: =IF(ISNUMBER(AJ13),IF(AND(AJ13>Parameters!$B$26,ISNUMBER(U13)),IF(U13<0,-1,1),0),0) -> 0 | BN13: =IF(ISNUMBER(AD13),IF(AD13>Parameters!$B$27,1,IF(AD13<Parameters!$B$28,-1,0)),0) -> 1 | BO13: =BG13+BH13+BI13+BJ13+BK13+BL13+BM13+BN13 -> 8 | BP13: =IF(ISNUMBER(F13),IF(F13>=Parameters!$B$30,2,IF(F13>=Parameters!$B$31,1,IF(F13<=Parameters!$B$32,-1,0))),0) -> 2 | BQ13: =IF(ISNUMBER(AK13),IF(AK13>Parameters!$B$33,1,IF(AK13<0,-1,0)),0) -> 1 | BR13: =IF(ISNUMBER(AL13),IF(AL13>Parameters!$B$34,1,IF(AL13<0,-1,0)),0) -> 1 | BS13: =IF(ISNUMBER(AP13),IF(AND(AP13>0,AP13<=Parameters!$B$35),1,IF(AP13>Parameters!$B$36,-1,0)),0) -> 1 | BT13: =IF(ISNUMBER(AY13),IF(AY13>Parameters!$B$37,1,IF(AY13<0,-1,0)),0) -> 1 | BU13: =IF(ISNUMBER(AZ13),IF(AZ13>0,1,0),0) -> 0 | BV13: =IF(ISNUMBER(AL13),IF(AL13>Parameters!$B$39,2,IF(AL13>Parameters!$B$40,1,IF(AL13<0,-2,IF(AL13<Parameters!$B$41,-1,0)))),0) -> 1 | BW13: =IF(ISNUMBER(AV13),IF(AV13>Parameters!$B$42,1,IF(AV13<Parameters!$B$43,-1,0)),0) -> 0 | BX13: =IF(AND(ISNUMBER(AX13),AX13>0),1,IF(AND(ISNUMBER(AY13),AY13<Parameters!$B$44),-1,0)) -> 1 | BY13: =IF(ISNUMBER(AW13),IF(AW13>0,1,0),0) -> 1 | BZ13: =IF(ISNUMBER(AQ13),IF(AQ13>Parameters!$B$46,-2,IF(AQ13>Parameters!$B$45,-1,0)),0) -> 0 | CA13: =IF(ISNUMBER(F13),IF(F13>=Parameters!$B$47,1,IF(F13<=Parameters!$B$48,-1,0)),0) -> 1 | CB13: =IF(BF13="Established",BP13+BQ13+BR13+BS13+BT13+BU13,IF(BF13="Early",BV13+BW13+BX13+BY13+BZ13+CA13,0)) -> 6 | CC13: =IF(BF13="Established",BO13+CB13,IF(BF13="Early",BO13+Parameters!$B$50*CB13,BO13)) -> 14 | CD13: =IF(BF13="Established",IF(CC13>=Parameters!$B$51,6,IF(CC13>=Parameters!$B$52,5,IF(CC13>=Parameters!$B$53,4,IF(CC13>=Parameters!$B$54,3,IF(CC13>=Parameters!$B$55,2,1))))),IF(BF13="Early",IF(CC13>=Parameters!$B$56,5,IF(CC13>=Parameters!$B$57,4,IF(CC13>=Parameters!$B$58,3,IF(CC13>=Parameters!$B$59,2,1)))),IF(CC13>=Parameters!$B$60,6,IF(CC13>=Parameters!$B$61,5,IF(CC13>=Parameters!$B$62,4,IF(CC13>=Parameters!$B$63,3,IF(CC13>=Parameters!$B$64,2,1))))))) -> 6 | CE13: =IF(AND(ISNUMBER(AR13),AR13<Parameters!$B$66),1,0) -> 0 | CF13: =IF(AND(LEFT(AH13,5)="Death",ISNUMBER(AG13)),IF(BF13="Early",IF(AND(AG13<Parameters!$B$70,ISNUMBER(U13),U13<Parameters!$B$71),1,0),IF(AND(AG13<Parameters!$B$67,OR(AND(ISNUMBER(U13),U13<Parameters!$B$68),AND(ISNUMBER(V13),V13<Parameters!$B$69))),1,0)),0) -> 0 | CG13: =IF(AND(ISNUMBER(AG13),AG13<0),1,0) -> 0 | CH13: =IF(OR(AND(ISNUMBER(U13),U13>Parameters!$B$74),AND(ISNUMBER(AF13),AF13>Parameters!$B$75),AND(ISNUMBER(AE13),AE13>Parameters!$B$76)),1,0) -> 0 | CI13: =IF(AND(ISNUMBER(BC13),BC13>=0,BC13<=Parameters!$B$77),1,0) -> 0 | CJ13: =IF(CF13=1,1,MIN(CD13,IF(CE13=1,3,6),IF(CG13=1,IF(BF13="Early",Parameters!$B$73,Parameters!$B$72),6),IF(CH13=1,3,6),IF(CI13=1,3,6))) -> 6 | CK13: =INDEX(Parameters!$F$2:$F$7,CJ13) -> Strong Buy | CL13: =IF(CF13=1,"Hard sell: breakdown; ","")&IF(CE13=1,"Insufficient history; ","")&IF(AND(CF13=0,CG13=1),"Below 200D; ","")&IF(CH13=1,"Extended - wait for pullback; ","")&IF(CI13=1,"Earnings within "&Parameters!$B$77&"d; ","")
A14: 005930 | B14: 7 | C14: 6 | D14: 51.6 | E14: 3.2 | F14: 10 | G14: Samsung Electronics Co., Ltd. | H14: Memory | I14: 269000 | J14: KRW | K14: Technology | L14: 1.7696888e+15 | M14: 46233 | N14: -1.66 | O14: 46324 | P14: estimated | Q14: -0.19 | R14: 0 | S14: 7.6 | T14: 1.13 | U14: 12.32 | V14: -10.03 | W14: 43.16 | X14: 286.49 | AC14: -14.67 | AD14: -28.17 | AE14: 53.71 | AF14: 3.24 | AG14: 25.04 | AH14: Golden | AI14: 1718.52 | AJ14: -4.42 | AK14: 1344.4 | AL14: 130 | AM14: 30.84 | AN14: 30.79 | AO14: 3.91 | AP14: 0.03 | AR14: 300 | AS14: 46275 | AT14: 485272047321088 | AU14: 278956985024512 | AV14: 57.48 | AW14: 149669174837248 | AX14: 69550825537536 | AY14: 14.33 | AZ14: 167590313852928 | BA14: 298.52 | BB14: 65.64 | BC14: =IF(AND(ISNUMBER(O14),ISNUMBER(AS14)),O14-AS14,"") -> 49 | BD14: =IF(OR(ISNUMBER(SEARCH("ETF",H14)),AND(F14="",AO14="")),1,0) -> 0 | BE14: =IF(ISNUMBER(L14),IF(L14>=Parameters!$B$3,2,IF(L14>=Parameters!$B$4,1,0)),0)+IF(ISNUMBER(AW14),IF(AW14>0,IF(AND(ISNUMBER(AM14),AM14>=Parameters!$B$5),2,1),0),0)+IF(ISNUMBER(AX14),IF(AND(AX14>0,ISNUMBER(AY14),AY14>=Parameters!$B$6),1,0),0)+IF(ISNUMBER(AO14),IF(AND(AO14>0,AO14<=Parameters!$B$7),1,0),0)+IF(ISNUMBER(F14),IF(F14>=Parameters!$B$8,1,0),0) -> 7 | BF14: =IF(BD14=1,"ETF",IF(OR(AND(ISNUMBER(L14),L14>=Parameters!$B$10),BE14>=Parameters!$B$9),"Established","Early")) -> Established | BG14: =IF(LEFT(AH14,6)="Golden",2,IF(LEFT(AH14,5)="Death",-2,0)) -> 2 | BH14: =IF(ISNUMBER(AG14),IF(AG14>Parameters!$B$12,2,IF(AG14>0,1,IF(AG14>=Parameters!$B$13,-1,-2))),0) -> 2 | BI14: =IF(ISNUMBER(AF14),IF(AND(AF14>=Parameters!$B$14,AF14<=Parameters!$B$15),1,IF(OR(AF14>Parameters!$B$16,AF14<Parameters!$B$17),-1,0)),0) -> 1 | BJ14: =IF(ISNUMBER(AE14),IF(AND(AE14>=Parameters!$B$18,AE14<=Parameters!$B$19),1,IF(OR(AE14>Parameters!$B$20,AE14<Parameters!$B$21),-1,0)),0) -> 1 | BK14: =IF(ISNUMBER(E14),IF(E14>Parameters!$B$22,1,IF(E14<Parameters!$B$23,-1,0)),0) -> 1 | BL14: =IF(ISNUMBER(C14),IF(C14>=Parameters!$B$24,1,IF(C14<=Parameters!$B$25,-1,0)),0) -> 0 | BM14: =IF(ISNUMBER(AJ14),IF(AND(AJ14>Parameters!$B$26,ISNUMBER(U14)),IF(U14<0,-1,1),0),0) -> 0 | BN14: =IF(ISNUMBER(AD14),IF(AD14>Parameters!$B$27,1,IF(AD14<Parameters!$B$28,-1,0)),0) -> 0 | BO14: =BG14+BH14+BI14+BJ14+BK14+BL14+BM14+BN14 -> 7 | BP14: =IF(ISNUMBER(F14),IF(F14>=Parameters!$B$30,2,IF(F14>=Parameters!$B$31,1,IF(F14<=Parameters!$B$32,-1,0))),0) -> 2 | BQ14: =IF(ISNUMBER(AK14),IF(AK14>Parameters!$B$33,1,IF(AK14<0,-1,0)),0) -> 1 | BR14: =IF(ISNUMBER(AL14),IF(AL14>Parameters!$B$34,1,IF(AL14<0,-1,0)),0) -> 1 | BS14: =IF(ISNUMBER(AP14),IF(AND(AP14>0,AP14<=Parameters!$B$35),1,IF(AP14>Parameters!$B$36,-1,0)),0) -> 1 | BT14: =IF(ISNUMBER(AY14),IF(AY14>Parameters!$B$37,1,IF(AY14<0,-1,0)),0) -> 1 | BU14: =IF(ISNUMBER(AZ14),IF(AZ14>0,1,0),0) -> 1 | BV14: =IF(ISNUMBER(AL14),IF(AL14>Parameters!$B$39,2,IF(AL14>Parameters!$B$40,1,IF(AL14<0,-2,IF(AL14<Parameters!$B$41,-1,0)))),0) -> 2 | BW14: =IF(ISNUMBER(AV14),IF(AV14>Parameters!$B$42,1,IF(AV14<Parameters!$B$43,-1,0)),0) -> 1 | BX14: =IF(AND(ISNUMBER(AX14),AX14>0),1,IF(AND(ISNUMBER(AY14),AY14<Parameters!$B$44),-1,0)) -> 1 | BY14: =IF(ISNUMBER(AW14),IF(AW14>0,1,0),0) -> 1 | BZ14: =IF(ISNUMBER(AQ14),IF(AQ14>Parameters!$B$46,-2,IF(AQ14>Parameters!$B$45,-1,0)),0) -> 0 | CA14: =IF(ISNUMBER(F14),IF(F14>=Parameters!$B$47,1,IF(F14<=Parameters!$B$48,-1,0)),0) -> 1 | CB14: =IF(BF14="Established",BP14+BQ14+BR14+BS14+BT14+BU14,IF(BF14="Early",BV14+BW14+BX14+BY14+BZ14+CA14,0)) -> 7 | CC14: =IF(BF14="Established",BO14+CB14,IF(BF14="Early",BO14+Parameters!$B$50*CB14,BO14)) -> 14 | CD14: =IF(BF14="Established",IF(CC14>=Parameters!$B$51,6,IF(CC14>=Parameters!$B$52,5,IF(CC14>=Parameters!$B$53,4,IF(CC14>=Parameters!$B$54,3,IF(CC14>=Parameters!$B$55,2,1))))),IF(BF14="Early",IF(CC14>=Parameters!$B$56,5,IF(CC14>=Parameters!$B$57,4,IF(CC14>=Parameters!$B$58,3,IF(CC14>=Parameters!$B$59,2,1)))),IF(CC14>=Parameters!$B$60,6,IF(CC14>=Parameters!$B$61,5,IF(CC14>=Parameters!$B$62,4,IF(CC14>=Parameters!$B$63,3,IF(CC14>=Parameters!$B$64,2,1))))))) -> 6 | CE14: =IF(AND(ISNUMBER(AR14),AR14<Parameters!$B$66),1,0) -> 0 | CF14: =IF(AND(LEFT(AH14,5)="Death",ISNUMBER(AG14)),IF(BF14="Early",IF(AND(AG14<Parameters!$B$70,ISNUMBER(U14),U14<Parameters!$B$71),1,0),IF(AND(AG14<Parameters!$B$67,OR(AND(ISNUMBER(U14),U14<Parameters!$B$68),AND(ISNUMBER(V14),V14<Parameters!$B$69))),1,0)),0) -> 0 | CG14: =IF(AND(ISNUMBER(AG14),AG14<0),1,0) -> 0 | CH14: =IF(OR(AND(ISNUMBER(U14),U14>Parameters!$B$74),AND(ISNUMBER(AF14),AF14>Parameters!$B$75),AND(ISNUMBER(AE14),AE14>Parameters!$B$76)),1,0) -> 0 | CI14: =IF(AND(ISNUMBER(BC14),BC14>=0,BC14<=Parameters!$B$77),1,0) -> 0 | CJ14: =IF(CF14=1,1,MIN(CD14,IF(CE14=1,3,6),IF(CG14=1,IF(BF14="Early",Parameters!$B$73,Parameters!$B$72),6),IF(CH14=1,3,6),IF(CI14=1,3,6))) -> 6 | CK14: =INDEX(Parameters!$F$2:$F$7,CJ14) -> Strong Buy | CL14: =IF(CF14=1,"Hard sell: breakdown; ","")&IF(CE14=1,"Insufficient history; ","")&IF(AND(CF14=0,CG14=1),"Below 200D; ","")&IF(CH14=1,"Extended - wait for pullback; ","")&IF(CI14=1,"Earnings within "&Parameters!$B$77&"d; ","")
A15: XOM | B15: 7 | C15: 7 | D15: 55.6 | E15: 7.5 | F15: 9 | G15: ExxonMobil Holdings Corporation Common Stock | H15: Energy | I15: 165.52 | J15: USD | K15: Energy | L15: 675299301190 | M15: 46234 | N15: 13.22 | O15: 46325 | P15: estimated | Q15: 0.79 | R15: 2.22 | S15: 0.83 | T15: 4.63 | U15: 3.58 | V15: 9.89 | W15: 9.2 | X15: 49.59 | AC15: 5.25 | AD15: -6.17 | AE15: 60.84 | AF15: 7.08 | AG15: 13.82 | AH15: Golden | AI15: -0.15 | AJ15: -13.99 | AK15: 105.1 | AL15: 44.1 | AM15: 9.07 | AN15: 12.58 | AO15: 15.2 | AP15: 0.19 | AQ15: 0.9 | AR15: 300 | AS15: 46275 | AT15: 361060007936 | AU15: 107475001344 | AV15: 29.77 | AW15: 32757000192 | AX15: 20671000576 | AY15: 5.73 | AZ15: -31779999744 | BA15: 49.94 | BB15: 83.5 | BC15: =IF(AND(ISNUMBER(O15),ISNUMBER(AS15)),O15-AS15,"") -> 50 | BD15: =IF(OR(ISNUMBER(SEARCH("ETF",H15)),AND(F15="",AO15="")),1,0) -> 0 | BE15: =IF(ISNUMBER(L15),IF(L15>=Parameters!$B$3,2,IF(L15>=Parameters!$B$4,1,0)),0)+IF(ISNUMBER(AW15),IF(AW15>0,IF(AND(ISNUMBER(AM15),AM15>=Parameters!$B$5),2,1),0),0)+IF(ISNUMBER(AX15),IF(AND(AX15>0,ISNUMBER(AY15),AY15>=Parameters!$B$6),1,0),0)+IF(ISNUMBER(AO15),IF(AND(AO15>0,AO15<=Parameters!$B$7),1,0),0)+IF(ISNUMBER(F15),IF(F15>=Parameters!$B$8,1,0),0) -> 7 | BF15: =IF(BD15=1,"ETF",IF(OR(AND(ISNUMBER(L15),L15>=Parameters!$B$10),BE15>=Parameters!$B$9),"Established","Early")) -> Established | BG15: =IF(LEFT(AH15,6)="Golden",2,IF(LEFT(AH15,5)="Death",-2,0)) -> 2 | BH15: =IF(ISNUMBER(AG15),IF(AG15>Parameters!$B$12,2,IF(AG15>0,1,IF(AG15>=Parameters!$B$13,-1,-2))),0) -> 2 | BI15: =IF(ISNUMBER(AF15),IF(AND(AF15>=Parameters!$B$14,AF15<=Parameters!$B$15),1,IF(OR(AF15>Parameters!$B$16,AF15<Parameters!$B$17),-1,0)),0) -> 1 | BJ15: =IF(ISNUMBER(AE15),IF(AND(AE15>=Parameters!$B$18,AE15<=Parameters!$B$19),1,IF(OR(AE15>Parameters!$B$20,AE15<Parameters!$B$21),-1,0)),0) -> 1 | BK15: =IF(ISNUMBER(E15),IF(E15>Parameters!$B$22,1,IF(E15<Parameters!$B$23,-1,0)),0) -> 1 | BL15: =IF(ISNUMBER(C15),IF(C15>=Parameters!$B$24,1,IF(C15<=Parameters!$B$25,-1,0)),0) -> 1 | BM15: =IF(ISNUMBER(AJ15),IF(AND(AJ15>Parameters!$B$26,ISNUMBER(U15)),IF(U15<0,-1,1),0),0) -> 0 | BN15: =IF(ISNUMBER(AD15),IF(AD15>Parameters!$B$27,1,IF(AD15<Parameters!$B$28,-1,0)),0) -> 1 | BO15: =BG15+BH15+BI15+BJ15+BK15+BL15+BM15+BN15 -> 9 | BP15: =IF(ISNUMBER(F15),IF(F15>=Parameters!$B$30,2,IF(F15>=Parameters!$B$31,1,IF(F15<=Parameters!$B$32,-1,0))),0) -> 2 | BQ15: =IF(ISNUMBER(AK15),IF(AK15>Parameters!$B$33,1,IF(AK15<0,-1,0)),0) -> 1 | BR15: =IF(ISNUMBER(AL15),IF(AL15>Parameters!$B$34,1,IF(AL15<0,-1,0)),0) -> 1 | BS15: =IF(ISNUMBER(AP15),IF(AND(AP15>0,AP15<=Parameters!$B$35),1,IF(AP15>Parameters!$B$36,-1,0)),0) -> 1 | BT15: =IF(ISNUMBER(AY15),IF(AY15>Parameters!$B$37,1,IF(AY15<0,-1,0)),0) -> 0 | BU15: =IF(ISNUMBER(AZ15),IF(AZ15>0,1,0),0) -> 0 | BV15: =IF(ISNUMBER(AL15),IF(AL15>Parameters!$B$39,2,IF(AL15>Parameters!$B$40,1,IF(AL15<0,-2,IF(AL15<Parameters!$B$41,-1,0)))),0) -> 2 | BW15: =IF(ISNUMBER(AV15),IF(AV15>Parameters!$B$42,1,IF(AV15<Parameters!$B$43,-1,0)),0) -> 0 | BX15: =IF(AND(ISNUMBER(AX15),AX15>0),1,IF(AND(ISNUMBER(AY15),AY15<Parameters!$B$44),-1,0)) -> 1 | BY15: =IF(ISNUMBER(AW15),IF(AW15>0,1,0),0) -> 1 | BZ15: =IF(ISNUMBER(AQ15),IF(AQ15>Parameters!$B$46,-2,IF(AQ15>Parameters!$B$45,-1,0)),0) -> 0 | CA15: =IF(ISNUMBER(F15),IF(F15>=Parameters!$B$47,1,IF(F15<=Parameters!$B$48,-1,0)),0) -> 1 | CB15: =IF(BF15="Established",BP15+BQ15+BR15+BS15+BT15+BU15,IF(BF15="Early",BV15+BW15+BX15+BY15+BZ15+CA15,0)) -> 5 | CC15: =IF(BF15="Established",BO15+CB15,IF(BF15="Early",BO15+Parameters!$B$50*CB15,BO15)) -> 14 | CD15: =IF(BF15="Established",IF(CC15>=Parameters!$B$51,6,IF(CC15>=Parameters!$B$52,5,IF(CC15>=Parameters!$B$53,4,IF(CC15>=Parameters!$B$54,3,IF(CC15>=Parameters!$B$55,2,1))))),IF(BF15="Early",IF(CC15>=Parameters!$B$56,5,IF(CC15>=Parameters!$B$57,4,IF(CC15>=Parameters!$B$58,3,IF(CC15>=Parameters!$B$59,2,1)))),IF(CC15>=Parameters!$B$60,6,IF(CC15>=Parameters!$B$61,5,IF(CC15>=Parameters!$B$62,4,IF(CC15>=Parameters!$B$63,3,IF(CC15>=Parameters!$B$64,2,1))))))) -> 6 | CE15: =IF(AND(ISNUMBER(AR15),AR15<Parameters!$B$66),1,0) -> 0 | CF15: =IF(AND(LEFT(AH15,5)="Death",ISNUMBER(AG15)),IF(BF15="Early",IF(AND(AG15<Parameters!$B$70,ISNUMBER(U15),U15<Parameters!$B$71),1,0),IF(AND(AG15<Parameters!$B$67,OR(AND(ISNUMBER(U15),U15<Parameters!$B$68),AND(ISNUMBER(V15),V15<Parameters!$B$69))),1,0)),0) -> 0 | CG15: =IF(AND(ISNUMBER(AG15),AG15<0),1,0) -> 0 | CH15: =IF(OR(AND(ISNUMBER(U15),U15>Parameters!$B$74),AND(ISNUMBER(AF15),AF15>Parameters!$B$75),AND(ISNUMBER(AE15),AE15>Parameters!$B$76)),1,0) -> 0 | CI15: =IF(AND(ISNUMBER(BC15),BC15>=0,BC15<=Parameters!$B$77),1,0) -> 0 | CJ15: =IF(CF15=1,1,MIN(CD15,IF(CE15=1,3,6),IF(CG15=1,IF(BF15="Early",Parameters!$B$73,Parameters!$B$72),6),IF(CH15=1,3,6),IF(CI15=1,3,6))) -> 6 | CK15: =INDEX(Parameters!$F$2:$F$7,CJ15) -> Strong Buy | CL15: =IF(CF15=1,"Hard sell: breakdown; ","")&IF(CE15=1,"Insufficient history; ","")&IF(AND(CF15=0,CG15=1),"Below 200D; ","")&IF(CH15=1,"Extended - wait for pullback; ","")&IF(CI15=1,"Earnings within "&Parameters!$B$77&"d; ","")
A16: XLE | B16: 7 | C16: 7 | D16: 63.4 | E16: 7 | G16: State Street Energy Select Sector SPDR ETF | H16: Energy | I16: 65.16 | J16: USD | L16: 10783696896 | M16: 46122 | N16: -12.5 | O16: 46213 | P16: estimated | Q16: -0.24 | R16: 0.83 | S16: 0.08 | T16: 4.36 | U16: 6.93 | V16: 11.85 | W16: 14.35 | X16: 48.79 | AC16: 7.21 | AD16: -1.56 | AE16: 67.03 | AF16: 8.78 | AG16: 18.18 | AH16: Golden | AI16: 0.01 | AJ16: -12.8 | AR16: 300 | AS16: 46275 | AT16: 0 | AU16: 0 | AW16: 0 | AX16: 0 | AZ16: 0 | BA16: 53.85 | BB16: 95.66 | BC16: =IF(AND(ISNUMBER(O16),ISNUMBER(AS16)),O16-AS16,"") -> -62 | BD16: =IF(OR(ISNUMBER(SEARCH("ETF",H16)),AND(F16="",AO16="")),1,0) -> 1 | BE16: =IF(ISNUMBER(L16),IF(L16>=Parameters!$B$3,2,IF(L16>=Parameters!$B$4,1,0)),0)+IF(ISNUMBER(AW16),IF(AW16>0,IF(AND(ISNUMBER(AM16),AM16>=Parameters!$B$5),2,1),0),0)+IF(ISNUMBER(AX16),IF(AND(AX16>0,ISNUMBER(AY16),AY16>=Parameters!$B$6),1,0),0)+IF(ISNUMBER(AO16),IF(AND(AO16>0,AO16<=Parameters!$B$7),1,0),0)+IF(ISNUMBER(F16),IF(F16>=Parameters!$B$8,1,0),0) -> 0 | BF16: =IF(BD16=1,"ETF",IF(OR(AND(ISNUMBER(L16),L16>=Parameters!$B$10),BE16>=Parameters!$B$9),"Established","Early")) -> ETF | BG16: =IF(LEFT(AH16,6)="Golden",2,IF(LEFT(AH16,5)="Death",-2,0)) -> 2 | BH16: =IF(ISNUMBER(AG16),IF(AG16>Parameters!$B$12,2,IF(AG16>0,1,IF(AG16>=Parameters!$B$13,-1,-2))),0) -> 2 | BI16: =IF(ISNUMBER(AF16),IF(AND(AF16>=Parameters!$B$14,AF16<=Parameters!$B$15),1,IF(OR(AF16>Parameters!$B$16,AF16<Parameters!$B$17),-1,0)),0) -> 0 | BJ16: =IF(ISNUMBER(AE16),IF(AND(AE16>=Parameters!$B$18,AE16<=Parameters!$B$19),1,IF(OR(AE16>Parameters!$B$20,AE16<Parameters!$B$21),-1,0)),0) -> 0 | BK16: =IF(ISNUMBER(E16),IF(E16>Parameters!$B$22,1,IF(E16<Parameters!$B$23,-1,0)),0) -> 1 | BL16: =IF(ISNUMBER(C16),IF(C16>=Parameters!$B$24,1,IF(C16<=Parameters!$B$25,-1,0)),0) -> 1 | BM16: =IF(ISNUMBER(AJ16),IF(AND(AJ16>Parameters!$B$26,ISNUMBER(U16)),IF(U16<0,-1,1),0),0) -> 0 | BN16: =IF(ISNUMBER(AD16),IF(AD16>Parameters!$B$27,1,IF(AD16<Parameters!$B$28,-1,0)),0) -> 1 | BO16: =BG16+BH16+BI16+BJ16+BK16+BL16+BM16+BN16 -> 7 | BP16: =IF(ISNUMBER(F16),IF(F16>=Parameters!$B$30,2,IF(F16>=Parameters!$B$31,1,IF(F16<=Parameters!$B$32,-1,0))),0) -> 0 | BQ16: =IF(ISNUMBER(AK16),IF(AK16>Parameters!$B$33,1,IF(AK16<0,-1,0)),0) -> 0 | BR16: =IF(ISNUMBER(AL16),IF(AL16>Parameters!$B$34,1,IF(AL16<0,-1,0)),0) -> 0 | BS16: =IF(ISNUMBER(AP16),IF(AND(AP16>0,AP16<=Parameters!$B$35),1,IF(AP16>Parameters!$B$36,-1,0)),0) -> 0 | BT16: =IF(ISNUMBER(AY16),IF(AY16>Parameters!$B$37,1,IF(AY16<0,-1,0)),0) -> 0 | BU16: =IF(ISNUMBER(AZ16),IF(AZ16>0,1,0),0) -> 0 | BV16: =IF(ISNUMBER(AL16),IF(AL16>Parameters!$B$39,2,IF(AL16>Parameters!$B$40,1,IF(AL16<0,-2,IF(AL16<Parameters!$B$41,-1,0)))),0) -> 0 | BW16: =IF(ISNUMBER(AV16),IF(AV16>Parameters!$B$42,1,IF(AV16<Parameters!$B$43,-1,0)),0) -> 0 | BX16: =IF(AND(ISNUMBER(AX16),AX16>0),1,IF(AND(ISNUMBER(AY16),AY16<Parameters!$B$44),-1,0)) -> 0 | BY16: =IF(ISNUMBER(AW16),IF(AW16>0,1,0),0) -> 0 | BZ16: =IF(ISNUMBER(AQ16),IF(AQ16>Parameters!$B$46,-2,IF(AQ16>Parameters!$B$45,-1,0)),0) -> 0 | CA16: =IF(ISNUMBER(F16),IF(F16>=Parameters!$B$47,1,IF(F16<=Parameters!$B$48,-1,0)),0) -> 0 | CB16: =IF(BF16="Established",BP16+BQ16+BR16+BS16+BT16+BU16,IF(BF16="Early",BV16+BW16+BX16+BY16+BZ16+CA16,0)) -> 0 | CC16: =IF(BF16="Established",BO16+CB16,IF(BF16="Early",BO16+Parameters!$B$50*CB16,BO16)) -> 7 | CD16: =IF(BF16="Established",IF(CC16>=Parameters!$B$51,6,IF(CC16>=Parameters!$B$52,5,IF(CC16>=Parameters!$B$53,4,IF(CC16>=Parameters!$B$54,3,IF(CC16>=Parameters!$B$55,2,1))))),IF(BF16="Early",IF(CC16>=Parameters!$B$56,5,IF(CC16>=Parameters!$B$57,4,IF(CC16>=Parameters!$B$58,3,IF(CC16>=Parameters!$B$59,2,1)))),IF(CC16>=Parameters!$B$60,6,IF(CC16>=Parameters!$B$61,5,IF(CC16>=Parameters!$B$62,4,IF(CC16>=Parameters!$B$63,3,IF(CC16>=Parameters!$B$64,2,1))))))) -> 5 | CE16: =IF(AND(ISNUMBER(AR16),AR16<Parameters!$B$66),1,0) -> 0 | CF16: =IF(AND(LEFT(AH16,5)="Death",ISNUMBER(AG16)),IF(BF16="Early",IF(AND(AG16<Parameters!$B$70,ISNUMBER(U16),U16<Parameters!$B$71),1,0),IF(AND(AG16<Parameters!$B$67,OR(AND(ISNUMBER(U16),U16<Parameters!$B$68),AND(ISNUMBER(V16),V16<Parameters!$B$69))),1,0)),0) -> 0 | CG16: =IF(AND(ISNUMBER(AG16),AG16<0),1,0) -> 0 | CH16: =IF(OR(AND(ISNUMBER(U16),U16>Parameters!$B$74),AND(ISNUMBER(AF16),AF16>Parameters!$B$75),AND(ISNUMBER(AE16),AE16>Parameters!$B$76)),1,0) -> 0 | CI16: =IF(AND(ISNUMBER(BC16),BC16>=0,BC16<=Parameters!$B$77),1,0) -> 0 | CJ16: =IF(CF16=1,1,MIN(CD16,IF(CE16=1,3,6),IF(CG16=1,IF(BF16="Early",Parameters!$B$73,Parameters!$B$72),6),IF(CH16=1,3,6),IF(CI16=1,3,6))) -> 5 | CK16: =INDEX(Parameters!$F$2:$F$7,CJ16) -> Buy | CL16: =IF(CF16=1,"Hard sell: breakdown; ","")&IF(CE16=1,"Insufficient history; ","")&IF(AND(CF16=0,CG16=1),"Below 200D; ","")&IF(CH16=1,"Extended - wait for pullback; ","")&IF(CI16=1,"Earnings within "&Parameters!$B$77&"d; ","")
A17: MRVL | B17: 7 | C17: 7 | D17: 67.7 | E17: -4.3 | F17: 8 | G17: Marvell Technology, Inc. | H17: Chips | I17: 229.53 | J17: USD | K17: Technology | L17: 211204566158 | M17: 46261 | N17: 1.08 | O17: 46352 | P17: estimated | Q17: -2.33 | R17: 4.26 | S17: 11.16 | T17: -6.36 | U17: 8.11 | V17: -9.13 | W17: 153.79 | X17: 243.4 | AC17: -13.77 | AD17: -30.42 | AE17: 53.02 | AF17: 5.47 | AG17: 49.01 | AH17: Golden | AI17: 0.19 | AJ17: -30.74 | AK17: 58.1 | AL17: 36.5 | AM17: 27.93 | AN17: 16.52 | AO17: 34.26 | AP17: 1.59 | AQ17: 3.25 | AR17: 300 | AS17: 46275 | AT17: 9450300416 | AU17: 4934600192 | AV17: 52.22 | AW17: 2639899904 | AX17: 2408049920 | AY17: 25.48 | AZ17: -1353299968 | BA17: 247.04 | BB17: 61.95 | BC17: =IF(AND(ISNUMBER(O17),ISNUMBER(AS17)),O17-AS17,"") -> 77 | BD17: =IF(OR(ISNUMBER(SEARCH("ETF",H17)),AND(F17="",AO17="")),1,0) -> 0 | BE17: =IF(ISNUMBER(L17),IF(L17>=Parameters!$B$3,2,IF(L17>=Parameters!$B$4,1,0)),0)+IF(ISNUMBER(AW17),IF(AW17>0,IF(AND(ISNUMBER(AM17),AM17>=Parameters!$B$5),2,1),0),0)+IF(ISNUMBER(AX17),IF(AND(AX17>0,ISNUMBER(AY17),AY17>=Parameters!$B$6),1,0),0)+IF(ISNUMBER(AO17),IF(AND(AO17>0,AO17<=Parameters!$B$7),1,0),0)+IF(ISNUMBER(F17),IF(F17>=Parameters!$B$8,1,0),0) -> 7 | BF17: =IF(BD17=1,"ETF",IF(OR(AND(ISNUMBER(L17),L17>=Parameters!$B$10),BE17>=Parameters!$B$9),"Established","Early")) -> Established | BG17: =IF(LEFT(AH17,6)="Golden",2,IF(LEFT(AH17,5)="Death",-2,0)) -> 2 | BH17: =IF(ISNUMBER(AG17),IF(AG17>Parameters!$B$12,2,IF(AG17>0,1,IF(AG17>=Parameters!$B$13,-1,-2))),0) -> 2 | BI17: =IF(ISNUMBER(AF17),IF(AND(AF17>=Parameters!$B$14,AF17<=Parameters!$B$15),1,IF(OR(AF17>Parameters!$B$16,AF17<Parameters!$B$17),-1,0)),0) -> 1 | BJ17: =IF(ISNUMBER(AE17),IF(AND(AE17>=Parameters!$B$18,AE17<=Parameters!$B$19),1,IF(OR(AE17>Parameters!$B$20,AE17<Parameters!$B$21),-1,0)),0) -> 1 | BK17: =IF(ISNUMBER(E17),IF(E17>Parameters!$B$22,1,IF(E17<Parameters!$B$23,-1,0)),0) -> 0 | BL17: =IF(ISNUMBER(C17),IF(C17>=Parameters!$B$24,1,IF(C17<=Parameters!$B$25,-1,0)),0) -> 1 | BM17: =IF(ISNUMBER(AJ17),IF(AND(AJ17>Parameters!$B$26,ISNUMBER(U17)),IF(U17<0,-1,1),0),0) -> 0 | BN17: =IF(ISNUMBER(AD17),IF(AD17>Parameters!$B$27,1,IF(AD17<Parameters!$B$28,-1,0)),0) -> -1 | BO17: =BG17+BH17+BI17+BJ17+BK17+BL17+BM17+BN17 -> 6 | BP17: =IF(ISNUMBER(F17),IF(F17>=Parameters!$B$30,2,IF(F17>=Parameters!$B$31,1,IF(F17<=Parameters!$B$32,-1,0))),0) -> 2 | BQ17: =IF(ISNUMBER(AK17),IF(AK17>Parameters!$B$33,1,IF(AK17<0,-1,0)),0) -> 1 | BR17: =IF(ISNUMBER(AL17),IF(AL17>Parameters!$B$34,1,IF(AL17<0,-1,0)),0) -> 1 | BS17: =IF(ISNUMBER(AP17),IF(AND(AP17>0,AP17<=Parameters!$B$35),1,IF(AP17>Parameters!$B$36,-1,0)),0) -> 0 | BT17: =IF(ISNUMBER(AY17),IF(AY17>Parameters!$B$37,1,IF(AY17<0,-1,0)),0) -> 1 | BU17: =IF(ISNUMBER(AZ17),IF(AZ17>0,1,0),0) -> 0 | BV17: =IF(ISNUMBER(AL17),IF(AL17>Parameters!$B$39,2,IF(AL17>Parameters!$B$40,1,IF(AL17<0,-2,IF(AL17<Parameters!$B$41,-1,0)))),0) -> 2 | BW17: =IF(ISNUMBER(AV17),IF(AV17>Parameters!$B$42,1,IF(AV17<Parameters!$B$43,-1,0)),0) -> 1 | BX17: =IF(AND(ISNUMBER(AX17),AX17>0),1,IF(AND(ISNUMBER(AY17),AY17<Parameters!$B$44),-1,0)) -> 1 | BY17: =IF(ISNUMBER(AW17),IF(AW17>0,1,0),0) -> 1 | BZ17: =IF(ISNUMBER(AQ17),IF(AQ17>Parameters!$B$46,-2,IF(AQ17>Parameters!$B$45,-1,0)),0) -> 0 | CA17: =IF(ISNUMBER(F17),IF(F17>=Parameters!$B$47,1,IF(F17<=Parameters!$B$48,-1,0)),0) -> 1 | CB17: =IF(BF17="Established",BP17+BQ17+BR17+BS17+BT17+BU17,IF(BF17="Early",BV17+BW17+BX17+BY17+BZ17+CA17,0)) -> 5 | CC17: =IF(BF17="Established",BO17+CB17,IF(BF17="Early",BO17+Parameters!$B$50*CB17,BO17)) -> 11 | CD17: =IF(BF17="Established",IF(CC17>=Parameters!$B$51,6,IF(CC17>=Parameters!$B$52,5,IF(CC17>=Parameters!$B$53,4,IF(CC17>=Parameters!$B$54,3,IF(CC17>=Parameters!$B$55,2,1))))),IF(BF17="Early",IF(CC17>=Parameters!$B$56,5,IF(CC17>=Parameters!$B$57,4,IF(CC17>=Parameters!$B$58,3,IF(CC17>=Parameters!$B$59,2,1)))),IF(CC17>=Parameters!$B$60,6,IF(CC17>=Parameters!$B$61,5,IF(CC17>=Parameters!$B$62,4,IF(CC17>=Parameters!$B$63,3,IF(CC17>=Parameters!$B$64,2,1))))))) -> 5 | CE17: =IF(AND(ISNUMBER(AR17),AR17<Parameters!$B$66),1,0) -> 0 | CF17: =IF(AND(LEFT(AH17,5)="Death",ISNUMBER(AG17)),IF(BF17="Early",IF(AND(AG17<Parameters!$B$70,ISNUMBER(U17),U17<Parameters!$B$71),1,0),IF(AND(AG17<Parameters!$B$67,OR(AND(ISNUMBER(U17),U17<Parameters!$B$68),AND(ISNUMBER(V17),V17<Parameters!$B$69))),1,0)),0) -> 0 | CG17: =IF(AND(ISNUMBER(AG17),AG17<0),1,0) -> 0 | CH17: =IF(OR(AND(ISNUMBER(U17),U17>Parameters!$B$74),AND(ISNUMBER(AF17),AF17>Parameters!$B$75),AND(ISNUMBER(AE17),AE17>Parameters!$B$76)),1,0) -> 0 | CI17: =IF(AND(ISNUMBER(BC17),BC17>=0,BC17<=Parameters!$B$77),1,0) -> 0 | CJ17: =IF(CF17=1,1,MIN(CD17,IF(CE17=1,3,6),IF(CG17=1,IF(BF17="Early",Parameters!$B$73,Parameters!$B$72),6),IF(CH17=1,3,6),IF(CI17=1,3,6))) -> 5 | CK17: =INDEX(Parameters!$F$2:$F$7,CJ17) -> Buy | CL17: =IF(CF17=1,"Hard sell: breakdown; ","")&IF(CE17=1,"Insufficient history; ","")&IF(AND(CF17=0,CG17=1),"Below 200D; ","")&IF(CH17=1,"Extended - wait for pullback; ","")&IF(CI17=1,"Earnings within "&Parameters!$B$77&"d; ","")
A18: LRCX | B18: 7 | C18: 6 | D18: 51.9 | E18: 6.7 | F18: 9 | G18: Lam Research Corp. | H18: Chips | I18: 300.89 | J18: USD | K18: Technology | L18: 395217224639 | M18: 46232 | N18: 8.33 | O18: 46323 | P18: estimated | Q18: -4.73 | R18: -1.43 | S18: 4.36 | T18: -3.83 | U18: -3.38 | V18: -6.5 | W18: 37.47 | X18: 185.01 | AC18: -11.14 | AD18: -31.38 | AE18: 46.05 | AF18: -4.83 | AG18: 14.22 | AH18: Golden | AI18: 0.55 | AJ18: -14.39 | AK18: 32.4 | AL18: 30 | AM18: 31.27 | AN18: 65.07 | AO18: 27.69 | AP18: 1.6 | AQ18: 2.28 | AR18: 300 | AS18: 46275 | AT18: 23232690176 | AU18: 11725307904 | AV18: 50.47 | AW18: 7265396224 | AX18: 3090484480 | AY18: 13.3 | AZ18: 1457605888 | BA18: 187.63 | BB18: 58.79 | BC18: =IF(AND(ISNUMBER(O18),ISNUMBER(AS18)),O18-AS18,"") -> 48 | BD18: =IF(OR(ISNUMBER(SEARCH("ETF",H18)),AND(F18="",AO18="")),1,0) -> 0 | BE18: =IF(ISNUMBER(L18),IF(L18>=Parameters!$B$3,2,IF(L18>=Parameters!$B$4,1,0)),0)+IF(ISNUMBER(AW18),IF(AW18>0,IF(AND(ISNUMBER(AM18),AM18>=Parameters!$B$5),2,1),0),0)+IF(ISNUMBER(AX18),IF(AND(AX18>0,ISNUMBER(AY18),AY18>=Parameters!$B$6),1,0),0)+IF(ISNUMBER(AO18),IF(AND(AO18>0,AO18<=Parameters!$B$7),1,0),0)+IF(ISNUMBER(F18),IF(F18>=Parameters!$B$8,1,0),0) -> 7 | BF18: =IF(BD18=1,"ETF",IF(OR(AND(ISNUMBER(L18),L18>=Parameters!$B$10),BE18>=Parameters!$B$9),"Established","Early")) -> Established | BG18: =IF(LEFT(AH18,6)="Golden",2,IF(LEFT(AH18,5)="Death",-2,0)) -> 2 | BH18: =IF(ISNUMBER(AG18),IF(AG18>Parameters!$B$12,2,IF(AG18>0,1,IF(AG18>=Parameters!$B$13,-1,-2))),0) -> 2 | BI18: =IF(ISNUMBER(AF18),IF(AND(AF18>=Parameters!$B$14,AF18<=Parameters!$B$15),1,IF(OR(AF18>Parameters!$B$16,AF18<Parameters!$B$17),-1,0)),0) -> 0 | BJ18: =IF(ISNUMBER(AE18),IF(AND(AE18>=Parameters!$B$18,AE18<=Parameters!$B$19),1,IF(OR(AE18>Parameters!$B$20,AE18<Parameters!$B$21),-1,0)),0) -> 1 | BK18: =IF(ISNUMBER(E18),IF(E18>Parameters!$B$22,1,IF(E18<Parameters!$B$23,-1,0)),0) -> 1 | BL18: =IF(ISNUMBER(C18),IF(C18>=Parameters!$B$24,1,IF(C18<=Parameters!$B$25,-1,0)),0) -> 0 | BM18: =IF(ISNUMBER(AJ18),IF(AND(AJ18>Parameters!$B$26,ISNUMBER(U18)),IF(U18<0,-1,1),0),0) -> 0 | BN18: =IF(ISNUMBER(AD18),IF(AD18>Parameters!$B$27,1,IF(AD18<Parameters!$B$28,-1,0)),0) -> -1 | BO18: =BG18+BH18+BI18+BJ18+BK18+BL18+BM18+BN18 -> 5 | BP18: =IF(ISNUMBER(F18),IF(F18>=Parameters!$B$30,2,IF(F18>=Parameters!$B$31,1,IF(F18<=Parameters!$B$32,-1,0))),0) -> 2 | BQ18: =IF(ISNUMBER(AK18),IF(AK18>Parameters!$B$33,1,IF(AK18<0,-1,0)),0) -> 1 | BR18: =IF(ISNUMBER(AL18),IF(AL18>Parameters!$B$34,1,IF(AL18<0,-1,0)),0) -> 1 | BS18: =IF(ISNUMBER(AP18),IF(AND(AP18>0,AP18<=Parameters!$B$35),1,IF(AP18>Parameters!$B$36,-1,0)),0) -> 0 | BT18: =IF(ISNUMBER(AY18),IF(AY18>Parameters!$B$37,1,IF(AY18<0,-1,0)),0) -> 1 | BU18: =IF(ISNUMBER(AZ18),IF(AZ18>0,1,0),0) -> 1 | BV18: =IF(ISNUMBER(AL18),IF(AL18>Parameters!$B$39,2,IF(AL18>Parameters!$B$40,1,IF(AL18<0,-2,IF(AL18<Parameters!$B$41,-1,0)))),0) -> 1 | BW18: =IF(ISNUMBER(AV18),IF(AV18>Parameters!$B$42,1,IF(AV18<Parameters!$B$43,-1,0)),0) -> 1 | BX18: =IF(AND(ISNUMBER(AX18),AX18>0),1,IF(AND(ISNUMBER(AY18),AY18<Parameters!$B$44),-1,0)) -> 1 | BY18: =IF(ISNUMBER(AW18),IF(AW18>0,1,0),0) -> 1 | BZ18: =IF(ISNUMBER(AQ18),IF(AQ18>Parameters!$B$46,-2,IF(AQ18>Parameters!$B$45,-1,0)),0) -> 0 | CA18: =IF(ISNUMBER(F18),IF(F18>=Parameters!$B$47,1,IF(F18<=Parameters!$B$48,-1,0)),0) -> 1 | CB18: =IF(BF18="Established",BP18+BQ18+BR18+BS18+BT18+BU18,IF(BF18="Early",BV18+BW18+BX18+BY18+BZ18+CA18,0)) -> 6 | CC18: =IF(BF18="Established",BO18+CB18,IF(BF18="Early",BO18+Parameters!$B$50*CB18,BO18)) -> 11 | CD18: =IF(BF18="Established",IF(CC18>=Parameters!$B$51,6,IF(CC18>=Parameters!$B$52,5,IF(CC18>=Parameters!$B$53,4,IF(CC18>=Parameters!$B$54,3,IF(CC18>=Parameters!$B$55,2,1))))),IF(BF18="Early",IF(CC18>=Parameters!$B$56,5,IF(CC18>=Parameters!$B$57,4,IF(CC18>=Parameters!$B$58,3,IF(CC18>=Parameters!$B$59,2,1)))),IF(CC18>=Parameters!$B$60,6,IF(CC18>=Parameters!$B$61,5,IF(CC18>=Parameters!$B$62,4,IF(CC18>=Parameters!$B$63,3,IF(CC18>=Parameters!$B$64,2,1))))))) -> 5 | CE18: =IF(AND(ISNUMBER(AR18),AR18<Parameters!$B$66),1,0) -> 0 | CF18: =IF(AND(LEFT(AH18,5)="Death",ISNUMBER(AG18)),IF(BF18="Early",IF(AND(AG18<Parameters!$B$70,ISNUMBER(U18),U18<Parameters!$B$71),1,0),IF(AND(AG18<Parameters!$B$67,OR(AND(ISNUMBER(U18),U18<Parameters!$B$68),AND(ISNUMBER(V18),V18<Parameters!$B$69))),1,0)),0) -> 0 | CG18: =IF(AND(ISNUMBER(AG18),AG18<0),1,0) -> 0 | CH18: =IF(OR(AND(ISNUMBER(U18),U18>Parameters!$B$74),AND(ISNUMBER(AF18),AF18>Parameters!$B$75),AND(ISNUMBER(AE18),AE18>Parameters!$B$76)),1,0) -> 0 | CI18: =IF(AND(ISNUMBER(BC18),BC18>=0,BC18<=Parameters!$B$77),1,0) -> 0 | CJ18: =IF(CF18=1,1,MIN(CD18,IF(CE18=1,3,6),IF(CG18=1,IF(BF18="Early",Parameters!$B$73,Parameters!$B$72),6),IF(CH18=1,3,6),IF(CI18=1,3,6))) -> 5 | CK18: =INDEX(Parameters!$F$2:$F$7,CJ18) -> Buy | CL18: =IF(CF18=1,"Hard sell: breakdown; ","")&IF(CE18=1,"Insufficient history; ","")&IF(AND(CF18=0,CG18=1),"Below 200D; ","")&IF(CH18=1,"Extended - wait for pullback; ","")&IF(CI18=1,"Earnings within "&Parameters!$B$77&"d; ","")
A19: NVDA | B19: 7 | C19: 6 | D19: 35.5 | E19: 16 | F19: 10 | G19: NVIDIA Corporation | H19: Mag 7; Chips | I19: 218.6 | J19: USD | K19: Technology | L19: 5400959490000 | M19: 46260 | N19: 6.22 | O19: 46351 | P19: estimated | Q19: -2.27 | R19: -0.91 | S19: -2.59 | T19: 4.26 | U19: 0.5 | V19: 9.07 | W19: 17.51 | X19: 28.01 | AC19: 4.43 | AD19: -7.59 | AE19: 49.99 | AF19: 3.03 | AG19: 10.81 | AH19: Golden | AI19: -0.13 | AJ19: -22.34 | AK19: 125.9 | AL19: 105.9 | AM19: 63.66 | AN19: 117.21 | AO19: 14.84 | AP19: 0.23 | AQ19: 1.24 | AR19: 300 | AS19: 46275 | AT19: 302970011648 | AU19: 226241003520 | AV19: 74.67 | AW19: 192880001024 | AX19: 41809874944 | AY19: 13.8 | AZ19: 23608999936 | BA19: 33.07 | BB19: 75.17 | BC19: =IF(AND(ISNUMBER(O19),ISNUMBER(AS19)),O19-AS19,"") -> 76 | BD19: =IF(OR(ISNUMBER(SEARCH("ETF",H19)),AND(F19="",AO19="")),1,0) -> 0 | BE19: =IF(ISNUMBER(L19),IF(L19>=Parameters!$B$3,2,IF(L19>=Parameters!$B$4,1,0)),0)+IF(ISNUMBER(AW19),IF(AW19>0,IF(AND(ISNUMBER(AM19),AM19>=Parameters!$B$5),2,1),0),0)+IF(ISNUMBER(AX19),IF(AND(AX19>0,ISNUMBER(AY19),AY19>=Parameters!$B$6),1,0),0)+IF(ISNUMBER(AO19),IF(AND(AO19>0,AO19<=Parameters!$B$7),1,0),0)+IF(ISNUMBER(F19),IF(F19>=Parameters!$B$8,1,0),0) -> 7 | BF19: =IF(BD19=1,"ETF",IF(OR(AND(ISNUMBER(L19),L19>=Parameters!$B$10),BE19>=Parameters!$B$9),"Established","Early")) -> Established | BG19: =IF(LEFT(AH19,6)="Golden",2,IF(LEFT(AH19,5)="Death",-2,0)) -> 2 | BH19: =IF(ISNUMBER(AG19),IF(AG19>Parameters!$B$12,2,IF(AG19>0,1,IF(AG19>=Parameters!$B$13,-1,-2))),0) -> 2 | BI19: =IF(ISNUMBER(AF19),IF(AND(AF19>=Parameters!$B$14,AF19<=Parameters!$B$15),1,IF(OR(AF19>Parameters!$B$16,AF19<Parameters!$B$17),-1,0)),0) -> 1 | BJ19: =IF(ISNUMBER(AE19),IF(AND(AE19>=Parameters!$B$18,AE19<=Parameters!$B$19),1,IF(OR(AE19>Parameters!$B$20,AE19<Parameters!$B$21),-1,0)),0) -> 1 | BK19: =IF(ISNUMBER(E19),IF(E19>Parameters!$B$22,1,IF(E19<Parameters!$B$23,-1,0)),0) -> 1 | BL19: =IF(ISNUMBER(C19),IF(C19>=Parameters!$B$24,1,IF(C19<=Parameters!$B$25,-1,0)),0) -> 0 | BM19: =IF(ISNUMBER(AJ19),IF(AND(AJ19>Parameters!$B$26,ISNUMBER(U19)),IF(U19<0,-1,1),0),0) -> 0 | BN19: =IF(ISNUMBER(AD19),IF(AD19>Parameters!$B$27,1,IF(AD19<Parameters!$B$28,-1,0)),0) -> 1 | BO19: =BG19+BH19+BI19+BJ19+BK19+BL19+BM19+BN19 -> 8 | BP19: =IF(ISNUMBER(F19),IF(F19>=Parameters!$B$30,2,IF(F19>=Parameters!$B$31,1,IF(F19<=Parameters!$B$32,-1,0))),0) -> 2 | BQ19: =IF(ISNUMBER(AK19),IF(AK19>Parameters!$B$33,1,IF(AK19<0,-1,0)),0) -> 1 | BR19: =IF(ISNUMBER(AL19),IF(AL19>Parameters!$B$34,1,IF(AL19<0,-1,0)),0) -> 1 | BS19: =IF(ISNUMBER(AP19),IF(AND(AP19>0,AP19<=Parameters!$B$35),1,IF(AP19>Parameters!$B$36,-1,0)),0) -> 1 | BT19: =IF(ISNUMBER(AY19),IF(AY19>Parameters!$B$37,1,IF(AY19<0,-1,0)),0) -> 1 | BU19: =IF(ISNUMBER(AZ19),IF(AZ19>0,1,0),0) -> 1 | BV19: =IF(ISNUMBER(AL19),IF(AL19>Parameters!$B$39,2,IF(AL19>Parameters!$B$40,1,IF(AL19<0,-2,IF(AL19<Parameters!$B$41,-1,0)))),0) -> 2 | BW19: =IF(ISNUMBER(AV19),IF(AV19>Parameters!$B$42,1,IF(AV19<Parameters!$B$43,-1,0)),0) -> 1 | BX19: =IF(AND(ISNUMBER(AX19),AX19>0),1,IF(AND(ISNUMBER(AY19),AY19<Parameters!$B$44),-1,0)) -> 1 | BY19: =IF(ISNUMBER(AW19),IF(AW19>0,1,0),0) -> 1 | BZ19: =IF(ISNUMBER(AQ19),IF(AQ19>Parameters!$B$46,-2,IF(AQ19>Parameters!$B$45,-1,0)),0) -> 0 | CA19: =IF(ISNUMBER(F19),IF(F19>=Parameters!$B$47,1,IF(F19<=Parameters!$B$48,-1,0)),0) -> 1 | CB19: =IF(BF19="Established",BP19+BQ19+BR19+BS19+BT19+BU19,IF(BF19="Early",BV19+BW19+BX19+BY19+BZ19+CA19,0)) -> 7 | CC19: =IF(BF19="Established",BO19+CB19,IF(BF19="Early",BO19+Parameters!$B$50*CB19,BO19)) -> 15 | CD19: =IF(BF19="Established",IF(CC19>=Parameters!$B$51,6,IF(CC19>=Parameters!$B$52,5,IF(CC19>=Parameters!$B$53,4,IF(CC19>=Parameters!$B$54,3,IF(CC19>=Parameters!$B$55,2,1))))),IF(BF19="Early",IF(CC19>=Parameters!$B$56,5,IF(CC19>=Parameters!$B$57,4,IF(CC19>=Parameters!$B$58,3,IF(CC19>=Parameters!$B$59,2,1)))),IF(CC19>=Parameters!$B$60,6,IF(CC19>=Parameters!$B$61,5,IF(CC19>=Parameters!$B$62,4,IF(CC19>=Parameters!$B$63,3,IF(CC19>=Parameters!$B$64,2,1))))))) -> 6 | CE19: =IF(AND(ISNUMBER(AR19),AR19<Parameters!$B$66),1,0) -> 0 | CF19: =IF(AND(LEFT(AH19,5)="Death",ISNUMBER(AG19)),IF(BF19="Early",IF(AND(AG19<Parameters!$B$70,ISNUMBER(U19),U19<Parameters!$B$71),1,0),IF(AND(AG19<Parameters!$B$67,OR(AND(ISNUMBER(U19),U19<Parameters!$B$68),AND(ISNUMBER(V19),V19<Parameters!$B$69))),1,0)),0) -> 0 | CG19: =IF(AND(ISNUMBER(AG19),AG19<0),1,0) -> 0 | CH19: =IF(OR(AND(ISNUMBER(U19),U19>Parameters!$B$74),AND(ISNUMBER(AF19),AF19>Parameters!$B$75),AND(ISNUMBER(AE19),AE19>Parameters!$B$76)),1,0) -> 0 | CI19: =IF(AND(ISNUMBER(BC19),BC19>=0,BC19<=Parameters!$B$77),1,0) -> 0 | CJ19: =IF(CF19=1,1,MIN(CD19,IF(CE19=1,3,6),IF(CG19=1,IF(BF19="Early",Parameters!$B$73,Parameters!$B$72),6),IF(CH19=1,3,6),IF(CI19=1,3,6))) -> 6 | CK19: =INDEX(Parameters!$F$2:$F$7,CJ19) -> Strong Buy | CL19: =IF(CF19=1,"Hard sell: breakdown; ","")&IF(CE19=1,"Insufficient history; ","")&IF(AND(CF19=0,CG19=1),"Below 200D; ","")&IF(CH19=1,"Extended - wait for pullback; ","")&IF(CI19=1,"Earnings within "&Parameters!$B$77&"d; ","")
A20: MSFT | B20: 7 | C20: 6 | D20: 47.4 | E20: 5.7 | F20: 10 | G20: Microsoft Corporation | H20: Mag 7 | I20: 493.51 | J20: USD | K20: Technology | L20: 3650769366394 | M20: 46232 | N20: 11.79 | O20: 46323 | P20: estimated | Q20: 0.38 | R20: -0.47 | S20: -0.67 | T20: -0.58 | U20: -2.04 | V20: 24.2 | W20: 21.89 | X20: -0.98 | AC20: 19.56 | AD20: -10.87 | AE20: 55.55 | AF20: 9.31 | AG20: 14.46 | AH20: Golden (8d) | AI20: -3.87 | AJ20: -27.37 | AK20: 31.3 | AL20: 17.7 | AM20: 40.31 | AN20: 34.04 | AO20: 20.93 | AP20: 0.87 | AQ20: 0.92 | AR20: 300 | AS20: 46275 | AT20: 331839012864 | AU20: 225465008128 | AV20: 67.94 | AW20: 133748998144 | AX20: 16545500160 | AY20: 4.99 | AZ20: -51969998848 | BA20: 41.33 | BB20: 70.56 | BC20: =IF(AND(ISNUMBER(O20),ISNUMBER(AS20)),O20-AS20,"") -> 48 | BD20: =IF(OR(ISNUMBER(SEARCH("ETF",H20)),AND(F20="",AO20="")),1,0) -> 0 | BE20: =IF(ISNUMBER(L20),IF(L20>=Parameters!$B$3,2,IF(L20>=Parameters!$B$4,1,0)),0)+IF(ISNUMBER(AW20),IF(AW20>0,IF(AND(ISNUMBER(AM20),AM20>=Parameters!$B$5),2,1),0),0)+IF(ISNUMBER(AX20),IF(AND(AX20>0,ISNUMBER(AY20),AY20>=Parameters!$B$6),1,0),0)+IF(ISNUMBER(AO20),IF(AND(AO20>0,AO20<=Parameters!$B$7),1,0),0)+IF(ISNUMBER(F20),IF(F20>=Parameters!$B$8,1,0),0) -> 6 | BF20: =IF(BD20=1,"ETF",IF(OR(AND(ISNUMBER(L20),L20>=Parameters!$B$10),BE20>=Parameters!$B$9),"Established","Early")) -> Established | BG20: =IF(LEFT(AH20,6)="Golden",2,IF(LEFT(AH20,5)="Death",-2,0)) -> 2 | BH20: =IF(ISNUMBER(AG20),IF(AG20>Parameters!$B$12,2,IF(AG20>0,1,IF(AG20>=Parameters!$B$13,-1,-2))),0) -> 2 | BI20: =IF(ISNUMBER(AF20),IF(AND(AF20>=Parameters!$B$14,AF20<=Parameters!$B$15),1,IF(OR(AF20>Parameters!$B$16,AF20<Parameters!$B$17),-1,0)),0) -> 0 | BJ20: =IF(ISNUMBER(AE20),IF(AND(AE20>=Parameters!$B$18,AE20<=Parameters!$B$19),1,IF(OR(AE20>Parameters!$B$20,AE20<Parameters!$B$21),-1,0)),0) -> 1 | BK20: =IF(ISNUMBER(E20),IF(E20>Parameters!$B$22,1,IF(E20<Parameters!$B$23,-1,0)),0) -> 1 | BL20: =IF(ISNUMBER(C20),IF(C20>=Parameters!$B$24,1,IF(C20<=Parameters!$B$25,-1,0)),0) -> 0 | BM20: =IF(ISNUMBER(AJ20),IF(AND(AJ20>Parameters!$B$26,ISNUMBER(U20)),IF(U20<0,-1,1),0),0) -> 0 | BN20: =IF(ISNUMBER(AD20),IF(AD20>Parameters!$B$27,1,IF(AD20<Parameters!$B$28,-1,0)),0) -> 0 | BO20: =BG20+BH20+BI20+BJ20+BK20+BL20+BM20+BN20 -> 6 | BP20: =IF(ISNUMBER(F20),IF(F20>=Parameters!$B$30,2,IF(F20>=Parameters!$B$31,1,IF(F20<=Parameters!$B$32,-1,0))),0) -> 2 | BQ20: =IF(ISNUMBER(AK20),IF(AK20>Parameters!$B$33,1,IF(AK20<0,-1,0)),0) -> 1 | BR20: =IF(ISNUMBER(AL20),IF(AL20>Parameters!$B$34,1,IF(AL20<0,-1,0)),0) -> 1 | BS20: =IF(ISNUMBER(AP20),IF(AND(AP20>0,AP20<=Parameters!$B$35),1,IF(AP20>Parameters!$B$36,-1,0)),0) -> 1 | BT20: =IF(ISNUMBER(AY20),IF(AY20>Parameters!$B$37,1,IF(AY20<0,-1,0)),0) -> 0 | BU20: =IF(ISNUMBER(AZ20),IF(AZ20>0,1,0),0) -> 0 | BV20: =IF(ISNUMBER(AL20),IF(AL20>Parameters!$B$39,2,IF(AL20>Parameters!$B$40,1,IF(AL20<0,-2,IF(AL20<Parameters!$B$41,-1,0)))),0) -> 1 | BW20: =IF(ISNUMBER(AV20),IF(AV20>Parameters!$B$42,1,IF(AV20<Parameters!$B$43,-1,0)),0) -> 1 | BX20: =IF(AND(ISNUMBER(AX20),AX20>0),1,IF(AND(ISNUMBER(AY20),AY20<Parameters!$B$44),-1,0)) -> 1 | BY20: =IF(ISNUMBER(AW20),IF(AW20>0,1,0),0) -> 1 | BZ20: =IF(ISNUMBER(AQ20),IF(AQ20>Parameters!$B$46,-2,IF(AQ20>Parameters!$B$45,-1,0)),0) -> 0 | CA20: =IF(ISNUMBER(F20),IF(F20>=Parameters!$B$47,1,IF(F20<=Parameters!$B$48,-1,0)),0) -> 1 | CB20: =IF(BF20="Established",BP20+BQ20+BR20+BS20+BT20+BU20,IF(BF20="Early",BV20+BW20+BX20+BY20+BZ20+CA20,0)) -> 5 | CC20: =IF(BF20="Established",BO20+CB20,IF(BF20="Early",BO20+Parameters!$B$50*CB20,BO20)) -> 11 | CD20: =IF(BF20="Established",IF(CC20>=Parameters!$B$51,6,IF(CC20>=Parameters!$B$52,5,IF(CC20>=Parameters!$B$53,4,IF(CC20>=Parameters!$B$54,3,IF(CC20>=Parameters!$B$55,2,1))))),IF(BF20="Early",IF(CC20>=Parameters!$B$56,5,IF(CC20>=Parameters!$B$57,4,IF(CC20>=Parameters!$B$58,3,IF(CC20>=Parameters!$B$59,2,1)))),IF(CC20>=Parameters!$B$60,6,IF(CC20>=Parameters!$B$61,5,IF(CC20>=Parameters!$B$62,4,IF(CC20>=Parameters!$B$63,3,IF(CC20>=Parameters!$B$64,2,1))))))) -> 5 | CE20: =IF(AND(ISNUMBER(AR20),AR20<Parameters!$B$66),1,0) -> 0 | CF20: =IF(AND(LEFT(AH20,5)="Death",ISNUMBER(AG20)),IF(BF20="Early",IF(AND(AG20<Parameters!$B$70,ISNUMBER(U20),U20<Parameters!$B$71),1,0),IF(AND(AG20<Parameters!$B$67,OR(AND(ISNUMBER(U20),U20<Parameters!$B$68),AND(ISNUMBER(V20),V20<Parameters!$B$69))),1,0)),0) -> 0 | CG20: =IF(AND(ISNUMBER(AG20),AG20<0),1,0) -> 0 | CH20: =IF(OR(AND(ISNUMBER(U20),U20>Parameters!$B$74),AND(ISNUMBER(AF20),AF20>Parameters!$B$75),AND(ISNUMBER(AE20),AE20>Parameters!$B$76)),1,0) -> 0 | CI20: =IF(AND(ISNUMBER(BC20),BC20>=0,BC20<=Parameters!$B$77),1,0) -> 0 | CJ20: =IF(CF20=1,1,MIN(CD20,IF(CE20=1,3,6),IF(CG20=1,IF(BF20="Early",Parameters!$B$73,Parameters!$B$72),6),IF(CH20=1,3,6),IF(CI20=1,3,6))) -> 5 | CK20: =INDEX(Parameters!$F$2:$F$7,CJ20) -> Buy | CL20: =IF(CF20=1,"Hard sell: breakdown; ","")&IF(CE20=1,"Insufficient history; ","")&IF(AND(CF20=0,CG20=1),"Below 200D; ","")&IF(CH20=1,"Extended - wait for pullback; ","")&IF(CI20=1,"Earnings within "&Parameters!$B$77&"d; ","")
A21: LLY | B21: 7 | C21: 6 | D21: 61.8 | E21: -5.8 | F21: 9 | G21: Eli Lilly and Company | H21: Watchlist | I21: 1126.37 | J21: USD | K21: Healthcare | L21: 1002504570369 | M21: 46239 | N21: 27.36 | O21: 46330 | P21: estimated | Q21: 0.19 | R21: 0.03 | S21: -2.91 | T21: -5.3 | U21: -7.3 | V21: -0.88 | W21: 12.66 | X21: 50.06 | AC21: -5.52 | AD21: -12.86 | AE21: 37.65 | AF21: -5.05 | AG21: 5.8 | AH21: Golden | AI21: -10.17 | AJ21: -22 | AK21: 25.3 | AL21: 47.7 | AM21: 33.53 | AN21: 102.29 | AO21: 23.78 | AP21: 1.43 | AQ21: 0.74 | AR21: 300 | AS21: 46275 | AT21: 79666003968 | AU21: 66440998912 | AV21: 83.4 | AW21: 26710999040 | AX21: 11065900032 | AY21: 13.89 | AZ21: -45957998592 | BA21: 58.19 | BB21: 71.36 | BC21: =IF(AND(ISNUMBER(O21),ISNUMBER(AS21)),O21-AS21,"") -> 55 | BD21: =IF(OR(ISNUMBER(SEARCH("ETF",H21)),AND(F21="",AO21="")),1,0) -> 0 | BE21: =IF(ISNUMBER(L21),IF(L21>=Parameters!$B$3,2,IF(L21>=Parameters!$B$4,1,0)),0)+IF(ISNUMBER(AW21),IF(AW21>0,IF(AND(ISNUMBER(AM21),AM21>=Parameters!$B$5),2,1),0),0)+IF(ISNUMBER(AX21),IF(AND(AX21>0,ISNUMBER(AY21),AY21>=Parameters!$B$6),1,0),0)+IF(ISNUMBER(AO21),IF(AND(AO21>0,AO21<=Parameters!$B$7),1,0),0)+IF(ISNUMBER(F21),IF(F21>=Parameters!$B$8,1,0),0) -> 7 | BF21: =IF(BD21=1,"ETF",IF(OR(AND(ISNUMBER(L21),L21>=Parameters!$B$10),BE21>=Parameters!$B$9),"Established","Early")) -> Established | BG21: =IF(LEFT(AH21,6)="Golden",2,IF(LEFT(AH21,5)="Death",-2,0)) -> 2 | BH21: =IF(ISNUMBER(AG21),IF(AG21>Parameters!$B$12,2,IF(AG21>0,1,IF(AG21>=Parameters!$B$13,-1,-2))),0) -> 1 | BI21: =IF(ISNUMBER(AF21),IF(AND(AF21>=Parameters!$B$14,AF21<=Parameters!$B$15),1,IF(OR(AF21>Parameters!$B$16,AF21<Parameters!$B$17),-1,0)),0) -> 0 | BJ21: =IF(ISNUMBER(AE21),IF(AND(AE21>=Parameters!$B$18,AE21<=Parameters!$B$19),1,IF(OR(AE21>Parameters!$B$20,AE21<Parameters!$B$21),-1,0)),0) -> 0 | BK21: =IF(ISNUMBER(E21),IF(E21>Parameters!$B$22,1,IF(E21<Parameters!$B$23,-1,0)),0) -> -1 | BL21: =IF(ISNUMBER(C21),IF(C21>=Parameters!$B$24,1,IF(C21<=Parameters!$B$25,-1,0)),0) -> 0 | BM21: =IF(ISNUMBER(AJ21),IF(AND(AJ21>Parameters!$B$26,ISNUMBER(U21)),IF(U21<0,-1,1),0),0) -> 0 | BN21: =IF(ISNUMBER(AD21),IF(AD21>Parameters!$B$27,1,IF(AD21<Parameters!$B$28,-1,0)),0) -> 0 | BO21: =BG21+BH21+BI21+BJ21+BK21+BL21+BM21+BN21 -> 2 | BP21: =IF(ISNUMBER(F21),IF(F21>=Parameters!$B$30,2,IF(F21>=Parameters!$B$31,1,IF(F21<=Parameters!$B$32,-1,0))),0) -> 2 | BQ21: =IF(ISNUMBER(AK21),IF(AK21>Parameters!$B$33,1,IF(AK21<0,-1,0)),0) -> 1 | BR21: =IF(ISNUMBER(AL21),IF(AL21>Parameters!$B$34,1,IF(AL21<0,-1,0)),0) -> 1 | BS21: =IF(ISNUMBER(AP21),IF(AND(AP21>0,AP21<=Parameters!$B$35),1,IF(AP21>Parameters!$B$36,-1,0)),0) -> 1 | BT21: =IF(ISNUMBER(AY21),IF(AY21>Parameters!$B$37,1,IF(AY21<0,-1,0)),0) -> 1 | BU21: =IF(ISNUMBER(AZ21),IF(AZ21>0,1,0),0) -> 0 | BV21: =IF(ISNUMBER(AL21),IF(AL21>Parameters!$B$39,2,IF(AL21>Parameters!$B$40,1,IF(AL21<0,-2,IF(AL21<Parameters!$B$41,-1,0)))),0) -> 2 | BW21: =IF(ISNUMBER(AV21),IF(AV21>Parameters!$B$42,1,IF(AV21<Parameters!$B$43,-1,0)),0) -> 1 | BX21: =IF(AND(ISNUMBER(AX21),AX21>0),1,IF(AND(ISNUMBER(AY21),AY21<Parameters!$B$44),-1,0)) -> 1 | BY21: =IF(ISNUMBER(AW21),IF(AW21>0,1,0),0) -> 1 | BZ21: =IF(ISNUMBER(AQ21),IF(AQ21>Parameters!$B$46,-2,IF(AQ21>Parameters!$B$45,-1,0)),0) -> 0 | CA21: =IF(ISNUMBER(F21),IF(F21>=Parameters!$B$47,1,IF(F21<=Parameters!$B$48,-1,0)),0) -> 1 | CB21: =IF(BF21="Established",BP21+BQ21+BR21+BS21+BT21+BU21,IF(BF21="Early",BV21+BW21+BX21+BY21+BZ21+CA21,0)) -> 6 | CC21: =IF(BF21="Established",BO21+CB21,IF(BF21="Early",BO21+Parameters!$B$50*CB21,BO21)) -> 8 | CD21: =IF(BF21="Established",IF(CC21>=Parameters!$B$51,6,IF(CC21>=Parameters!$B$52,5,IF(CC21>=Parameters!$B$53,4,IF(CC21>=Parameters!$B$54,3,IF(CC21>=Parameters!$B$55,2,1))))),IF(BF21="Early",IF(CC21>=Parameters!$B$56,5,IF(CC21>=Parameters!$B$57,4,IF(CC21>=Parameters!$B$58,3,IF(CC21>=Parameters!$B$59,2,1)))),IF(CC21>=Parameters!$B$60,6,IF(CC21>=Parameters!$B$61,5,IF(CC21>=Parameters!$B$62,4,IF(CC21>=Parameters!$B$63,3,IF(CC21>=Parameters!$B$64,2,1))))))) -> 4 | CE21: =IF(AND(ISNUMBER(AR21),AR21<Parameters!$B$66),1,0) -> 0 | CF21: =IF(AND(LEFT(AH21,5)="Death",ISNUMBER(AG21)),IF(BF21="Early",IF(AND(AG21<Parameters!$B$70,ISNUMBER(U21),U21<Parameters!$B$71),1,0),IF(AND(AG21<Parameters!$B$67,OR(AND(ISNUMBER(U21),U21<Parameters!$B$68),AND(ISNUMBER(V21),V21<Parameters!$B$69))),1,0)),0) -> 0 | CG21: =IF(AND(ISNUMBER(AG21),AG21<0),1,0) -> 0 | CH21: =IF(OR(AND(ISNUMBER(U21),U21>Parameters!$B$74),AND(ISNUMBER(AF21),AF21>Parameters!$B$75),AND(ISNUMBER(AE21),AE21>Parameters!$B$76)),1,0) -> 0 | CI21: =IF(AND(ISNUMBER(BC21),BC21>=0,BC21<=Parameters!$B$77),1,0) -> 0 | CJ21: =IF(CF21=1,1,MIN(CD21,IF(CE21=1,3,6),IF(CG21=1,IF(BF21="Early",Parameters!$B$73,Parameters!$B$72),6),IF(CH21=1,3,6),IF(CI21=1,3,6))) -> 4 | CK21: =INDEX(Parameters!$F$2:$F$7,CJ21) -> Buy with Risk | CL21: =IF(CF21=1,"Hard sell: breakdown; ","")&IF(CE21=1,"Insufficient history; ","")&IF(AND(CF21=0,CG21=1),"Below 200D; ","")&IF(CH21=1,"Extended - wait for pullback; ","")&IF(CI21=1,"Earnings within "&Parameters!$B$77&"d; ","")
A22: CRWD | B22: 7 | C22: 8 | D22: 70.8 | E22: 6.8 | F22: 5 | G22: CrowdStrike Holdings, Inc. | H22: CyberSecurity | I22: 214.05 | J22: USD | K22: Technology | L22: 212773660167 | M22: 46260 | N22: 6.9 | O22: 46351 | P22: estimated | Q22: 3.01 | R22: -1.06 | S22: 5.22 | T22: 13.14 | U22: -3.54 | V22: 32.18 | W22: 93.69 | X22: 102.16 | AC22: 27.54 | AD22: -8.48 | AE22: 53.52 | AF22: 5.75 | AG22: 48.92 | AH22: Golden (75d) | AI22: -0.33 | AJ22: -30.84 | AK22: 25.83 | AL22: 25.8 | AM22: 0.83 | AN22: 1.46 | AO22: 130.81 | AP22: -46.45 | AQ22: 2.4 | AR22: 300 | AS22: 46275 | AT22: 5396145152 | AU22: 4057167872 | AV22: 75.19 | AW22: 44995000 | AX22: 1995385472 | AY22: 36.98 | AZ22: 4193668032 | BA22: 149.82 | BB22: 86.62 | BC22: =IF(AND(ISNUMBER(O22),ISNUMBER(AS22)),O22-AS22,"") -> 76 | BD22: =IF(OR(ISNUMBER(SEARCH("ETF",H22)),AND(F22="",AO22="")),1,0) -> 0 | BE22: =IF(ISNUMBER(L22),IF(L22>=Parameters!$B$3,2,IF(L22>=Parameters!$B$4,1,0)),0)+IF(ISNUMBER(AW22),IF(AW22>0,IF(AND(ISNUMBER(AM22),AM22>=Parameters!$B$5),2,1),0),0)+IF(ISNUMBER(AX22),IF(AND(AX22>0,ISNUMBER(AY22),AY22>=Parameters!$B$6),1,0),0)+IF(ISNUMBER(AO22),IF(AND(AO22>0,AO22<=Parameters!$B$7),1,0),0)+IF(ISNUMBER(F22),IF(F22>=Parameters!$B$8,1,0),0) -> 4 | BF22: =IF(BD22=1,"ETF",IF(OR(AND(ISNUMBER(L22),L22>=Parameters!$B$10),BE22>=Parameters!$B$9),"Established","Early")) -> Established | BG22: =IF(LEFT(AH22,6)="Golden",2,IF(LEFT(AH22,5)="Death",-2,0)) -> 2 | BH22: =IF(ISNUMBER(AG22),IF(AG22>Parameters!$B$12,2,IF(AG22>0,1,IF(AG22>=Parameters!$B$13,-1,-2))),0) -> 2 | BI22: =IF(ISNUMBER(AF22),IF(AND(AF22>=Parameters!$B$14,AF22<=Parameters!$B$15),1,IF(OR(AF22>Parameters!$B$16,AF22<Parameters!$B$17),-1,0)),0) -> 1 | BJ22: =IF(ISNUMBER(AE22),IF(AND(AE22>=Parameters!$B$18,AE22<=Parameters!$B$19),1,IF(OR(AE22>Parameters!$B$20,AE22<Parameters!$B$21),-1,0)),0) -> 1 | BK22: =IF(ISNUMBER(E22),IF(E22>Parameters!$B$22,1,IF(E22<Parameters!$B$23,-1,0)),0) -> 1 | BL22: =IF(ISNUMBER(C22),IF(C22>=Parameters!$B$24,1,IF(C22<=Parameters!$B$25,-1,0)),0) -> 1 | BM22: =IF(ISNUMBER(AJ22),IF(AND(AJ22>Parameters!$B$26,ISNUMBER(U22)),IF(U22<0,-1,1),0),0) -> 0 | BN22: =IF(ISNUMBER(AD22),IF(AD22>Parameters!$B$27,1,IF(AD22<Parameters!$B$28,-1,0)),0) -> 1 | BO22: =BG22+BH22+BI22+BJ22+BK22+BL22+BM22+BN22 -> 9 | BP22: =IF(ISNUMBER(F22),IF(F22>=Parameters!$B$30,2,IF(F22>=Parameters!$B$31,1,IF(F22<=Parameters!$B$32,-1,0))),0) -> 0 | BQ22: =IF(ISNUMBER(AK22),IF(AK22>Parameters!$B$33,1,IF(AK22<0,-1,0)),0) -> 1 | BR22: =IF(ISNUMBER(AL22),IF(AL22>Parameters!$B$34,1,IF(AL22<0,-1,0)),0) -> 1 | BS22: =IF(ISNUMBER(AP22),IF(AND(AP22>0,AP22<=Parameters!$B$35),1,IF(AP22>Parameters!$B$36,-1,0)),0) -> 0 | BT22: =IF(ISNUMBER(AY22),IF(AY22>Parameters!$B$37,1,IF(AY22<0,-1,0)),0) -> 1 | BU22: =IF(ISNUMBER(AZ22),IF(AZ22>0,1,0),0) -> 1 | BV22: =IF(ISNUMBER(AL22),IF(AL22>Parameters!$B$39,2,IF(AL22>Parameters!$B$40,1,IF(AL22<0,-2,IF(AL22<Parameters!$B$41,-1,0)))),0) -> 1 | BW22: =IF(ISNUMBER(AV22),IF(AV22>Parameters!$B$42,1,IF(AV22<Parameters!$B$43,-1,0)),0) -> 1 | BX22: =IF(AND(ISNUMBER(AX22),AX22>0),1,IF(AND(ISNUMBER(AY22),AY22<Parameters!$B$44),-1,0)) -> 1 | BY22: =IF(ISNUMBER(AW22),IF(AW22>0,1,0),0) -> 1 | BZ22: =IF(ISNUMBER(AQ22),IF(AQ22>Parameters!$B$46,-2,IF(AQ22>Parameters!$B$45,-1,0)),0) -> 0 | CA22: =IF(ISNUMBER(F22),IF(F22>=Parameters!$B$47,1,IF(F22<=Parameters!$B$48,-1,0)),0) -> 0 | CB22: =IF(BF22="Established",BP22+BQ22+BR22+BS22+BT22+BU22,IF(BF22="Early",BV22+BW22+BX22+BY22+BZ22+CA22,0)) -> 4 | CC22: =IF(BF22="Established",BO22+CB22,IF(BF22="Early",BO22+Parameters!$B$50*CB22,BO22)) -> 13 | CD22: =IF(BF22="Established",IF(CC22>=Parameters!$B$51,6,IF(CC22>=Parameters!$B$52,5,IF(CC22>=Parameters!$B$53,4,IF(CC22>=Parameters!$B$54,3,IF(CC22>=Parameters!$B$55,2,1))))),IF(BF22="Early",IF(CC22>=Parameters!$B$56,5,IF(CC22>=Parameters!$B$57,4,IF(CC22>=Parameters!$B$58,3,IF(CC22>=Parameters!$B$59,2,1)))),IF(CC22>=Parameters!$B$60,6,IF(CC22>=Parameters!$B$61,5,IF(CC22>=Parameters!$B$62,4,IF(CC22>=Parameters!$B$63,3,IF(CC22>=Parameters!$B$64,2,1))))))) -> 6 | CE22: =IF(AND(ISNUMBER(AR22),AR22<Parameters!$B$66),1,0) -> 0 | CF22: =IF(AND(LEFT(AH22,5)="Death",ISNUMBER(AG22)),IF(BF22="Early",IF(AND(AG22<Parameters!$B$70,ISNUMBER(U22),U22<Parameters!$B$71),1,0),IF(AND(AG22<Parameters!$B$67,OR(AND(ISNUMBER(U22),U22<Parameters!$B$68),AND(ISNUMBER(V22),V22<Parameters!$B$69))),1,0)),0) -> 0 | CG22: =IF(AND(ISNUMBER(AG22),AG22<0),1,0) -> 0 | CH22: =IF(OR(AND(ISNUMBER(U22),U22>Parameters!$B$74),AND(ISNUMBER(AF22),AF22>Parameters!$B$75),AND(ISNUMBER(AE22),AE22>Parameters!$B$76)),1,0) -> 0 | CI22: =IF(AND(ISNUMBER(BC22),BC22>=0,BC22<=Parameters!$B$77),1,0) -> 0 | CJ22: =IF(CF22=1,1,MIN(CD22,IF(CE22=1,3,6),IF(CG22=1,IF(BF22="Early",Parameters!$B$73,Parameters!$B$72),6),IF(CH22=1,3,6),IF(CI22=1,3,6))) -> 6 | CK22: =INDEX(Parameters!$F$2:$F$7,CJ22) -> Strong Buy | CL22: =IF(CF22=1,"Hard sell: breakdown; ","")&IF(CE22=1,"Insufficient history; ","")&IF(AND(CF22=0,CG22=1),"Below 200D; ","")&IF(CH22=1,"Extended - wait for pullback; ","")&IF(CI22=1,"Earnings within "&Parameters!$B$77&"d; ","")
A23: PANW | B23: 7 | C23: 8 | D23: 77.6 | E23: -2.7 | F23: 6 | G23: Palo Alto Networks, Inc. | H23: CyberSecurity | I23: 342.95 | J23: USD | K23: Technology | L23: 273106508150 | M23: 46266 | N23: 4.08 | O23: 46357 | P23: estimated | Q23: 2.34 | R23: -0.56 | S23: 4.4 | T23: 1.07 | U23: -10.64 | V23: 30.29 | W23: 107.93 | X23: 73.6 | AC23: 25.65 | AD23: -14.02 | AE23: 47.4 | AF23: -2.03 | AG23: 45.8 | AH23: Golden (73d) | AI23: -3.97 | AJ23: -20.52 | AK23: 31.15 | AL23: 34.4 | AM23: 2.67 | AN23: 1.74 | AO23: 68.28 | AP23: -1.85 | AQ23: 2.77 | AR23: 300 | AS23: 46275 | AT23: 11480000512 | AU23: 8092000256 | AV23: 70.49 | AW23: 307000000 | AX23: 4469550080 | AY23: 38.93 | AZ23: 571000064 | BA23: 145.72 | BB23: 78.43 | BC23: =IF(AND(ISNUMBER(O23),ISNUMBER(AS23)),O23-AS23,"") -> 82 | BD23: =IF(OR(ISNUMBER(SEARCH("ETF",H23)),AND(F23="",AO23="")),1,0) -> 0 | BE23: =IF(ISNUMBER(L23),IF(L23>=Parameters!$B$3,2,IF(L23>=Parameters!$B$4,1,0)),0)+IF(ISNUMBER(AW23),IF(AW23>0,IF(AND(ISNUMBER(AM23),AM23>=Parameters!$B$5),2,1),0),0)+IF(ISNUMBER(AX23),IF(AND(AX23>0,ISNUMBER(AY23),AY23>=Parameters!$B$6),1,0),0)+IF(ISNUMBER(AO23),IF(AND(AO23>0,AO23<=Parameters!$B$7),1,0),0)+IF(ISNUMBER(F23),IF(F23>=Parameters!$B$8,1,0),0) -> 4 | BF23: =IF(BD23=1,"ETF",IF(OR(AND(ISNUMBER(L23),L23>=Parameters!$B$10),BE23>=Parameters!$B$9),"Established","Early")) -> Established | BG23: =IF(LEFT(AH23,6)="Golden",2,IF(LEFT(AH23,5)="Death",-2,0)) -> 2 | BH23: =IF(ISNUMBER(AG23),IF(AG23>Parameters!$B$12,2,IF(AG23>0,1,IF(AG23>=Parameters!$B$13,-1,-2))),0) -> 2 | BI23: =IF(ISNUMBER(AF23),IF(AND(AF23>=Parameters!$B$14,AF23<=Parameters!$B$15),1,IF(OR(AF23>Parameters!$B$16,AF23<Parameters!$B$17),-1,0)),0) -> 1 | BJ23: =IF(ISNUMBER(AE23),IF(AND(AE23>=Parameters!$B$18,AE23<=Parameters!$B$19),1,IF(OR(AE23>Parameters!$B$20,AE23<Parameters!$B$21),-1,0)),0) -> 1 | BK23: =IF(ISNUMBER(E23),IF(E23>Parameters!$B$22,1,IF(E23<Parameters!$B$23,-1,0)),0) -> 0 | BL23: =IF(ISNUMBER(C23),IF(C23>=Parameters!$B$24,1,IF(C23<=Parameters!$B$25,-1,0)),0) -> 1 | BM23: =IF(ISNUMBER(AJ23),IF(AND(AJ23>Parameters!$B$26,ISNUMBER(U23)),IF(U23<0,-1,1),0),0) -> 0 | BN23: =IF(ISNUMBER(AD23),IF(AD23>Parameters!$B$27,1,IF(AD23<Parameters!$B$28,-1,0)),0) -> 0 | BO23: =BG23+BH23+BI23+BJ23+BK23+BL23+BM23+BN23 -> 7 | BP23: =IF(ISNUMBER(F23),IF(F23>=Parameters!$B$30,2,IF(F23>=Parameters!$B$31,1,IF(F23<=Parameters!$B$32,-1,0))),0) -> 1 | BQ23: =IF(ISNUMBER(AK23),IF(AK23>Parameters!$B$33,1,IF(AK23<0,-1,0)),0) -> 1 | BR23: =IF(ISNUMBER(AL23),IF(AL23>Parameters!$B$34,1,IF(AL23<0,-1,0)),0) -> 1 | BS23: =IF(ISNUMBER(AP23),IF(AND(AP23>0,AP23<=Parameters!$B$35),1,IF(AP23>Parameters!$B$36,-1,0)),0) -> 0 | BT23: =IF(ISNUMBER(AY23),IF(AY23>Parameters!$B$37,1,IF(AY23<0,-1,0)),0) -> 1 | BU23: =IF(ISNUMBER(AZ23),IF(AZ23>0,1,0),0) -> 1 | BV23: =IF(ISNUMBER(AL23),IF(AL23>Parameters!$B$39,2,IF(AL23>Parameters!$B$40,1,IF(AL23<0,-2,IF(AL23<Parameters!$B$41,-1,0)))),0) -> 2 | BW23: =IF(ISNUMBER(AV23),IF(AV23>Parameters!$B$42,1,IF(AV23<Parameters!$B$43,-1,0)),0) -> 1 | BX23: =IF(AND(ISNUMBER(AX23),AX23>0),1,IF(AND(ISNUMBER(AY23),AY23<Parameters!$B$44),-1,0)) -> 1 | BY23: =IF(ISNUMBER(AW23),IF(AW23>0,1,0),0) -> 1 | BZ23: =IF(ISNUMBER(AQ23),IF(AQ23>Parameters!$B$46,-2,IF(AQ23>Parameters!$B$45,-1,0)),0) -> 0 | CA23: =IF(ISNUMBER(F23),IF(F23>=Parameters!$B$47,1,IF(F23<=Parameters!$B$48,-1,0)),0) -> 1 | CB23: =IF(BF23="Established",BP23+BQ23+BR23+BS23+BT23+BU23,IF(BF23="Early",BV23+BW23+BX23+BY23+BZ23+CA23,0)) -> 5 | CC23: =IF(BF23="Established",BO23+CB23,IF(BF23="Early",BO23+Parameters!$B$50*CB23,BO23)) -> 12 | CD23: =IF(BF23="Established",IF(CC23>=Parameters!$B$51,6,IF(CC23>=Parameters!$B$52,5,IF(CC23>=Parameters!$B$53,4,IF(CC23>=Parameters!$B$54,3,IF(CC23>=Parameters!$B$55,2,1))))),IF(BF23="Early",IF(CC23>=Parameters!$B$56,5,IF(CC23>=Parameters!$B$57,4,IF(CC23>=Parameters!$B$58,3,IF(CC23>=Parameters!$B$59,2,1)))),IF(CC23>=Parameters!$B$60,6,IF(CC23>=Parameters!$B$61,5,IF(CC23>=Parameters!$B$62,4,IF(CC23>=Parameters!$B$63,3,IF(CC23>=Parameters!$B$64,2,1))))))) -> 5 | CE23: =IF(AND(ISNUMBER(AR23),AR23<Parameters!$B$66),1,0) -> 0 | CF23: =IF(AND(LEFT(AH23,5)="Death",ISNUMBER(AG23)),IF(BF23="Early",IF(AND(AG23<Parameters!$B$70,ISNUMBER(U23),U23<Parameters!$B$71),1,0),IF(AND(AG23<Parameters!$B$67,OR(AND(ISNUMBER(U23),U23<Parameters!$B$68),AND(ISNUMBER(V23),V23<Parameters!$B$69))),1,0)),0) -> 0 | CG23: =IF(AND(ISNUMBER(AG23),AG23<0),1,0) -> 0 | CH23: =IF(OR(AND(ISNUMBER(U23),U23>Parameters!$B$74),AND(ISNUMBER(AF23),AF23>Parameters!$B$75),AND(ISNUMBER(AE23),AE23>Parameters!$B$76)),1,0) -> 0 | CI23: =IF(AND(ISNUMBER(BC23),BC23>=0,BC23<=Parameters!$B$77),1,0) -> 0 | CJ23: =IF(CF23=1,1,MIN(CD23,IF(CE23=1,3,6),IF(CG23=1,IF(BF23="Early",Parameters!$B$73,Parameters!$B$72),6),IF(CH23=1,3,6),IF(CI23=1,3,6))) -> 5 | CK23: =INDEX(Parameters!$F$2:$F$7,CJ23) -> Buy | CL23: =IF(CF23=1,"Hard sell: breakdown; ","")&IF(CE23=1,"Insufficient history; ","")&IF(AND(CF23=0,CG23=1),"Below 200D; ","")&IF(CH23=1,"Extended - wait for pullback; ","")&IF(CI23=1,"Earnings within "&Parameters!$B$77&"d; ","")
A24: GEV | B24: 7 | C24: 6 | D24: 42.1 | E24: 9 | F24: 9 | G24: GE Vernova Inc. | H24: Industrials | I24: 923.22 | J24: USD | K24: Industrials | L24: 253293883014 | M24: 46225 | N24: -22.33 | O24: 46316 | P24: estimated | Q24: -2.93 | R24: -2.09 | S24: 0.14 | T24: -3.13 | U24: -8.76 | V24: 6.47 | W24: 8.92 | X24: 52.42 | AC24: 1.83 | AD24: -22.8 | AE24: 42.28 | AF24: -8.22 | AG24: 3.52 | AH24: Golden | AI24: 1.98 | AJ24: -36.16 | AK24: 30 | AL24: 21.9 | AM24: 23.04 | AN24: 82.58 | AO24: 37.27 | AP24: 0.85 | AQ24: 2.99 | AR24: 300 | AS24: 46275 | AT24: 41366999040 | AU24: 8509000192 | AV24: 20.57 | AW24: 9528999936 | AX24: 15722125312 | AY24: 38.01 | AZ24: 9000000000 | BA24: 74.14 | BB24: 59.04 | BC24: =IF(AND(ISNUMBER(O24),ISNUMBER(AS24)),O24-AS24,"") -> 41 | BD24: =IF(OR(ISNUMBER(SEARCH("ETF",H24)),AND(F24="",AO24="")),1,0) -> 0 | BE24: =IF(ISNUMBER(L24),IF(L24>=Parameters!$B$3,2,IF(L24>=Parameters!$B$4,1,0)),0)+IF(ISNUMBER(AW24),IF(AW24>0,IF(AND(ISNUMBER(AM24),AM24>=Parameters!$B$5),2,1),0),0)+IF(ISNUMBER(AX24),IF(AND(AX24>0,ISNUMBER(AY24),AY24>=Parameters!$B$6),1,0),0)+IF(ISNUMBER(AO24),IF(AND(AO24>0,AO24<=Parameters!$B$7),1,0),0)+IF(ISNUMBER(F24),IF(F24>=Parameters!$B$8,1,0),0) -> 7 | BF24: =IF(BD24=1,"ETF",IF(OR(AND(ISNUMBER(L24),L24>=Parameters!$B$10),BE24>=Parameters!$B$9),"Established","Early")) -> Established | BG24: =IF(LEFT(AH24,6)="Golden",2,IF(LEFT(AH24,5)="Death",-2,0)) -> 2 | BH24: =IF(ISNUMBER(AG24),IF(AG24>Parameters!$B$12,2,IF(AG24>0,1,IF(AG24>=Parameters!$B$13,-1,-2))),0) -> 1 | BI24: =IF(ISNUMBER(AF24),IF(AND(AF24>=Parameters!$B$14,AF24<=Parameters!$B$15),1,IF(OR(AF24>Parameters!$B$16,AF24<Parameters!$B$17),-1,0)),0) -> -1 | BJ24: =IF(ISNUMBER(AE24),IF(AND(AE24>=Parameters!$B$18,AE24<=Parameters!$B$19),1,IF(OR(AE24>Parameters!$B$20,AE24<Parameters!$B$21),-1,0)),0) -> 0 | BK24: =IF(ISNUMBER(E24),IF(E24>Parameters!$B$22,1,IF(E24<Parameters!$B$23,-1,0)),0) -> 1 | BL24: =IF(ISNUMBER(C24),IF(C24>=Parameters!$B$24,1,IF(C24<=Parameters!$B$25,-1,0)),0) -> 0 | BM24: =IF(ISNUMBER(AJ24),IF(AND(AJ24>Parameters!$B$26,ISNUMBER(U24)),IF(U24<0,-1,1),0),0) -> 0 | BN24: =IF(ISNUMBER(AD24),IF(AD24>Parameters!$B$27,1,IF(AD24<Parameters!$B$28,-1,0)),0) -> 0 | BO24: =BG24+BH24+BI24+BJ24+BK24+BL24+BM24+BN24 -> 3 | BP24: =IF(ISNUMBER(F24),IF(F24>=Parameters!$B$30,2,IF(F24>=Parameters!$B$31,1,IF(F24<=Parameters!$B$32,-1,0))),0) -> 2 | BQ24: =IF(ISNUMBER(AK24),IF(AK24>Parameters!$B$33,1,IF(AK24<0,-1,0)),0) -> 1 | BR24: =IF(ISNUMBER(AL24),IF(AL24>Parameters!$B$34,1,IF(AL24<0,-1,0)),0) -> 1 | BS24: =IF(ISNUMBER(AP24),IF(AND(AP24>0,AP24<=Parameters!$B$35),1,IF(AP24>Parameters!$B$36,-1,0)),0) -> 1 | BT24: =IF(ISNUMBER(AY24),IF(AY24>Parameters!$B$37,1,IF(AY24<0,-1,0)),0) -> 1 | BU24: =IF(ISNUMBER(AZ24),IF(AZ24>0,1,0),0) -> 1 | BV24: =IF(ISNUMBER(AL24),IF(AL24>Parameters!$B$39,2,IF(AL24>Parameters!$B$40,1,IF(AL24<0,-2,IF(AL24<Parameters!$B$41,-1,0)))),0) -> 1 | BW24: =IF(ISNUMBER(AV24),IF(AV24>Parameters!$B$42,1,IF(AV24<Parameters!$B$43,-1,0)),0) -> -1 | BX24: =IF(AND(ISNUMBER(AX24),AX24>0),1,IF(AND(ISNUMBER(AY24),AY24<Parameters!$B$44),-1,0)) -> 1 | BY24: =IF(ISNUMBER(AW24),IF(AW24>0,1,0),0) -> 1 | BZ24: =IF(ISNUMBER(AQ24),IF(AQ24>Parameters!$B$46,-2,IF(AQ24>Parameters!$B$45,-1,0)),0) -> 0 | CA24: =IF(ISNUMBER(F24),IF(F24>=Parameters!$B$47,1,IF(F24<=Parameters!$B$48,-1,0)),0) -> 1 | CB24: =IF(BF24="Established",BP24+BQ24+BR24+BS24+BT24+BU24,IF(BF24="Early",BV24+BW24+BX24+BY24+BZ24+CA24,0)) -> 7 | CC24: =IF(BF24="Established",BO24+CB24,IF(BF24="Early",BO24+Parameters!$B$50*CB24,BO24)) -> 10 | CD24: =IF(BF24="Established",IF(CC24>=Parameters!$B$51,6,IF(CC24>=Parameters!$B$52,5,IF(CC24>=Parameters!$B$53,4,IF(CC24>=Parameters!$B$54,3,IF(CC24>=Parameters!$B$55,2,1))))),IF(BF24="Early",IF(CC24>=Parameters!$B$56,5,IF(CC24>=Parameters!$B$57,4,IF(CC24>=Parameters!$B$58,3,IF(CC24>=Parameters!$B$59,2,1)))),IF(CC24>=Parameters!$B$60,6,IF(CC24>=Parameters!$B$61,5,IF(CC24>=Parameters!$B$62,4,IF(CC24>=Parameters!$B$63,3,IF(CC24>=Parameters!$B$64,2,1))))))) -> 5 | CE24: =IF(AND(ISNUMBER(AR24),AR24<Parameters!$B$66),1,0) -> 0 | CF24: =IF(AND(LEFT(AH24,5)="Death",ISNUMBER(AG24)),IF(BF24="Early",IF(AND(AG24<Parameters!$B$70,ISNUMBER(U24),U24<Parameters!$B$71),1,0),IF(AND(AG24<Parameters!$B$67,OR(AND(ISNUMBER(U24),U24<Parameters!$B$68),AND(ISNUMBER(V24),V24<Parameters!$B$69))),1,0)),0) -> 0 | CG24: =IF(AND(ISNUMBER(AG24),AG24<0),1,0) -> 0 | CH24: =IF(OR(AND(ISNUMBER(U24),U24>Parameters!$B$74),AND(ISNUMBER(AF24),AF24>Parameters!$B$75),AND(ISNUMBER(AE24),AE24>Parameters!$B$76)),1,0) -> 0 | CI24: =IF(AND(ISNUMBER(BC24),BC24>=0,BC24<=Parameters!$B$77),1,0) -> 0 | CJ24: =IF(CF24=1,1,MIN(CD24,IF(CE24=1,3,6),IF(CG24=1,IF(BF24="Early",Parameters!$B$73,Parameters!$B$72),6),IF(CH24=1,3,6),IF(CI24=1,3,6))) -> 5 | CK24: =INDEX(Parameters!$F$2:$F$7,CJ24) -> Buy | CL24: =IF(CF24=1,"Hard sell: breakdown; ","")&IF(CE24=1,"Insufficient history; ","")&IF(AND(CF24=0,CG24=1),"Below 200D; ","")&IF(CH24=1,"Extended - wait for pullback; ","")&IF(CI24=1,"Earnings within "&Parameters!$B$77&"d; ","")
A25: SOXX | B25: 7 | C25: 7 | D25: 56.8 | E25: 8.1 | G25: iShares Semiconductor ETF | H25: ETFs | I25: 520.63 | J25: USD | L25: 3483886592 | M25: 46000 | N25: 111.11 | O25: 46091 | P25: estimated | Q25: -2.14 | R25: 0.68 | S25: 3.83 | T25: 1.01 | U25: -2.54 | V25: -3.86 | W25: 52.19 | X25: 109.04 | AC25: -8.5 | AD25: -20.63 | AE25: 48.88 | AF25: -2.33 | AG25: 19.6 | AH25: Golden | AI25: 2.22 | AJ25: -7.46 | AR25: 300 | AS25: 46275 | AT25: 0 | AU25: 0 | AW25: 0 | AX25: 0 | AZ25: 0 | BA25: 106.71 | BB25: 66.51 | BC25: =IF(AND(ISNUMBER(O25),ISNUMBER(AS25)),O25-AS25,"") -> -184 | BD25: =IF(OR(ISNUMBER(SEARCH("ETF",H25)),AND(F25="",AO25="")),1,0) -> 1 | BE25: =IF(ISNUMBER(L25),IF(L25>=Parameters!$B$3,2,IF(L25>=Parameters!$B$4,1,0)),0)+IF(ISNUMBER(AW25),IF(AW25>0,IF(AND(ISNUMBER(AM25),AM25>=Parameters!$B$5),2,1),0),0)+IF(ISNUMBER(AX25),IF(AND(AX25>0,ISNUMBER(AY25),AY25>=Parameters!$B$6),1,0),0)+IF(ISNUMBER(AO25),IF(AND(AO25>0,AO25<=Parameters!$B$7),1,0),0)+IF(ISNUMBER(F25),IF(F25>=Parameters!$B$8,1,0),0) -> 0 | BF25: =IF(BD25=1,"ETF",IF(OR(AND(ISNUMBER(L25),L25>=Parameters!$B$10),BE25>=Parameters!$B$9),"Established","Early")) -> ETF | BG25: =IF(LEFT(AH25,6)="Golden",2,IF(LEFT(AH25,5)="Death",-2,0)) -> 2 | BH25: =IF(ISNUMBER(AG25),IF(AG25>Parameters!$B$12,2,IF(AG25>0,1,IF(AG25>=Parameters!$B$13,-1,-2))),0) -> 2 | BI25: =IF(ISNUMBER(AF25),IF(AND(AF25>=Parameters!$B$14,AF25<=Parameters!$B$15),1,IF(OR(AF25>Parameters!$B$16,AF25<Parameters!$B$17),-1,0)),0) -> 1 | BJ25: =IF(ISNUMBER(AE25),IF(AND(AE25>=Parameters!$B$18,AE25<=Parameters!$B$19),1,IF(OR(AE25>Parameters!$B$20,AE25<Parameters!$B$21),-1,0)),0) -> 1 | BK25: =IF(ISNUMBER(E25),IF(E25>Parameters!$B$22,1,IF(E25<Parameters!$B$23,-1,0)),0) -> 1 | BL25: =IF(ISNUMBER(C25),IF(C25>=Parameters!$B$24,1,IF(C25<=Parameters!$B$25,-1,0)),0) -> 1 | BM25: =IF(ISNUMBER(AJ25),IF(AND(AJ25>Parameters!$B$26,ISNUMBER(U25)),IF(U25<0,-1,1),0),0) -> 0 | BN25: =IF(ISNUMBER(AD25),IF(AD25>Parameters!$B$27,1,IF(AD25<Parameters!$B$28,-1,0)),0) -> 0 | BO25: =BG25+BH25+BI25+BJ25+BK25+BL25+BM25+BN25 -> 8 | BP25: =IF(ISNUMBER(F25),IF(F25>=Parameters!$B$30,2,IF(F25>=Parameters!$B$31,1,IF(F25<=Parameters!$B$32,-1,0))),0) -> 0 | BQ25: =IF(ISNUMBER(AK25),IF(AK25>Parameters!$B$33,1,IF(AK25<0,-1,0)),0) -> 0 | BR25: =IF(ISNUMBER(AL25),IF(AL25>Parameters!$B$34,1,IF(AL25<0,-1,0)),0) -> 0 | BS25: =IF(ISNUMBER(AP25),IF(AND(AP25>0,AP25<=Parameters!$B$35),1,IF(AP25>Parameters!$B$36,-1,0)),0) -> 0 | BT25: =IF(ISNUMBER(AY25),IF(AY25>Parameters!$B$37,1,IF(AY25<0,-1,0)),0) -> 0 | BU25: =IF(ISNUMBER(AZ25),IF(AZ25>0,1,0),0) -> 0 | BV25: =IF(ISNUMBER(AL25),IF(AL25>Parameters!$B$39,2,IF(AL25>Parameters!$B$40,1,IF(AL25<0,-2,IF(AL25<Parameters!$B$41,-1,0)))),0) -> 0 | BW25: =IF(ISNUMBER(AV25),IF(AV25>Parameters!$B$42,1,IF(AV25<Parameters!$B$43,-1,0)),0) -> 0 | BX25: =IF(AND(ISNUMBER(AX25),AX25>0),1,IF(AND(ISNUMBER(AY25),AY25<Parameters!$B$44),-1,0)) -> 0 | BY25: =IF(ISNUMBER(AW25),IF(AW25>0,1,0),0) -> 0 | BZ25: =IF(ISNUMBER(AQ25),IF(AQ25>Parameters!$B$46,-2,IF(AQ25>Parameters!$B$45,-1,0)),0) -> 0 | CA25: =IF(ISNUMBER(F25),IF(F25>=Parameters!$B$47,1,IF(F25<=Parameters!$B$48,-1,0)),0) -> 0 | CB25: =IF(BF25="Established",BP25+BQ25+BR25+BS25+BT25+BU25,IF(BF25="Early",BV25+BW25+BX25+BY25+BZ25+CA25,0)) -> 0 | CC25: =IF(BF25="Established",BO25+CB25,IF(BF25="Early",BO25+Parameters!$B$50*CB25,BO25)) -> 8 | CD25: =IF(BF25="Established",IF(CC25>=Parameters!$B$51,6,IF(CC25>=Parameters!$B$52,5,IF(CC25>=Parameters!$B$53,4,IF(CC25>=Parameters!$B$54,3,IF(CC25>=Parameters!$B$55,2,1))))),IF(BF25="Early",IF(CC25>=Parameters!$B$56,5,IF(CC25>=Parameters!$B$57,4,IF(CC25>=Parameters!$B$58,3,IF(CC25>=Parameters!$B$59,2,1)))),IF(CC25>=Parameters!$B$60,6,IF(CC25>=Parameters!$B$61,5,IF(CC25>=Parameters!$B$62,4,IF(CC25>=Parameters!$B$63,3,IF(CC25>=Parameters!$B$64,2,1))))))) -> 6 | CE25: =IF(AND(ISNUMBER(AR25),AR25<Parameters!$B$66),1,0) -> 0 | CF25: =IF(AND(LEFT(AH25,5)="Death",ISNUMBER(AG25)),IF(BF25="Early",IF(AND(AG25<Parameters!$B$70,ISNUMBER(U25),U25<Parameters!$B$71),1,0),IF(AND(AG25<Parameters!$B$67,OR(AND(ISNUMBER(U25),U25<Parameters!$B$68),AND(ISNUMBER(V25),V25<Parameters!$B$69))),1,0)),0) -> 0 | CG25: =IF(AND(ISNUMBER(AG25),AG25<0),1,0) -> 0 | CH25: =IF(OR(AND(ISNUMBER(U25),U25>Parameters!$B$74),AND(ISNUMBER(AF25),AF25>Parameters!$B$75),AND(ISNUMBER(AE25),AE25>Parameters!$B$76)),1,0) -> 0 | CI25: =IF(AND(ISNUMBER(BC25),BC25>=0,BC25<=Parameters!$B$77),1,0) -> 0 | CJ25: =IF(CF25=1,1,MIN(CD25,IF(CE25=1,3,6),IF(CG25=1,IF(BF25="Early",Parameters!$B$73,Parameters!$B$72),6),IF(CH25=1,3,6),IF(CI25=1,3,6))) -> 6 | CK25: =INDEX(Parameters!$F$2:$F$7,CJ25) -> Strong Buy | CL25: =IF(CF25=1,"Hard sell: breakdown; ","")&IF(CE25=1,"Insufficient history; ","")&IF(AND(CF25=0,CG25=1),"Below 200D; ","")&IF(CH25=1,"Extended - wait for pullback; ","")&IF(CI25=1,"Earnings within "&Parameters!$B$77&"d; ","")
A26: AMZN | B26: 7 | C26: 5 | D26: 39.5 | E26: 10.3 | F26: 9 | G26: Amazon.com, Inc. | H26: Mag 7 | I26: 252.88 | J26: USD | K26: Consumer Cyclical | L26: 2722465437709 | M26: 46233 | N26: 214.21 | O26: 46324 | P26: estimated | Q26: 0.19 | R26: -1.78 | S26: -0.83 | T26: -2.85 | U26: -7.12 | V26: 6.25 | W26: 18.92 | X26: 6.14 | AC26: 1.61 | AD26: -11.95 | AE26: 44.59 | AF26: -0.82 | AG26: 5.53 | AH26: Golden (88d) | AI26: -1.37 | AJ26: -22.11 | AK26: 244.9 | AL26: 19.6 | AM26: 17.44 | AN26: 30.56 | AO26: 24.72 | AP26: 0.09 | AQ26: 0.97 | AR26: 300 | AS26: 46275 | AT26: 775680032768 | AU26: 393809985536 | AV26: 50.77 | AW26: 135281000448 | AX26: 3219124992 | AY26: 0.42 | AZ26: -128647004160 | BA26: 29.02 | BB26: 62.36 | BC26: =IF(AND(ISNUMBER(O26),ISNUMBER(AS26)),O26-AS26,"") -> 49 | BD26: =IF(OR(ISNUMBER(SEARCH("ETF",H26)),AND(F26="",AO26="")),1,0) -> 0 | BE26: =IF(ISNUMBER(L26),IF(L26>=Parameters!$B$3,2,IF(L26>=Parameters!$B$4,1,0)),0)+IF(ISNUMBER(AW26),IF(AW26>0,IF(AND(ISNUMBER(AM26),AM26>=Parameters!$B$5),2,1),0),0)+IF(ISNUMBER(AX26),IF(AND(AX26>0,ISNUMBER(AY26),AY26>=Parameters!$B$6),1,0),0)+IF(ISNUMBER(AO26),IF(AND(AO26>0,AO26<=Parameters!$B$7),1,0),0)+IF(ISNUMBER(F26),IF(F26>=Parameters!$B$8,1,0),0) -> 6 | BF26: =IF(BD26=1,"ETF",IF(OR(AND(ISNUMBER(L26),L26>=Parameters!$B$10),BE26>=Parameters!$B$9),"Established","Early")) -> Established | BG26: =IF(LEFT(AH26,6)="Golden",2,IF(LEFT(AH26,5)="Death",-2,0)) -> 2 | BH26: =IF(ISNUMBER(AG26),IF(AG26>Parameters!$B$12,2,IF(AG26>0,1,IF(AG26>=Parameters!$B$13,-1,-2))),0) -> 1 | BI26: =IF(ISNUMBER(AF26),IF(AND(AF26>=Parameters!$B$14,AF26<=Parameters!$B$15),1,IF(OR(AF26>Parameters!$B$16,AF26<Parameters!$B$17),-1,0)),0) -> 1 | BJ26: =IF(ISNUMBER(AE26),IF(AND(AE26>=Parameters!$B$18,AE26<=Parameters!$B$19),1,IF(OR(AE26>Parameters!$B$20,AE26<Parameters!$B$21),-1,0)),0) -> 0 | BK26: =IF(ISNUMBER(E26),IF(E26>Parameters!$B$22,1,IF(E26<Parameters!$B$23,-1,0)),0) -> 1 | BL26: =IF(ISNUMBER(C26),IF(C26>=Parameters!$B$24,1,IF(C26<=Parameters!$B$25,-1,0)),0) -> 0 | BM26: =IF(ISNUMBER(AJ26),IF(AND(AJ26>Parameters!$B$26,ISNUMBER(U26)),IF(U26<0,-1,1),0),0) -> 0 | BN26: =IF(ISNUMBER(AD26),IF(AD26>Parameters!$B$27,1,IF(AD26<Parameters!$B$28,-1,0)),0) -> 0 | BO26: =BG26+BH26+BI26+BJ26+BK26+BL26+BM26+BN26 -> 5 | BP26: =IF(ISNUMBER(F26),IF(F26>=Parameters!$B$30,2,IF(F26>=Parameters!$B$31,1,IF(F26<=Parameters!$B$32,-1,0))),0) -> 2 | BQ26: =IF(ISNUMBER(AK26),IF(AK26>Parameters!$B$33,1,IF(AK26<0,-1,0)),0) -> 1 | BR26: =IF(ISNUMBER(AL26),IF(AL26>Parameters!$B$34,1,IF(AL26<0,-1,0)),0) -> 1 | BS26: =IF(ISNUMBER(AP26),IF(AND(AP26>0,AP26<=Parameters!$B$35),1,IF(AP26>Parameters!$B$36,-1,0)),0) -> 1 | BT26: =IF(ISNUMBER(AY26),IF(AY26>Parameters!$B$37,1,IF(AY26<0,-1,0)),0) -> 0 | BU26: =IF(ISNUMBER(AZ26),IF(AZ26>0,1,0),0) -> 0 | BV26: =IF(ISNUMBER(AL26),IF(AL26>Parameters!$B$39,2,IF(AL26>Parameters!$B$40,1,IF(AL26<0,-2,IF(AL26<Parameters!$B$41,-1,0)))),0) -> 1 | BW26: =IF(ISNUMBER(AV26),IF(AV26>Parameters!$B$42,1,IF(AV26<Parameters!$B$43,-1,0)),0) -> 1 | BX26: =IF(AND(ISNUMBER(AX26),AX26>0),1,IF(AND(ISNUMBER(AY26),AY26<Parameters!$B$44),-1,0)) -> 1 | BY26: =IF(ISNUMBER(AW26),IF(AW26>0,1,0),0) -> 1 | BZ26: =IF(ISNUMBER(AQ26),IF(AQ26>Parameters!$B$46,-2,IF(AQ26>Parameters!$B$45,-1,0)),0) -> 0 | CA26: =IF(ISNUMBER(F26),IF(F26>=Parameters!$B$47,1,IF(F26<=Parameters!$B$48,-1,0)),0) -> 1 | CB26: =IF(BF26="Established",BP26+BQ26+BR26+BS26+BT26+BU26,IF(BF26="Early",BV26+BW26+BX26+BY26+BZ26+CA26,0)) -> 5 | CC26: =IF(BF26="Established",BO26+CB26,IF(BF26="Early",BO26+Parameters!$B$50*CB26,BO26)) -> 10 | CD26: =IF(BF26="Established",IF(CC26>=Parameters!$B$51,6,IF(CC26>=Parameters!$B$52,5,IF(CC26>=Parameters!$B$53,4,IF(CC26>=Parameters!$B$54,3,IF(CC26>=Parameters!$B$55,2,1))))),IF(BF26="Early",IF(CC26>=Parameters!$B$56,5,IF(CC26>=Parameters!$B$57,4,IF(CC26>=Parameters!$B$58,3,IF(CC26>=Parameters!$B$59,2,1)))),IF(CC26>=Parameters!$B$60,6,IF(CC26>=Parameters!$B$61,5,IF(CC26>=Parameters!$B$62,4,IF(CC26>=Parameters!$B$63,3,IF(CC26>=Parameters!$B$64,2,1))))))) -> 5 | CE26: =IF(AND(ISNUMBER(AR26),AR26<Parameters!$B$66),1,0) -> 0 | CF26: =IF(AND(LEFT(AH26,5)="Death",ISNUMBER(AG26)),IF(BF26="Early",IF(AND(AG26<Parameters!$B$70,ISNUMBER(U26),U26<Parameters!$B$71),1,0),IF(AND(AG26<Parameters!$B$67,OR(AND(ISNUMBER(U26),U26<Parameters!$B$68),AND(ISNUMBER(V26),V26<Parameters!$B$69))),1,0)),0) -> 0 | CG26: =IF(AND(ISNUMBER(AG26),AG26<0),1,0) -> 0 | CH26: =IF(OR(AND(ISNUMBER(U26),U26>Parameters!$B$74),AND(ISNUMBER(AF26),AF26>Parameters!$B$75),AND(ISNUMBER(AE26),AE26>Parameters!$B$76)),1,0) -> 0 | CI26: =IF(AND(ISNUMBER(BC26),BC26>=0,BC26<=Parameters!$B$77),1,0) -> 0 | CJ26: =IF(CF26=1,1,MIN(CD26,IF(CE26=1,3,6),IF(CG26=1,IF(BF26="Early",Parameters!$B$73,Parameters!$B$72),6),IF(CH26=1,3,6),IF(CI26=1,3,6))) -> 5 | CK26: =INDEX(Parameters!$F$2:$F$7,CJ26) -> Buy | CL26: =IF(CF26=1,"Hard sell: breakdown; ","")&IF(CE26=1,"Insufficient history; ","")&IF(AND(CF26=0,CG26=1),"Below 200D; ","")&IF(CH26=1,"Extended - wait for pullback; ","")&IF(CI26=1,"Earnings within "&Parameters!$B$77&"d; ","")
A27: FLEX | B27: 7 | C27: 6 | D27: 55.2 | E27: -1 | F27: 8 | G27: Flex Ltd. | H27: Hardware | I27: 109.59 | J27: USD | K27: Technology | L27: 41624327561 | M27: 46232 | N27: 8.7 | O27: 46323 | P27: estimated | Q27: -2.74 | R27: -1.43 | S27: 3.44 | T27: -1.99 | U27: -10.47 | V27: -21.44 | W27: 72.88 | X27: 95 | AC27: -26.08 | AD27: -34.32 | AE27: 43.81 | AF27: -8.98 | AG27: 14.55 | AH27: Golden | AI27: 0.58 | AJ27: -0.72 | AK27: 48.4 | AL27: 20.6 | AM27: 3.32 | AN27: 18.38 | AO27: 15.4 | AP27: 0.83 | AQ27: 2.56 | AR27: 300 | AS27: 46275 | AT27: 29266999296 | AU27: 2788999936 | AV27: 9.53 | AW27: 973000000 | AX27: 625750016 | AY27: 2.14 | AZ27: -3089999872 | BA27: 106.5 | BB27: 49.67 | BC27: =IF(AND(ISNUMBER(O27),ISNUMBER(AS27)),O27-AS27,"") -> 48 | BD27: =IF(OR(ISNUMBER(SEARCH("ETF",H27)),AND(F27="",AO27="")),1,0) -> 0 | BE27: =IF(ISNUMBER(L27),IF(L27>=Parameters!$B$3,2,IF(L27>=Parameters!$B$4,1,0)),0)+IF(ISNUMBER(AW27),IF(AW27>0,IF(AND(ISNUMBER(AM27),AM27>=Parameters!$B$5),2,1),0),0)+IF(ISNUMBER(AX27),IF(AND(AX27>0,ISNUMBER(AY27),AY27>=Parameters!$B$6),1,0),0)+IF(ISNUMBER(AO27),IF(AND(AO27>0,AO27<=Parameters!$B$7),1,0),0)+IF(ISNUMBER(F27),IF(F27>=Parameters!$B$8,1,0),0) -> 4 | BF27: =IF(BD27=1,"ETF",IF(OR(AND(ISNUMBER(L27),L27>=Parameters!$B$10),BE27>=Parameters!$B$9),"Established","Early")) -> Early | BG27: =IF(LEFT(AH27,6)="Golden",2,IF(LEFT(AH27,5)="Death",-2,0)) -> 2 | BH27: =IF(ISNUMBER(AG27),IF(AG27>Parameters!$B$12,2,IF(AG27>0,1,IF(AG27>=Parameters!$B$13,-1,-2))),0) -> 2 | BI27: =IF(ISNUMBER(AF27),IF(AND(AF27>=Parameters!$B$14,AF27<=Parameters!$B$15),1,IF(OR(AF27>Parameters!$B$16,AF27<Parameters!$B$17),-1,0)),0) -> -1 | BJ27: =IF(ISNUMBER(AE27),IF(AND(AE27>=Parameters!$B$18,AE27<=Parameters!$B$19),1,IF(OR(AE27>Parameters!$B$20,AE27<Parameters!$B$21),-1,0)),0) -> 0 | BK27: =IF(ISNUMBER(E27),IF(E27>Parameters!$B$22,1,IF(E27<Parameters!$B$23,-1,0)),0) -> 0 | BL27: =IF(ISNUMBER(C27),IF(C27>=Parameters!$B$24,1,IF(C27<=Parameters!$B$25,-1,0)),0) -> 0 | BM27: =IF(ISNUMBER(AJ27),IF(AND(AJ27>Parameters!$B$26,ISNUMBER(U27)),IF(U27<0,-1,1),0),0) -> 0 | BN27: =IF(ISNUMBER(AD27),IF(AD27>Parameters!$B$27,1,IF(AD27<Parameters!$B$28,-1,0)),0) -> -1 | BO27: =BG27+BH27+BI27+BJ27+BK27+BL27+BM27+BN27 -> 2 | BP27: =IF(ISNUMBER(F27),IF(F27>=Parameters!$B$30,2,IF(F27>=Parameters!$B$31,1,IF(F27<=Parameters!$B$32,-1,0))),0) -> 2 | BQ27: =IF(ISNUMBER(AK27),IF(AK27>Parameters!$B$33,1,IF(AK27<0,-1,0)),0) -> 1 | BR27: =IF(ISNUMBER(AL27),IF(AL27>Parameters!$B$34,1,IF(AL27<0,-1,0)),0) -> 1 | BS27: =IF(ISNUMBER(AP27),IF(AND(AP27>0,AP27<=Parameters!$B$35),1,IF(AP27>Parameters!$B$36,-1,0)),0) -> 1 | BT27: =IF(ISNUMBER(AY27),IF(AY27>Parameters!$B$37,1,IF(AY27<0,-1,0)),0) -> 0 | BU27: =IF(ISNUMBER(AZ27),IF(AZ27>0,1,0),0) -> 0 | BV27: =IF(ISNUMBER(AL27),IF(AL27>Parameters!$B$39,2,IF(AL27>Parameters!$B$40,1,IF(AL27<0,-2,IF(AL27<Parameters!$B$41,-1,0)))),0) -> 1 | BW27: =IF(ISNUMBER(AV27),IF(AV27>Parameters!$B$42,1,IF(AV27<Parameters!$B$43,-1,0)),0) -> -1 | BX27: =IF(AND(ISNUMBER(AX27),AX27>0),1,IF(AND(ISNUMBER(AY27),AY27<Parameters!$B$44),-1,0)) -> 1 | BY27: =IF(ISNUMBER(AW27),IF(AW27>0,1,0),0) -> 1 | BZ27: =IF(ISNUMBER(AQ27),IF(AQ27>Parameters!$B$46,-2,IF(AQ27>Parameters!$B$45,-1,0)),0) -> 0 | CA27: =IF(ISNUMBER(F27),IF(F27>=Parameters!$B$47,1,IF(F27<=Parameters!$B$48,-1,0)),0) -> 1 | CB27: =IF(BF27="Established",BP27+BQ27+BR27+BS27+BT27+BU27,IF(BF27="Early",BV27+BW27+BX27+BY27+BZ27+CA27,0)) -> 3 | CC27: =IF(BF27="Established",BO27+CB27,IF(BF27="Early",BO27+Parameters!$B$50*CB27,BO27)) -> 3.5 | CD27: =IF(BF27="Established",IF(CC27>=Parameters!$B$51,6,IF(CC27>=Parameters!$B$52,5,IF(CC27>=Parameters!$B$53,4,IF(CC27>=Parameters!$B$54,3,IF(CC27>=Parameters!$B$55,2,1))))),IF(BF27="Early",IF(CC27>=Parameters!$B$56,5,IF(CC27>=Parameters!$B$57,4,IF(CC27>=Parameters!$B$58,3,IF(CC27>=Parameters!$B$59,2,1)))),IF(CC27>=Parameters!$B$60,6,IF(CC27>=Parameters!$B$61,5,IF(CC27>=Parameters!$B$62,4,IF(CC27>=Parameters!$B$63,3,IF(CC27>=Parameters!$B$64,2,1))))))) -> 3 | CE27: =IF(AND(ISNUMBER(AR27),AR27<Parameters!$B$66),1,0) -> 0 | CF27: =IF(AND(LEFT(AH27,5)="Death",ISNUMBER(AG27)),IF(BF27="Early",IF(AND(AG27<Parameters!$B$70,ISNUMBER(U27),U27<Parameters!$B$71),1,0),IF(AND(AG27<Parameters!$B$67,OR(AND(ISNUMBER(U27),U27<Parameters!$B$68),AND(ISNUMBER(V27),V27<Parameters!$B$69))),1,0)),0) -> 0 | CG27: =IF(AND(ISNUMBER(AG27),AG27<0),1,0) -> 0 | CH27: =IF(OR(AND(ISNUMBER(U27),U27>Parameters!$B$74),AND(ISNUMBER(AF27),AF27>Parameters!$B$75),AND(ISNUMBER(AE27),AE27>Parameters!$B$76)),1,0) -> 0 | CI27: =IF(AND(ISNUMBER(BC27),BC27>=0,BC27<=Parameters!$B$77),1,0) -> 0 | CJ27: =IF(CF27=1,1,MIN(CD27,IF(CE27=1,3,6),IF(CG27=1,IF(BF27="Early",Parameters!$B$73,Parameters!$B$72),6),IF(CH27=1,3,6),IF(CI27=1,3,6))) -> 3 | CK27: =INDEX(Parameters!$F$2:$F$7,CJ27) -> Hold | CL27: =IF(CF27=1,"Hard sell: breakdown; ","")&IF(CE27=1,"Insufficient history; ","")&IF(AND(CF27=0,CG27=1),"Below 200D; ","")&IF(CH27=1,"Extended - wait for pullback; ","")&IF(CI27=1,"Earnings within "&Parameters!$B$77&"d; ","")
A28: BUG | B28: 7 | C28: 7 | D28: 66.3 | E28: -2.1 | G28: Global X Cybersecurity ETF | H28: ETFs | I28: 41.32 | J28: USD | M28: 46114 | N28: 14.52 | O28: 46205 | P28: estimated | Q28: 1.09 | R28: 0.07 | S28: 1.86 | T28: 3.34 | U28: -3.74 | V28: 23 | W28: 54.45 | X28: 20.24 | AC28: 18.36 | AD28: -7.26 | AE28: 51.1 | AF28: 1.81 | AG28: 27.81 | AH28: Golden (57d) | AI28: -0.2 | AJ28: -34.75 | AR28: 300 | AS28: 46275 | AT28: 0 | AU28: 0 | AW28: 0 | AX28: 0 | AZ28: 0 | BA28: 78.51 | BB28: 84.89 | BC28: =IF(AND(ISNUMBER(O28),ISNUMBER(AS28)),O28-AS28,"") -> -70 | BD28: =IF(OR(ISNUMBER(SEARCH("ETF",H28)),AND(F28="",AO28="")),1,0) -> 1 | BE28: =IF(ISNUMBER(L28),IF(L28>=Parameters!$B$3,2,IF(L28>=Parameters!$B$4,1,0)),0)+IF(ISNUMBER(AW28),IF(AW28>0,IF(AND(ISNUMBER(AM28),AM28>=Parameters!$B$5),2,1),0),0)+IF(ISNUMBER(AX28),IF(AND(AX28>0,ISNUMBER(AY28),AY28>=Parameters!$B$6),1,0),0)+IF(ISNUMBER(AO28),IF(AND(AO28>0,AO28<=Parameters!$B$7),1,0),0)+IF(ISNUMBER(F28),IF(F28>=Parameters!$B$8,1,0),0) -> 0 | BF28: =IF(BD28=1,"ETF",IF(OR(AND(ISNUMBER(L28),L28>=Parameters!$B$10),BE28>=Parameters!$B$9),"Established","Early")) -> ETF | BG28: =IF(LEFT(AH28,6)="Golden",2,IF(LEFT(AH28,5)="Death",-2,0)) -> 2 | BH28: =IF(ISNUMBER(AG28),IF(AG28>Parameters!$B$12,2,IF(AG28>0,1,IF(AG28>=Parameters!$B$13,-1,-2))),0) -> 2 | BI28: =IF(ISNUMBER(AF28),IF(AND(AF28>=Parameters!$B$14,AF28<=Parameters!$B$15),1,IF(OR(AF28>Parameters!$B$16,AF28<Parameters!$B$17),-1,0)),0) -> 1 | BJ28: =IF(ISNUMBER(AE28),IF(AND(AE28>=Parameters!$B$18,AE28<=Parameters!$B$19),1,IF(OR(AE28>Parameters!$B$20,AE28<Parameters!$B$21),-1,0)),0) -> 1 | BK28: =IF(ISNUMBER(E28),IF(E28>Parameters!$B$22,1,IF(E28<Parameters!$B$23,-1,0)),0) -> 0 | BL28: =IF(ISNUMBER(C28),IF(C28>=Parameters!$B$24,1,IF(C28<=Parameters!$B$25,-1,0)),0) -> 1 | BM28: =IF(ISNUMBER(AJ28),IF(AND(AJ28>Parameters!$B$26,ISNUMBER(U28)),IF(U28<0,-1,1),0),0) -> 0 | BN28: =IF(ISNUMBER(AD28),IF(AD28>Parameters!$B$27,1,IF(AD28<Parameters!$B$28,-1,0)),0) -> 1 | BO28: =BG28+BH28+BI28+BJ28+BK28+BL28+BM28+BN28 -> 8 | BP28: =IF(ISNUMBER(F28),IF(F28>=Parameters!$B$30,2,IF(F28>=Parameters!$B$31,1,IF(F28<=Parameters!$B$32,-1,0))),0) -> 0 | BQ28: =IF(ISNUMBER(AK28),IF(AK28>Parameters!$B$33,1,IF(AK28<0,-1,0)),0) -> 0 | BR28: =IF(ISNUMBER(AL28),IF(AL28>Parameters!$B$34,1,IF(AL28<0,-1,0)),0) -> 0 | BS28: =IF(ISNUMBER(AP28),IF(AND(AP28>0,AP28<=Parameters!$B$35),1,IF(AP28>Parameters!$B$36,-1,0)),0) -> 0 | BT28: =IF(ISNUMBER(AY28),IF(AY28>Parameters!$B$37,1,IF(AY28<0,-1,0)),0) -> 0 | BU28: =IF(ISNUMBER(AZ28),IF(AZ28>0,1,0),0) -> 0 | BV28: =IF(ISNUMBER(AL28),IF(AL28>Parameters!$B$39,2,IF(AL28>Parameters!$B$40,1,IF(AL28<0,-2,IF(AL28<Parameters!$B$41,-1,0)))),0) -> 0 | BW28: =IF(ISNUMBER(AV28),IF(AV28>Parameters!$B$42,1,IF(AV28<Parameters!$B$43,-1,0)),0) -> 0 | BX28: =IF(AND(ISNUMBER(AX28),AX28>0),1,IF(AND(ISNUMBER(AY28),AY28<Parameters!$B$44),-1,0)) -> 0 | BY28: =IF(ISNUMBER(AW28),IF(AW28>0,1,0),0) -> 0 | BZ28: =IF(ISNUMBER(AQ28),IF(AQ28>Parameters!$B$46,-2,IF(AQ28>Parameters!$B$45,-1,0)),0) -> 0 | CA28: =IF(ISNUMBER(F28),IF(F28>=Parameters!$B$47,1,IF(F28<=Parameters!$B$48,-1,0)),0) -> 0 | CB28: =IF(BF28="Established",BP28+BQ28+BR28+BS28+BT28+BU28,IF(BF28="Early",BV28+BW28+BX28+BY28+BZ28+CA28,0)) -> 0 | CC28: =IF(BF28="Established",BO28+CB28,IF(BF28="Early",BO28+Parameters!$B$50*CB28,BO28)) -> 8 | CD28: =IF(BF28="Established",IF(CC28>=Parameters!$B$51,6,IF(CC28>=Parameters!$B$52,5,IF(CC28>=Parameters!$B$53,4,IF(CC28>=Parameters!$B$54,3,IF(CC28>=Parameters!$B$55,2,1))))),IF(BF28="Early",IF(CC28>=Parameters!$B$56,5,IF(CC28>=Parameters!$B$57,4,IF(CC28>=Parameters!$B$58,3,IF(CC28>=Parameters!$B$59,2,1)))),IF(CC28>=Parameters!$B$60,6,IF(CC28>=Parameters!$B$61,5,IF(CC28>=Parameters!$B$62,4,IF(CC28>=Parameters!$B$63,3,IF(CC28>=Parameters!$B$64,2,1))))))) -> 6 | CE28: =IF(AND(ISNUMBER(AR28),AR28<Parameters!$B$66),1,0) -> 0 | CF28: =IF(AND(LEFT(AH28,5)="Death",ISNUMBER(AG28)),IF(BF28="Early",IF(AND(AG28<Parameters!$B$70,ISNUMBER(U28),U28<Parameters!$B$71),1,0),IF(AND(AG28<Parameters!$B$67,OR(AND(ISNUMBER(U28),U28<Parameters!$B$68),AND(ISNUMBER(V28),V28<Parameters!$B$69))),1,0)),0) -> 0 | CG28: =IF(AND(ISNUMBER(AG28),AG28<0),1,0) -> 0 | CH28: =IF(OR(AND(ISNUMBER(U28),U28>Parameters!$B$74),AND(ISNUMBER(AF28),AF28>Parameters!$B$75),AND(ISNUMBER(AE28),AE28>Parameters!$B$76)),1,0) -> 0 | CI28: =IF(AND(ISNUMBER(BC28),BC28>=0,BC28<=Parameters!$B$77),1,0) -> 0 | CJ28: =IF(CF28=1,1,MIN(CD28,IF(CE28=1,3,6),IF(CG28=1,IF(BF28="Early",Parameters!$B$73,Parameters!$B$72),6),IF(CH28=1,3,6),IF(CI28=1,3,6))) -> 6 | CK28: =INDEX(Parameters!$F$2:$F$7,CJ28) -> Strong Buy | CL28: =IF(CF28=1,"Hard sell: breakdown; ","")&IF(CE28=1,"Insufficient history; ","")&IF(AND(CF28=0,CG28=1),"Below 200D; ","")&IF(CH28=1,"Extended - wait for pullback; ","")&IF(CI28=1,"Earnings within "&Parameters!$B$77&"d; ","")
A29: SMH | B29: 7 | C29: 7 | D29: 56.4 | E29: 7.2 | G29: VanEck Semiconductor ETF | H29: Chips | I29: 563.67 | J29: USD | L29: 5911077376 | M29: 46211 | N29: 25 | O29: 46302 | P29: estimated | Q29: -1.85 | R29: 0.1 | S29: 2.4 | T29: 1.42 | U29: -1.62 | V29: -1.27 | W29: 40.56 | X29: 89.27 | AC29: -5.91 | AD29: -16.1 | AE29: 49.37 | AF29: -1.15 | AG29: 17.2 | AH29: Golden | AI29: 1.82 | AJ29: -16.48 | AR29: 300 | AS29: 46275 | AT29: 0 | AU29: 0 | AW29: 0 | AX29: 0 | AZ29: 0 | BA29: 88.66 | BB29: 71.01 | BC29: =IF(AND(ISNUMBER(O29),ISNUMBER(AS29)),O29-AS29,"") -> 27 | BD29: =IF(OR(ISNUMBER(SEARCH("ETF",H29)),AND(F29="",AO29="")),1,0) -> 1 | BE29: =IF(ISNUMBER(L29),IF(L29>=Parameters!$B$3,2,IF(L29>=Parameters!$B$4,1,0)),0)+IF(ISNUMBER(AW29),IF(AW29>0,IF(AND(ISNUMBER(AM29),AM29>=Parameters!$B$5),2,1),0),0)+IF(ISNUMBER(AX29),IF(AND(AX29>0,ISNUMBER(AY29),AY29>=Parameters!$B$6),1,0),0)+IF(ISNUMBER(AO29),IF(AND(AO29>0,AO29<=Parameters!$B$7),1,0),0)+IF(ISNUMBER(F29),IF(F29>=Parameters!$B$8,1,0),0) -> 0 | BF29: =IF(BD29=1,"ETF",IF(OR(AND(ISNUMBER(L29),L29>=Parameters!$B$10),BE29>=Parameters!$B$9),"Established","Early")) -> ETF | BG29: =IF(LEFT(AH29,6)="Golden",2,IF(LEFT(AH29,5)="Death",-2,0)) -> 2 | BH29: =IF(ISNUMBER(AG29),IF(AG29>Parameters!$B$12,2,IF(AG29>0,1,IF(AG29>=Parameters!$B$13,-1,-2))),0) -> 2 | BI29: =IF(ISNUMBER(AF29),IF(AND(AF29>=Parameters!$B$14,AF29<=Parameters!$B$15),1,IF(OR(AF29>Parameters!$B$16,AF29<Parameters!$B$17),-1,0)),0) -> 1 | BJ29: =IF(ISNUMBER(AE29),IF(AND(AE29>=Parameters!$B$18,AE29<=Parameters!$B$19),1,IF(OR(AE29>Parameters!$B$20,AE29<Parameters!$B$21),-1,0)),0) -> 1 | BK29: =IF(ISNUMBER(E29),IF(E29>Parameters!$B$22,1,IF(E29<Parameters!$B$23,-1,0)),0) -> 1 | BL29: =IF(ISNUMBER(C29),IF(C29>=Parameters!$B$24,1,IF(C29<=Parameters!$B$25,-1,0)),0) -> 1 | BM29: =IF(ISNUMBER(AJ29),IF(AND(AJ29>Parameters!$B$26,ISNUMBER(U29)),IF(U29<0,-1,1),0),0) -> 0 | BN29: =IF(ISNUMBER(AD29),IF(AD29>Parameters!$B$27,1,IF(AD29<Parameters!$B$28,-1,0)),0) -> 0 | BO29: =BG29+BH29+BI29+BJ29+BK29+BL29+BM29+BN29 -> 8 | BP29: =IF(ISNUMBER(F29),IF(F29>=Parameters!$B$30,2,IF(F29>=Parameters!$B$31,1,IF(F29<=Parameters!$B$32,-1,0))),0) -> 0 | BQ29: =IF(ISNUMBER(AK29),IF(AK29>Parameters!$B$33,1,IF(AK29<0,-1,0)),0) -> 0 | BR29: =IF(ISNUMBER(AL29),IF(AL29>Parameters!$B$34,1,IF(AL29<0,-1,0)),0) -> 0 | BS29: =IF(ISNUMBER(AP29),IF(AND(AP29>0,AP29<=Parameters!$B$35),1,IF(AP29>Parameters!$B$36,-1,0)),0) -> 0 | BT29: =IF(ISNUMBER(AY29),IF(AY29>Parameters!$B$37,1,IF(AY29<0,-1,0)),0) -> 0 | BU29: =IF(ISNUMBER(AZ29),IF(AZ29>0,1,0),0) -> 0 | BV29: =IF(ISNUMBER(AL29),IF(AL29>Parameters!$B$39,2,IF(AL29>Parameters!$B$40,1,IF(AL29<0,-2,IF(AL29<Parameters!$B$41,-1,0)))),0) -> 0 | BW29: =IF(ISNUMBER(AV29),IF(AV29>Parameters!$B$42,1,IF(AV29<Parameters!$B$43,-1,0)),0) -> 0 | BX29: =IF(AND(ISNUMBER(AX29),AX29>0),1,IF(AND(ISNUMBER(AY29),AY29<Parameters!$B$44),-1,0)) -> 0 | BY29: =IF(ISNUMBER(AW29),IF(AW29>0,1,0),0) -> 0 | BZ29: =IF(ISNUMBER(AQ29),IF(AQ29>Parameters!$B$46,-2,IF(AQ29>Parameters!$B$45,-1,0)),0) -> 0 | CA29: =IF(ISNUMBER(F29),IF(F29>=Parameters!$B$47,1,IF(F29<=Parameters!$B$48,-1,0)),0) -> 0 | CB29: =IF(BF29="Established",BP29+BQ29+BR29+BS29+BT29+BU29,IF(BF29="Early",BV29+BW29+BX29+BY29+BZ29+CA29,0)) -> 0 | CC29: =IF(BF29="Established",BO29+CB29,IF(BF29="Early",BO29+Parameters!$B$50*CB29,BO29)) -> 8 | CD29: =IF(BF29="Established",IF(CC29>=Parameters!$B$51,6,IF(CC29>=Parameters!$B$52,5,IF(CC29>=Parameters!$B$53,4,IF(CC29>=Parameters!$B$54,3,IF(CC29>=Parameters!$B$55,2,1))))),IF(BF29="Early",IF(CC29>=Parameters!$B$56,5,IF(CC29>=Parameters!$B$57,4,IF(CC29>=Parameters!$B$58,3,IF(CC29>=Parameters!$B$59,2,1)))),IF(CC29>=Parameters!$B$60,6,IF(CC29>=Parameters!$B$61,5,IF(CC29>=Parameters!$B$62,4,IF(CC29>=Parameters!$B$63,3,IF(CC29>=Parameters!$B$64,2,1))))))) -> 6 | CE29: =IF(AND(ISNUMBER(AR29),AR29<Parameters!$B$66),1,0) -> 0 | CF29: =IF(AND(LEFT(AH29,5)="Death",ISNUMBER(AG29)),IF(BF29="Early",IF(AND(AG29<Parameters!$B$70,ISNUMBER(U29),U29<Parameters!$B$71),1,0),IF(AND(AG29<Parameters!$B$67,OR(AND(ISNUMBER(U29),U29<Parameters!$B$68),AND(ISNUMBER(V29),V29<Parameters!$B$69))),1,0)),0) -> 0 | CG29: =IF(AND(ISNUMBER(AG29),AG29<0),1,0) -> 0 | CH29: =IF(OR(AND(ISNUMBER(U29),U29>Parameters!$B$74),AND(ISNUMBER(AF29),AF29>Parameters!$B$75),AND(ISNUMBER(AE29),AE29>Parameters!$B$76)),1,0) -> 0 | CI29: =IF(AND(ISNUMBER(BC29),BC29>=0,BC29<=Parameters!$B$77),1,0) -> 0 | CJ29: =IF(CF29=1,1,MIN(CD29,IF(CE29=1,3,6),IF(CG29=1,IF(BF29="Early",Parameters!$B$73,Parameters!$B$72),6),IF(CH29=1,3,6),IF(CI29=1,3,6))) -> 6 | CK29: =INDEX(Parameters!$F$2:$F$7,CJ29) -> Strong Buy | CL29: =IF(CF29=1,"Hard sell: breakdown; ","")&IF(CE29=1,"Insufficient history; ","")&IF(AND(CF29=0,CG29=1),"Below 200D; ","")&IF(CH29=1,"Extended - wait for pullback; ","")&IF(CI29=1,"Earnings within "&Parameters!$B$77&"d; ","")
A30: CRM | B30: 7 | C30: 5 | D30: 32.6 | E30: 16.9 | F30: 9 | G30: Salesforce Inc | H30: Software | I30: 244.84 | J30: USD | K30: Technology | L30: 200943680000 | M30: 46260 | N30: 80.43 | O30: 46351 | P30: estimated | Q30: 0.28 | R30: -1.99 | S30: -4.71 | T30: 19.07 | U30: 23.99 | V30: 43.25 | W30: 26.12 | X30: -2.86 | AC30: 38.61 | AD30: -9.02 | AE30: 63.88 | AF30: 24.31 | AG30: 21.81 | AH30: Death | AI30: -0.01 | AJ30: -30.91 | AK30: 86.9 | AL30: 10.8 | AM30: 21.99 | AN30: 19.38 | AO30: 15.62 | AP30: 0.19 | AQ30: 3.32 | AR30: 300 | AS30: 46275 | AT30: 43938000896 | AU30: 33955999744 | AV30: 77.28 | AW30: 9662000128 | AX30: 17731874816 | AY30: 40.36 | AZ30: -30972999680 | BA30: 67.33 | BB30: 80.23 | BC30: =IF(AND(ISNUMBER(O30),ISNUMBER(AS30)),O30-AS30,"") -> 76 | BD30: =IF(OR(ISNUMBER(SEARCH("ETF",H30)),AND(F30="",AO30="")),1,0) -> 0 | BE30: =IF(ISNUMBER(L30),IF(L30>=Parameters!$B$3,2,IF(L30>=Parameters!$B$4,1,0)),0)+IF(ISNUMBER(AW30),IF(AW30>0,IF(AND(ISNUMBER(AM30),AM30>=Parameters!$B$5),2,1),0),0)+IF(ISNUMBER(AX30),IF(AND(AX30>0,ISNUMBER(AY30),AY30>=Parameters!$B$6),1,0),0)+IF(ISNUMBER(AO30),IF(AND(AO30>0,AO30<=Parameters!$B$7),1,0),0)+IF(ISNUMBER(F30),IF(F30>=Parameters!$B$8,1,0),0) -> 7 | BF30: =IF(BD30=1,"ETF",IF(OR(AND(ISNUMBER(L30),L30>=Parameters!$B$10),BE30>=Parameters!$B$9),"Established","Early")) -> Established | BG30: =IF(LEFT(AH30,6)="Golden",2,IF(LEFT(AH30,5)="Death",-2,0)) -> -2 | BH30: =IF(ISNUMBER(AG30),IF(AG30>Parameters!$B$12,2,IF(AG30>0,1,IF(AG30>=Parameters!$B$13,-1,-2))),0) -> 2 | BI30: =IF(ISNUMBER(AF30),IF(AND(AF30>=Parameters!$B$14,AF30<=Parameters!$B$15),1,IF(OR(AF30>Parameters!$B$16,AF30<Parameters!$B$17),-1,0)),0) -> -1 | BJ30: =IF(ISNUMBER(AE30),IF(AND(AE30>=Parameters!$B$18,AE30<=Parameters!$B$19),1,IF(OR(AE30>Parameters!$B$20,AE30<Parameters!$B$21),-1,0)),0) -> 1 | BK30: =IF(ISNUMBER(E30),IF(E30>Parameters!$B$22,1,IF(E30<Parameters!$B$23,-1,0)),0) -> 1 | BL30: =IF(ISNUMBER(C30),IF(C30>=Parameters!$B$24,1,IF(C30<=Parameters!$B$25,-1,0)),0) -> 0 | BM30: =IF(ISNUMBER(AJ30),IF(AND(AJ30>Parameters!$B$26,ISNUMBER(U30)),IF(U30<0,-1,1),0),0) -> 0 | BN30: =IF(ISNUMBER(AD30),IF(AD30>Parameters!$B$27,1,IF(AD30<Parameters!$B$28,-1,0)),0) -> 1 | BO30: =BG30+BH30+BI30+BJ30+BK30+BL30+BM30+BN30 -> 2 | BP30: =IF(ISNUMBER(F30),IF(F30>=Parameters!$B$30,2,IF(F30>=Parameters!$B$31,1,IF(F30<=Parameters!$B$32,-1,0))),0) -> 2 | BQ30: =IF(ISNUMBER(AK30),IF(AK30>Parameters!$B$33,1,IF(AK30<0,-1,0)),0) -> 1 | BR30: =IF(ISNUMBER(AL30),IF(AL30>Parameters!$B$34,1,IF(AL30<0,-1,0)),0) -> 1 | BS30: =IF(ISNUMBER(AP30),IF(AND(AP30>0,AP30<=Parameters!$B$35),1,IF(AP30>Parameters!$B$36,-1,0)),0) -> 1 | BT30: =IF(ISNUMBER(AY30),IF(AY30>Parameters!$B$37,1,IF(AY30<0,-1,0)),0) -> 1 | BU30: =IF(ISNUMBER(AZ30),IF(AZ30>0,1,0),0) -> 0 | BV30: =IF(ISNUMBER(AL30),IF(AL30>Parameters!$B$39,2,IF(AL30>Parameters!$B$40,1,IF(AL30<0,-2,IF(AL30<Parameters!$B$41,-1,0)))),0) -> 0 | BW30: =IF(ISNUMBER(AV30),IF(AV30>Parameters!$B$42,1,IF(AV30<Parameters!$B$43,-1,0)),0) -> 1 | BX30: =IF(AND(ISNUMBER(AX30),AX30>0),1,IF(AND(ISNUMBER(AY30),AY30<Parameters!$B$44),-1,0)) -> 1 | BY30: =IF(ISNUMBER(AW30),IF(AW30>0,1,0),0) -> 1 | BZ30: =IF(ISNUMBER(AQ30),IF(AQ30>Parameters!$B$46,-2,IF(AQ30>Parameters!$B$45,-1,0)),0) -> 0 | CA30: =IF(ISNUMBER(F30),IF(F30>=Parameters!$B$47,1,IF(F30<=Parameters!$B$48,-1,0)),0) -> 1 | CB30: =IF(BF30="Established",BP30+BQ30+BR30+BS30+BT30+BU30,IF(BF30="Early",BV30+BW30+BX30+BY30+BZ30+CA30,0)) -> 6 | CC30: =IF(BF30="Established",BO30+CB30,IF(BF30="Early",BO30+Parameters!$B$50*CB30,BO30)) -> 8 | CD30: =IF(BF30="Established",IF(CC30>=Parameters!$B$51,6,IF(CC30>=Parameters!$B$52,5,IF(CC30>=Parameters!$B$53,4,IF(CC30>=Parameters!$B$54,3,IF(CC30>=Parameters!$B$55,2,1))))),IF(BF30="Early",IF(CC30>=Parameters!$B$56,5,IF(CC30>=Parameters!$B$57,4,IF(CC30>=Parameters!$B$58,3,IF(CC30>=Parameters!$B$59,2,1)))),IF(CC30>=Parameters!$B$60,6,IF(CC30>=Parameters!$B$61,5,IF(CC30>=Parameters!$B$62,4,IF(CC30>=Parameters!$B$63,3,IF(CC30>=Parameters!$B$64,2,1))))))) -> 4 | CE30: =IF(AND(ISNUMBER(AR30),AR30<Parameters!$B$66),1,0) -> 0 | CF30: =IF(AND(LEFT(AH30,5)="Death",ISNUMBER(AG30)),IF(BF30="Early",IF(AND(AG30<Parameters!$B$70,ISNUMBER(U30),U30<Parameters!$B$71),1,0),IF(AND(AG30<Parameters!$B$67,OR(AND(ISNUMBER(U30),U30<Parameters!$B$68),AND(ISNUMBER(V30),V30<Parameters!$B$69))),1,0)),0) -> 0 | CG30: =IF(AND(ISNUMBER(AG30),AG30<0),1,0) -> 0 | CH30: =IF(OR(AND(ISNUMBER(U30),U30>Parameters!$B$74),AND(ISNUMBER(AF30),AF30>Parameters!$B$75),AND(ISNUMBER(AE30),AE30>Parameters!$B$76)),1,0) -> 1 | CI30: =IF(AND(ISNUMBER(BC30),BC30>=0,BC30<=Parameters!$B$77),1,0) -> 0 | CJ30: =IF(CF30=1,1,MIN(CD30,IF(CE30=1,3,6),IF(CG30=1,IF(BF30="Early",Parameters!$B$73,Parameters!$B$72),6),IF(CH30=1,3,6),IF(CI30=1,3,6))) -> 3 | CK30: =INDEX(Parameters!$F$2:$F$7,CJ30) -> Hold | CL30: =IF(CF30=1,"Hard sell: breakdown; ","")&IF(CE30=1,"Insufficient history; ","")&IF(AND(CF30=0,CG30=1),"Below 200D; ","")&IF(CH30=1,"Extended - wait for pullback; ","")&IF(CI30=1,"Earnings within "&Parameters!$B$77&"d; ","") -> Extended - wait for pullback;
A31: DDOG | B31: 6 | C31: 6 | D31: 66 | E31: -10 | F31: 7 | G31: Datadog, Inc. Class A Common Stock | H31: Software | I31: 226.82 | J31: USD | K31: Technology | L31: 80888830656 | M31: 46233 | N31: 4.38 | O31: 46324 | P31: estimated | Q31: 0.69 | R31: 7.15 | S31: 8.41 | T31: -0.37 | U31: -8.09 | V31: -0.36 | W31: 77.91 | X31: 61.48 | AC31: -5 | AD31: -22.51 | AE31: 46.85 | AF31: -8.36 | AG31: 28.06 | AH31: Golden (78d) | AI31: -0.38 | AJ31: -4.67 | AK31: 1583.3 | AL31: 35.6 | AM31: 4.48 | AN31: 4.7 | AO31: 70.1 | AP31: 0.35 | AQ31: 2.78 | AR31: 300 | AS31: 46275 | AT31: 3966725120 | AU31: 3154957056 | AV31: 79.54 | AW31: 177584000 | AX31: 1051412352 | AY31: 26.51 | AZ31: 3707637248 | BA31: 131.43 | BB31: 66.15 | BC31: =IF(AND(ISNUMBER(O31),ISNUMBER(AS31)),O31-AS31,"") -> 49 | BD31: =IF(OR(ISNUMBER(SEARCH("ETF",H31)),AND(F31="",AO31="")),1,0) -> 0 | BE31: =IF(ISNUMBER(L31),IF(L31>=Parameters!$B$3,2,IF(L31>=Parameters!$B$4,1,0)),0)+IF(ISNUMBER(AW31),IF(AW31>0,IF(AND(ISNUMBER(AM31),AM31>=Parameters!$B$5),2,1),0),0)+IF(ISNUMBER(AX31),IF(AND(AX31>0,ISNUMBER(AY31),AY31>=Parameters!$B$6),1,0),0)+IF(ISNUMBER(AO31),IF(AND(AO31>0,AO31<=Parameters!$B$7),1,0),0)+IF(ISNUMBER(F31),IF(F31>=Parameters!$B$8,1,0),0) -> 4 | BF31: =IF(BD31=1,"ETF",IF(OR(AND(ISNUMBER(L31),L31>=Parameters!$B$10),BE31>=Parameters!$B$9),"Established","Early")) -> Early | BG31: =IF(LEFT(AH31,6)="Golden",2,IF(LEFT(AH31,5)="Death",-2,0)) -> 2 | BH31: =IF(ISNUMBER(AG31),IF(AG31>Parameters!$B$12,2,IF(AG31>0,1,IF(AG31>=Parameters!$B$13,-1,-2))),0) -> 2 | BI31: =IF(ISNUMBER(AF31),IF(AND(AF31>=Parameters!$B$14,AF31<=Parameters!$B$15),1,IF(OR(AF31>Parameters!$B$16,AF31<Parameters!$B$17),-1,0)),0) -> -1 | BJ31: =IF(ISNUMBER(AE31),IF(AND(AE31>=Parameters!$B$18,AE31<=Parameters!$B$19),1,IF(OR(AE31>Parameters!$B$20,AE31<Parameters!$B$21),-1,0)),0) -> 1 | BK31: =IF(ISNUMBER(E31),IF(E31>Parameters!$B$22,1,IF(E31<Parameters!$B$23,-1,0)),0) -> -1 | BL31: =IF(ISNUMBER(C31),IF(C31>=Parameters!$B$24,1,IF(C31<=Parameters!$B$25,-1,0)),0) -> 0 | BM31: =IF(ISNUMBER(AJ31),IF(AND(AJ31>Parameters!$B$26,ISNUMBER(U31)),IF(U31<0,-1,1),0),0) -> 0 | BN31: =IF(ISNUMBER(AD31),IF(AD31>Parameters!$B$27,1,IF(AD31<Parameters!$B$28,-1,0)),0) -> 0 | BO31: =BG31+BH31+BI31+BJ31+BK31+BL31+BM31+BN31 -> 3 | BP31: =IF(ISNUMBER(F31),IF(F31>=Parameters!$B$30,2,IF(F31>=Parameters!$B$31,1,IF(F31<=Parameters!$B$32,-1,0))),0) -> 1 | BQ31: =IF(ISNUMBER(AK31),IF(AK31>Parameters!$B$33,1,IF(AK31<0,-1,0)),0) -> 1 | BR31: =IF(ISNUMBER(AL31),IF(AL31>Parameters!$B$34,1,IF(AL31<0,-1,0)),0) -> 1 | BS31: =IF(ISNUMBER(AP31),IF(AND(AP31>0,AP31<=Parameters!$B$35),1,IF(AP31>Parameters!$B$36,-1,0)),0) -> 1 | BT31: =IF(ISNUMBER(AY31),IF(AY31>Parameters!$B$37,1,IF(AY31<0,-1,0)),0) -> 1 | BU31: =IF(ISNUMBER(AZ31),IF(AZ31>0,1,0),0) -> 1 | BV31: =IF(ISNUMBER(AL31),IF(AL31>Parameters!$B$39,2,IF(AL31>Parameters!$B$40,1,IF(AL31<0,-2,IF(AL31<Parameters!$B$41,-1,0)))),0) -> 2 | BW31: =IF(ISNUMBER(AV31),IF(AV31>Parameters!$B$42,1,IF(AV31<Parameters!$B$43,-1,0)),0) -> 1 | BX31: =IF(AND(ISNUMBER(AX31),AX31>0),1,IF(AND(ISNUMBER(AY31),AY31<Parameters!$B$44),-1,0)) -> 1 | BY31: =IF(ISNUMBER(AW31),IF(AW31>0,1,0),0) -> 1 | BZ31: =IF(ISNUMBER(AQ31),IF(AQ31>Parameters!$B$46,-2,IF(AQ31>Parameters!$B$45,-1,0)),0) -> 0 | CA31: =IF(ISNUMBER(F31),IF(F31>=Parameters!$B$47,1,IF(F31<=Parameters!$B$48,-1,0)),0) -> 1 | CB31: =IF(BF31="Established",BP31+BQ31+BR31+BS31+BT31+BU31,IF(BF31="Early",BV31+BW31+BX31+BY31+BZ31+CA31,0)) -> 6 | CC31: =IF(BF31="Established",BO31+CB31,IF(BF31="Early",BO31+Parameters!$B$50*CB31,BO31)) -> 6 | CD31: =IF(BF31="Established",IF(CC31>=Parameters!$B$51,6,IF(CC31>=Parameters!$B$52,5,IF(CC31>=Parameters!$B$53,4,IF(CC31>=Parameters!$B$54,3,IF(CC31>=Parameters!$B$55,2,1))))),IF(BF31="Early",IF(CC31>=Parameters!$B$56,5,IF(CC31>=Parameters!$B$57,4,IF(CC31>=Parameters!$B$58,3,IF(CC31>=Parameters!$B$59,2,1)))),IF(CC31>=Parameters!$B$60,6,IF(CC31>=Parameters!$B$61,5,IF(CC31>=Parameters!$B$62,4,IF(CC31>=Parameters!$B$63,3,IF(CC31>=Parameters!$B$64,2,1))))))) -> 4 | CE31: =IF(AND(ISNUMBER(AR31),AR31<Parameters!$B$66),1,0) -> 0 | CF31: =IF(AND(LEFT(AH31,5)="Death",ISNUMBER(AG31)),IF(BF31="Early",IF(AND(AG31<Parameters!$B$70,ISNUMBER(U31),U31<Parameters!$B$71),1,0),IF(AND(AG31<Parameters!$B$67,OR(AND(ISNUMBER(U31),U31<Parameters!$B$68),AND(ISNUMBER(V31),V31<Parameters!$B$69))),1,0)),0) -> 0 | CG31: =IF(AND(ISNUMBER(AG31),AG31<0),1,0) -> 0 | CH31: =IF(OR(AND(ISNUMBER(U31),U31>Parameters!$B$74),AND(ISNUMBER(AF31),AF31>Parameters!$B$75),AND(ISNUMBER(AE31),AE31>Parameters!$B$76)),1,0) -> 0 | CI31: =IF(AND(ISNUMBER(BC31),BC31>=0,BC31<=Parameters!$B$77),1,0) -> 0 | CJ31: =IF(CF31=1,1,MIN(CD31,IF(CE31=1,3,6),IF(CG31=1,IF(BF31="Early",Parameters!$B$73,Parameters!$B$72),6),IF(CH31=1,3,6),IF(CI31=1,3,6))) -> 4 | CK31: =INDEX(Parameters!$F$2:$F$7,CJ31) -> Buy with Risk | CL31: =IF(CF31=1,"Hard sell: breakdown; ","")&IF(CE31=1,"Insufficient history; ","")&IF(AND(CF31=0,CG31=1),"Below 200D; ","")&IF(CH31=1,"Extended - wait for pullback; ","")&IF(CI31=1,"Earnings within "&Parameters!$B$77&"d; ","")
A32: AFRM | B32: 6 | C32: 5 | D32: 45.7 | E32: -6.2 | F32: 10 | G32: Affirm Holdings, Inc. | H32: Fin | I32: 68.07 | J32: USD | K32: Financial Services | L32: 22995258596 | M32: 46261 | N32: 484.71 | O32: 46352 | P32: estimated | Q32: -0.12 | R32: -5.45 | S32: -8.13 | T32: -10.97 | U32: -11.26 | V32: 8.37 | W32: 34.02 | X32: -23.02 | AC32: 3.73 | AD32: -26.46 | AE32: 37.91 | AF32: -10.9 | AG32: 2.23 | AH32: Golden (55d) | AI32: -0.84 | AJ32: -37.35 | AK32: 2234.7 | AL32: 33 | AM32: 45.29 | AN32: 45.13 | AO32: 14.55 | AP32: 0.01 | AQ32: 5.1 | AR32: 300 | AS32: 46275 | AT32: 4261082112 | AU32: 2084964992 | AV32: 48.93 | AW32: 1929793024 | AX32: 478676736 | AY32: 11.23 | AZ32: -8320907392 | BA32: 61.71 | BB32: 51.47 | BC32: =IF(AND(ISNUMBER(O32),ISNUMBER(AS32)),O32-AS32,"") -> 77 | BD32: =IF(OR(ISNUMBER(SEARCH("ETF",H32)),AND(F32="",AO32="")),1,0) -> 0 | BE32: =IF(ISNUMBER(L32),IF(L32>=Parameters!$B$3,2,IF(L32>=Parameters!$B$4,1,0)),0)+IF(ISNUMBER(AW32),IF(AW32>0,IF(AND(ISNUMBER(AM32),AM32>=Parameters!$B$5),2,1),0),0)+IF(ISNUMBER(AX32),IF(AND(AX32>0,ISNUMBER(AY32),AY32>=Parameters!$B$6),1,0),0)+IF(ISNUMBER(AO32),IF(AND(AO32>0,AO32<=Parameters!$B$7),1,0),0)+IF(ISNUMBER(F32),IF(F32>=Parameters!$B$8,1,0),0) -> 6 | BF32: =IF(BD32=1,"ETF",IF(OR(AND(ISNUMBER(L32),L32>=Parameters!$B$10),BE32>=Parameters!$B$9),"Established","Early")) -> Established | BG32: =IF(LEFT(AH32,6)="Golden",2,IF(LEFT(AH32,5)="Death",-2,0)) -> 2 | BH32: =IF(ISNUMBER(AG32),IF(AG32>Parameters!$B$12,2,IF(AG32>0,1,IF(AG32>=Parameters!$B$13,-1,-2))),0) -> 1 | BI32: =IF(ISNUMBER(AF32),IF(AND(AF32>=Parameters!$B$14,AF32<=Parameters!$B$15),1,IF(OR(AF32>Parameters!$B$16,AF32<Parameters!$B$17),-1,0)),0) -> -1 | BJ32: =IF(ISNUMBER(AE32),IF(AND(AE32>=Parameters!$B$18,AE32<=Parameters!$B$19),1,IF(OR(AE32>Parameters!$B$20,AE32<Parameters!$B$21),-1,0)),0) -> 0 | BK32: =IF(ISNUMBER(E32),IF(E32>Parameters!$B$22,1,IF(E32<Parameters!$B$23,-1,0)),0) -> -1 | BL32: =IF(ISNUMBER(C32),IF(C32>=Parameters!$B$24,1,IF(C32<=Parameters!$B$25,-1,0)),0) -> 0 | BM32: =IF(ISNUMBER(AJ32),IF(AND(AJ32>Parameters!$B$26,ISNUMBER(U32)),IF(U32<0,-1,1),0),0) -> 0 | BN32: =IF(ISNUMBER(AD32),IF(AD32>Parameters!$B$27,1,IF(AD32<Parameters!$B$28,-1,0)),0) -> 0 | BO32: =BG32+BH32+BI32+BJ32+BK32+BL32+BM32+BN32 -> 1 | BP32: =IF(ISNUMBER(F32),IF(F32>=Parameters!$B$30,2,IF(F32>=Parameters!$B$31,1,IF(F32<=Parameters!$B$32,-1,0))),0) -> 2 | BQ32: =IF(ISNUMBER(AK32),IF(AK32>Parameters!$B$33,1,IF(AK32<0,-1,0)),0) -> 1 | BR32: =IF(ISNUMBER(AL32),IF(AL32>Parameters!$B$34,1,IF(AL32<0,-1,0)),0) -> 1 | BS32: =IF(ISNUMBER(AP32),IF(AND(AP32>0,AP32<=Parameters!$B$35),1,IF(AP32>Parameters!$B$36,-1,0)),0) -> 1 | BT32: =IF(ISNUMBER(AY32),IF(AY32>Parameters!$B$37,1,IF(AY32<0,-1,0)),0) -> 1 | BU32: =IF(ISNUMBER(AZ32),IF(AZ32>0,1,0),0) -> 0 | BV32: =IF(ISNUMBER(AL32),IF(AL32>Parameters!$B$39,2,IF(AL32>Parameters!$B$40,1,IF(AL32<0,-2,IF(AL32<Parameters!$B$41,-1,0)))),0) -> 2 | BW32: =IF(ISNUMBER(AV32),IF(AV32>Parameters!$B$42,1,IF(AV32<Parameters!$B$43,-1,0)),0) -> 0 | BX32: =IF(AND(ISNUMBER(AX32),AX32>0),1,IF(AND(ISNUMBER(AY32),AY32<Parameters!$B$44),-1,0)) -> 1 | BY32: =IF(ISNUMBER(AW32),IF(AW32>0,1,0),0) -> 1 | BZ32: =IF(ISNUMBER(AQ32),IF(AQ32>Parameters!$B$46,-2,IF(AQ32>Parameters!$B$45,-1,0)),0) -> 0 | CA32: =IF(ISNUMBER(F32),IF(F32>=Parameters!$B$47,1,IF(F32<=Parameters!$B$48,-1,0)),0) -> 1 | CB32: =IF(BF32="Established",BP32+BQ32+BR32+BS32+BT32+BU32,IF(BF32="Early",BV32+BW32+BX32+BY32+BZ32+CA32,0)) -> 6 | CC32: =IF(BF32="Established",BO32+CB32,IF(BF32="Early",BO32+Parameters!$B$50*CB32,BO32)) -> 7 | CD32: =IF(BF32="Established",IF(CC32>=Parameters!$B$51,6,IF(CC32>=Parameters!$B$52,5,IF(CC32>=Parameters!$B$53,4,IF(CC32>=Parameters!$B$54,3,IF(CC32>=Parameters!$B$55,2,1))))),IF(BF32="Early",IF(CC32>=Parameters!$B$56,5,IF(CC32>=Parameters!$B$57,4,IF(CC32>=Parameters!$B$58,3,IF(CC32>=Parameters!$B$59,2,1)))),IF(CC32>=Parameters!$B$60,6,IF(CC32>=Parameters!$B$61,5,IF(CC32>=Parameters!$B$62,4,IF(CC32>=Parameters!$B$63,3,IF(CC32>=Parameters!$B$64,2,1))))))) -> 4 | CE32: =IF(AND(ISNUMBER(AR32),AR32<Parameters!$B$66),1,0) -> 0 | CF32: =IF(AND(LEFT(AH32,5)="Death",ISNUMBER(AG32)),IF(BF32="Early",IF(AND(AG32<Parameters!$B$70,ISNUMBER(U32),U32<Parameters!$B$71),1,0),IF(AND(AG32<Parameters!$B$67,OR(AND(ISNUMBER(U32),U32<Parameters!$B$68),AND(ISNUMBER(V32),V32<Parameters!$B$69))),1,0)),0) -> 0 | CG32: =IF(AND(ISNUMBER(AG32),AG32<0),1,0) -> 0 | CH32: =IF(OR(AND(ISNUMBER(U32),U32>Parameters!$B$74),AND(ISNUMBER(AF32),AF32>Parameters!$B$75),AND(ISNUMBER(AE32),AE32>Parameters!$B$76)),1,0) -> 0 | CI32: =IF(AND(ISNUMBER(BC32),BC32>=0,BC32<=Parameters!$B$77),1,0) -> 0 | CJ32: =IF(CF32=1,1,MIN(CD32,IF(CE32=1,3,6),IF(CG32=1,IF(BF32="Early",Parameters!$B$73,Parameters!$B$72),6),IF(CH32=1,3,6),IF(CI32=1,3,6))) -> 4 | CK32: =INDEX(Parameters!$F$2:$F$7,CJ32) -> Buy with Risk | CL32: =IF(CF32=1,"Hard sell: breakdown; ","")&IF(CE32=1,"Insufficient history; ","")&IF(AND(CF32=0,CG32=1),"Below 200D; ","")&IF(CH32=1,"Extended - wait for pullback; ","")&IF(CI32=1,"Earnings within "&Parameters!$B$77&"d; ","")
A33: ZM | B33: 6 | C33: 5 | D33: 36 | E33: 10.7 | F33: 9 | G33: Zoom Communications, Inc. Class A Common Stock | H33: Faded | I33: 95.68 | J33: USD | K33: Technology | L33: 28063757323 | M33: 46259 | N33: 4.73 | O33: 46350 | P33: estimated | Q33: -0.52 | R33: -0.27 | S33: -0.19 | T33: 1.97 | U33: -9.79 | V33: 1.83 | W33: 25.81 | X33: 11.75 | AC33: -2.81 | AD33: -16.61 | AE33: 44.94 | AF33: -0.8 | AG33: 5.53 | AH33: Golden (88d) | AI33: -0.88 | AJ33: -32.37 | AK33: 330.1 | AL33: 4.9 | AM33: 65.19 | AN33: 32.14 | AO33: 15.21 | AP33: 0.03 | AQ33: 2.8 | AR33: 300 | AS33: 46275 | AT33: 4993050112 | AU33: 3877772032 | AV33: 77.66 | AW33: 3255075072 | AX33: 1975528320 | AY33: 39.57 | AZ33: 7189448832 | BA33: 35.33 | BB33: 56.72 | BC33: =IF(AND(ISNUMBER(O33),ISNUMBER(AS33)),O33-AS33,"") -> 75 | BD33: =IF(OR(ISNUMBER(SEARCH("ETF",H33)),AND(F33="",AO33="")),1,0) -> 0 | BE33: =IF(ISNUMBER(L33),IF(L33>=Parameters!$B$3,2,IF(L33>=Parameters!$B$4,1,0)),0)+IF(ISNUMBER(AW33),IF(AW33>0,IF(AND(ISNUMBER(AM33),AM33>=Parameters!$B$5),2,1),0),0)+IF(ISNUMBER(AX33),IF(AND(AX33>0,ISNUMBER(AY33),AY33>=Parameters!$B$6),1,0),0)+IF(ISNUMBER(AO33),IF(AND(AO33>0,AO33<=Parameters!$B$7),1,0),0)+IF(ISNUMBER(F33),IF(F33>=Parameters!$B$8,1,0),0) -> 6 | BF33: =IF(BD33=1,"ETF",IF(OR(AND(ISNUMBER(L33),L33>=Parameters!$B$10),BE33>=Parameters!$B$9),"Established","Early")) -> Established | BG33: =IF(LEFT(AH33,6)="Golden",2,IF(LEFT(AH33,5)="Death",-2,0)) -> 2 | BH33: =IF(ISNUMBER(AG33),IF(AG33>Parameters!$B$12,2,IF(AG33>0,1,IF(AG33>=Parameters!$B$13,-1,-2))),0) -> 1 | BI33: =IF(ISNUMBER(AF33),IF(AND(AF33>=Parameters!$B$14,AF33<=Parameters!$B$15),1,IF(OR(AF33>Parameters!$B$16,AF33<Parameters!$B$17),-1,0)),0) -> 1 | BJ33: =IF(ISNUMBER(AE33),IF(AND(AE33>=Parameters!$B$18,AE33<=Parameters!$B$19),1,IF(OR(AE33>Parameters!$B$20,AE33<Parameters!$B$21),-1,0)),0) -> 0 | BK33: =IF(ISNUMBER(E33),IF(E33>Parameters!$B$22,1,IF(E33<Parameters!$B$23,-1,0)),0) -> 1 | BL33: =IF(ISNUMBER(C33),IF(C33>=Parameters!$B$24,1,IF(C33<=Parameters!$B$25,-1,0)),0) -> 0 | BM33: =IF(ISNUMBER(AJ33),IF(AND(AJ33>Parameters!$B$26,ISNUMBER(U33)),IF(U33<0,-1,1),0),0) -> 0 | BN33: =IF(ISNUMBER(AD33),IF(AD33>Parameters!$B$27,1,IF(AD33<Parameters!$B$28,-1,0)),0) -> 0 | BO33: =BG33+BH33+BI33+BJ33+BK33+BL33+BM33+BN33 -> 5 | BP33: =IF(ISNUMBER(F33),IF(F33>=Parameters!$B$30,2,IF(F33>=Parameters!$B$31,1,IF(F33<=Parameters!$B$32,-1,0))),0) -> 2 | BQ33: =IF(ISNUMBER(AK33),IF(AK33>Parameters!$B$33,1,IF(AK33<0,-1,0)),0) -> 1 | BR33: =IF(ISNUMBER(AL33),IF(AL33>Parameters!$B$34,1,IF(AL33<0,-1,0)),0) -> 0 | BS33: =IF(ISNUMBER(AP33),IF(AND(AP33>0,AP33<=Parameters!$B$35),1,IF(AP33>Parameters!$B$36,-1,0)),0) -> 1 | BT33: =IF(ISNUMBER(AY33),IF(AY33>Parameters!$B$37,1,IF(AY33<0,-1,0)),0) -> 1 | BU33: =IF(ISNUMBER(AZ33),IF(AZ33>0,1,0),0) -> 1 | BV33: =IF(ISNUMBER(AL33),IF(AL33>Parameters!$B$39,2,IF(AL33>Parameters!$B$40,1,IF(AL33<0,-2,IF(AL33<Parameters!$B$41,-1,0)))),0) -> -1 | BW33: =IF(ISNUMBER(AV33),IF(AV33>Parameters!$B$42,1,IF(AV33<Parameters!$B$43,-1,0)),0) -> 1 | BX33: =IF(AND(ISNUMBER(AX33),AX33>0),1,IF(AND(ISNUMBER(AY33),AY33<Parameters!$B$44),-1,0)) -> 1 | BY33: =IF(ISNUMBER(AW33),IF(AW33>0,1,0),0) -> 1 | BZ33: =IF(ISNUMBER(AQ33),IF(AQ33>Parameters!$B$46,-2,IF(AQ33>Parameters!$B$45,-1,0)),0) -> 0 | CA33: =IF(ISNUMBER(F33),IF(F33>=Parameters!$B$47,1,IF(F33<=Parameters!$B$48,-1,0)),0) -> 1 | CB33: =IF(BF33="Established",BP33+BQ33+BR33+BS33+BT33+BU33,IF(BF33="Early",BV33+BW33+BX33+BY33+BZ33+CA33,0)) -> 6 | CC33: =IF(BF33="Established",BO33+CB33,IF(BF33="Early",BO33+Parameters!$B$50*CB33,BO33)) -> 11 | CD33: =IF(BF33="Established",IF(CC33>=Parameters!$B$51,6,IF(CC33>=Parameters!$B$52,5,IF(CC33>=Parameters!$B$53,4,IF(CC33>=Parameters!$B$54,3,IF(CC33>=Parameters!$B$55,2,1))))),IF(BF33="Early",IF(CC33>=Parameters!$B$56,5,IF(CC33>=Parameters!$B$57,4,IF(CC33>=Parameters!$B$58,3,IF(CC33>=Parameters!$B$59,2,1)))),IF(CC33>=Parameters!$B$60,6,IF(CC33>=Parameters!$B$61,5,IF(CC33>=Parameters!$B$62,4,IF(CC33>=Parameters!$B$63,3,IF(CC33>=Parameters!$B$64,2,1))))))) -> 5 | CE33: =IF(AND(ISNUMBER(AR33),AR33<Parameters!$B$66),1,0) -> 0 | CF33: =IF(AND(LEFT(AH33,5)="Death",ISNUMBER(AG33)),IF(BF33="Early",IF(AND(AG33<Parameters!$B$70,ISNUMBER(U33),U33<Parameters!$B$71),1,0),IF(AND(AG33<Parameters!$B$67,OR(AND(ISNUMBER(U33),U33<Parameters!$B$68),AND(ISNUMBER(V33),V33<Parameters!$B$69))),1,0)),0) -> 0 | CG33: =IF(AND(ISNUMBER(AG33),AG33<0),1,0) -> 0 | CH33: =IF(OR(AND(ISNUMBER(U33),U33>Parameters!$B$74),AND(ISNUMBER(AF33),AF33>Parameters!$B$75),AND(ISNUMBER(AE33),AE33>Parameters!$B$76)),1,0) -> 0 | CI33: =IF(AND(ISNUMBER(BC33),BC33>=0,BC33<=Parameters!$B$77),1,0) -> 0 | CJ33: =IF(CF33=1,1,MIN(CD33,IF(CE33=1,3,6),IF(CG33=1,IF(BF33="Early",Parameters!$B$73,Parameters!$B$72),6),IF(CH33=1,3,6),IF(CI33=1,3,6))) -> 5 | CK33: =INDEX(Parameters!$F$2:$F$7,CJ33) -> Buy | CL33: =IF(CF33=1,"Hard sell: breakdown; ","")&IF(CE33=1,"Insufficient history; ","")&IF(AND(CF33=0,CG33=1),"Below 200D; ","")&IF(CH33=1,"Extended - wait for pullback; ","")&IF(CI33=1,"Earnings within "&Parameters!$B$77&"d; ","")
A34: PLTR | B34: 6 | C34: 5 | D34: 44.4 | E34: -0.7 | F34: 9 | G34: Palantir Technologies Inc. | H34: Software | I34: 166.96 | J34: USD | K34: Technology | L34: 407390504114 | M34: 46237 | N34: 17.14 | O34: 46328 | P34: estimated | Q34: -1.52 | R34: -0.45 | S34: -1.48 | T34: -5.94 | U34: -4.56 | V34: 28.22 | W34: 10.13 | X34: 2.83 | AC34: 23.58 | AD34: -19.55 | AE34: 48.85 | AF34: 9.04 | AG34: 10.23 | AH34: Golden (2d) | AI34: -3.02 | AJ34: -22.27 | AK34: 225 | AL34: 92.8 | AM34: 49 | AN34: 38.1 | AO34: 74.01 | AP34: 0.69 | AQ34: 3.24 | AR34: 300 | AS34: 46275 | AT34: 6155940864 | AU34: 5219999744 | AV34: 84.8 | AW34: 3016691968 | AX34: 2159104512 | AY34: 35.07 | AZ34: 9197698752 | BA34: 56.96 | BB34: 59.9 | BC34: =IF(AND(ISNUMBER(O34),ISNUMBER(AS34)),O34-AS34,"") -> 53 | BD34: =IF(OR(ISNUMBER(SEARCH("ETF",H34)),AND(F34="",AO34="")),1,0) -> 0 | BE34: =IF(ISNUMBER(L34),IF(L34>=Parameters!$B$3,2,IF(L34>=Parameters!$B$4,1,0)),0)+IF(ISNUMBER(AW34),IF(AW34>0,IF(AND(ISNUMBER(AM34),AM34>=Parameters!$B$5),2,1),0),0)+IF(ISNUMBER(AX34),IF(AND(AX34>0,ISNUMBER(AY34),AY34>=Parameters!$B$6),1,0),0)+IF(ISNUMBER(AO34),IF(AND(AO34>0,AO34<=Parameters!$B$7),1,0),0)+IF(ISNUMBER(F34),IF(F34>=Parameters!$B$8,1,0),0) -> 6 | BF34: =IF(BD34=1,"ETF",IF(OR(AND(ISNUMBER(L34),L34>=Parameters!$B$10),BE34>=Parameters!$B$9),"Established","Early")) -> Established | BG34: =IF(LEFT(AH34,6)="Golden",2,IF(LEFT(AH34,5)="Death",-2,0)) -> 2 | BH34: =IF(ISNUMBER(AG34),IF(AG34>Parameters!$B$12,2,IF(AG34>0,1,IF(AG34>=Parameters!$B$13,-1,-2))),0) -> 2 | BI34: =IF(ISNUMBER(AF34),IF(AND(AF34>=Parameters!$B$14,AF34<=Parameters!$B$15),1,IF(OR(AF34>Parameters!$B$16,AF34<Parameters!$B$17),-1,0)),0) -> 0 | BJ34: =IF(ISNUMBER(AE34),IF(AND(AE34>=Parameters!$B$18,AE34<=Parameters!$B$19),1,IF(OR(AE34>Parameters!$B$20,AE34<Parameters!$B$21),-1,0)),0) -> 1 | BK34: =IF(ISNUMBER(E34),IF(E34>Parameters!$B$22,1,IF(E34<Parameters!$B$23,-1,0)),0) -> 0 | BL34: =IF(ISNUMBER(C34),IF(C34>=Parameters!$B$24,1,IF(C34<=Parameters!$B$25,-1,0)),0) -> 0 | BM34: =IF(ISNUMBER(AJ34),IF(AND(AJ34>Parameters!$B$26,ISNUMBER(U34)),IF(U34<0,-1,1),0),0) -> 0 | BN34: =IF(ISNUMBER(AD34),IF(AD34>Parameters!$B$27,1,IF(AD34<Parameters!$B$28,-1,0)),0) -> 0 | BO34: =BG34+BH34+BI34+BJ34+BK34+BL34+BM34+BN34 -> 5 | BP34: =IF(ISNUMBER(F34),IF(F34>=Parameters!$B$30,2,IF(F34>=Parameters!$B$31,1,IF(F34<=Parameters!$B$32,-1,0))),0) -> 2 | BQ34: =IF(ISNUMBER(AK34),IF(AK34>Parameters!$B$33,1,IF(AK34<0,-1,0)),0) -> 1 | BR34: =IF(ISNUMBER(AL34),IF(AL34>Parameters!$B$34,1,IF(AL34<0,-1,0)),0) -> 1 | BS34: =IF(ISNUMBER(AP34),IF(AND(AP34>0,AP34<=Parameters!$B$35),1,IF(AP34>Parameters!$B$36,-1,0)),0) -> 1 | BT34: =IF(ISNUMBER(AY34),IF(AY34>Parameters!$B$37,1,IF(AY34<0,-1,0)),0) -> 1 | BU34: =IF(ISNUMBER(AZ34),IF(AZ34>0,1,0),0) -> 1 | BV34: =IF(ISNUMBER(AL34),IF(AL34>Parameters!$B$39,2,IF(AL34>Parameters!$B$40,1,IF(AL34<0,-2,IF(AL34<Parameters!$B$41,-1,0)))),0) -> 2 | BW34: =IF(ISNUMBER(AV34),IF(AV34>Parameters!$B$42,1,IF(AV34<Parameters!$B$43,-1,0)),0) -> 1 | BX34: =IF(AND(ISNUMBER(AX34),AX34>0),1,IF(AND(ISNUMBER(AY34),AY34<Parameters!$B$44),-1,0)) -> 1 | BY34: =IF(ISNUMBER(AW34),IF(AW34>0,1,0),0) -> 1 | BZ34: =IF(ISNUMBER(AQ34),IF(AQ34>Parameters!$B$46,-2,IF(AQ34>Parameters!$B$45,-1,0)),0) -> 0 | CA34: =IF(ISNUMBER(F34),IF(F34>=Parameters!$B$47,1,IF(F34<=Parameters!$B$48,-1,0)),0) -> 1 | CB34: =IF(BF34="Established",BP34+BQ34+BR34+BS34+BT34+BU34,IF(BF34="Early",BV34+BW34+BX34+BY34+BZ34+CA34,0)) -> 7 | CC34: =IF(BF34="Established",BO34+CB34,IF(BF34="Early",BO34+Parameters!$B$50*CB34,BO34)) -> 12 | CD34: =IF(BF34="Established",IF(CC34>=Parameters!$B$51,6,IF(CC34>=Parameters!$B$52,5,IF(CC34>=Parameters!$B$53,4,IF(CC34>=Parameters!$B$54,3,IF(CC34>=Parameters!$B$55,2,1))))),IF(BF34="Early",IF(CC34>=Parameters!$B$56,5,IF(CC34>=Parameters!$B$57,4,IF(CC34>=Parameters!$B$58,3,IF(CC34>=Parameters!$B$59,2,1)))),IF(CC34>=Parameters!$B$60,6,IF(CC34>=Parameters!$B$61,5,IF(CC34>=Parameters!$B$62,4,IF(CC34>=Parameters!$B$63,3,IF(CC34>=Parameters!$B$64,2,1))))))) -> 5 | CE34: =IF(AND(ISNUMBER(AR34),AR34<Parameters!$B$66),1,0) -> 0 | CF34: =IF(AND(LEFT(AH34,5)="Death",ISNUMBER(AG34)),IF(BF34="Early",IF(AND(AG34<Parameters!$B$70,ISNUMBER(U34),U34<Parameters!$B$71),1,0),IF(AND(AG34<Parameters!$B$67,OR(AND(ISNUMBER(U34),U34<Parameters!$B$68),AND(ISNUMBER(V34),V34<Parameters!$B$69))),1,0)),0) -> 0 | CG34: =IF(AND(ISNUMBER(AG34),AG34<0),1,0) -> 0 | CH34: =IF(OR(AND(ISNUMBER(U34),U34>Parameters!$B$74),AND(ISNUMBER(AF34),AF34>Parameters!$B$75),AND(ISNUMBER(AE34),AE34>Parameters!$B$76)),1,0) -> 0 | CI34: =IF(AND(ISNUMBER(BC34),BC34>=0,BC34<=Parameters!$B$77),1,0) -> 0 | CJ34: =IF(CF34=1,1,MIN(CD34,IF(CE34=1,3,6),IF(CG34=1,IF(BF34="Early",Parameters!$B$73,Parameters!$B$72),6),IF(CH34=1,3,6),IF(CI34=1,3,6))) -> 5 | CK34: =INDEX(Parameters!$F$2:$F$7,CJ34) -> Buy | CL34: =IF(CF34=1,"Hard sell: breakdown; ","")&IF(CE34=1,"Insufficient history; ","")&IF(AND(CF34=0,CG34=1),"Below 200D; ","")&IF(CH34=1,"Extended - wait for pullback; ","")&IF(CI34=1,"Earnings within "&Parameters!$B$77&"d; ","")
A35: BE | B35: 6 | C35: 6 | D35: 45.8 | E35: 12.6 | F35: 7 | G35: Bloom Energy Corporation | H35: Energy | I35: 263.6 | J35: USD | K35: Industrials | L35: 79310323730 | M35: 46231 | N35: 90.24 | O35: 46322 | P35: estimated | Q35: -2.11 | R35: -2.86 | S35: 21.32 | T35: 20.8 | U35: 24.8 | V35: 12.54 | W35: 65.57 | X35: 379.27 | AC35: 7.9 | AD35: -24.96 | AE35: 62.74 | AF35: 16.59 | AG35: 36.04 | AH35: Golden | AI35: 7.34 | AJ35: 16.95 | AK35: 165.52 | AL35: 165.5 | AM35: 7.87 | AN35: 22.21 | AO35: 56.46 | AP35: -0.76 | AQ35: 6.31 | AR35: 300 | AS35: 46275 | AT35: 3113149952 | AU35: 985355008 | AV35: 31.65 | AW35: 244942000 | AX35: 531637504 | AY35: 17.08 | AZ35: -98164224 | BA35: 339.33 | BB35: 69.9 | BC35: =IF(AND(ISNUMBER(O35),ISNUMBER(AS35)),O35-AS35,"") -> 47 | BD35: =IF(OR(ISNUMBER(SEARCH("ETF",H35)),AND(F35="",AO35="")),1,0) -> 0 | BE35: =IF(ISNUMBER(L35),IF(L35>=Parameters!$B$3,2,IF(L35>=Parameters!$B$4,1,0)),0)+IF(ISNUMBER(AW35),IF(AW35>0,IF(AND(ISNUMBER(AM35),AM35>=Parameters!$B$5),2,1),0),0)+IF(ISNUMBER(AX35),IF(AND(AX35>0,ISNUMBER(AY35),AY35>=Parameters!$B$6),1,0),0)+IF(ISNUMBER(AO35),IF(AND(AO35>0,AO35<=Parameters!$B$7),1,0),0)+IF(ISNUMBER(F35),IF(F35>=Parameters!$B$8,1,0),0) -> 5 | BF35: =IF(BD35=1,"ETF",IF(OR(AND(ISNUMBER(L35),L35>=Parameters!$B$10),BE35>=Parameters!$B$9),"Established","Early")) -> Established | BG35: =IF(LEFT(AH35,6)="Golden",2,IF(LEFT(AH35,5)="Death",-2,0)) -> 2 | BH35: =IF(ISNUMBER(AG35),IF(AG35>Parameters!$B$12,2,IF(AG35>0,1,IF(AG35>=Parameters!$B$13,-1,-2))),0) -> 2 | BI35: =IF(ISNUMBER(AF35),IF(AND(AF35>=Parameters!$B$14,AF35<=Parameters!$B$15),1,IF(OR(AF35>Parameters!$B$16,AF35<Parameters!$B$17),-1,0)),0) -> -1 | BJ35: =IF(ISNUMBER(AE35),IF(AND(AE35>=Parameters!$B$18,AE35<=Parameters!$B$19),1,IF(OR(AE35>Parameters!$B$20,AE35<Parameters!$B$21),-1,0)),0) -> 1 | BK35: =IF(ISNUMBER(E35),IF(E35>Parameters!$B$22,1,IF(E35<Parameters!$B$23,-1,0)),0) -> 1 | BL35: =IF(ISNUMBER(C35),IF(C35>=Parameters!$B$24,1,IF(C35<=Parameters!$B$25,-1,0)),0) -> 0 | BM35: =IF(ISNUMBER(AJ35),IF(AND(AJ35>Parameters!$B$26,ISNUMBER(U35)),IF(U35<0,-1,1),0),0) -> 1 | BN35: =IF(ISNUMBER(AD35),IF(AD35>Parameters!$B$27,1,IF(AD35<Parameters!$B$28,-1,0)),0) -> 0 | BO35: =BG35+BH35+BI35+BJ35+BK35+BL35+BM35+BN35 -> 6 | BP35: =IF(ISNUMBER(F35),IF(F35>=Parameters!$B$30,2,IF(F35>=Parameters!$B$31,1,IF(F35<=Parameters!$B$32,-1,0))),0) -> 1 | BQ35: =IF(ISNUMBER(AK35),IF(AK35>Parameters!$B$33,1,IF(AK35<0,-1,0)),0) -> 1 | BR35: =IF(ISNUMBER(AL35),IF(AL35>Parameters!$B$34,1,IF(AL35<0,-1,0)),0) -> 1 | BS35: =IF(ISNUMBER(AP35),IF(AND(AP35>0,AP35<=Parameters!$B$35),1,IF(AP35>Parameters!$B$36,-1,0)),0) -> 0 | BT35: =IF(ISNUMBER(AY35),IF(AY35>Parameters!$B$37,1,IF(AY35<0,-1,0)),0) -> 1 | BU35: =IF(ISNUMBER(AZ35),IF(AZ35>0,1,0),0) -> 0 | BV35: =IF(ISNUMBER(AL35),IF(AL35>Parameters!$B$39,2,IF(AL35>Parameters!$B$40,1,IF(AL35<0,-2,IF(AL35<Parameters!$B$41,-1,0)))),0) -> 2 | BW35: =IF(ISNUMBER(AV35),IF(AV35>Parameters!$B$42,1,IF(AV35<Parameters!$B$43,-1,0)),0) -> 0 | BX35: =IF(AND(ISNUMBER(AX35),AX35>0),1,IF(AND(ISNUMBER(AY35),AY35<Parameters!$B$44),-1,0)) -> 1 | BY35: =IF(ISNUMBER(AW35),IF(AW35>0,1,0),0) -> 1 | BZ35: =IF(ISNUMBER(AQ35),IF(AQ35>Parameters!$B$46,-2,IF(AQ35>Parameters!$B$45,-1,0)),0) -> 0 | CA35: =IF(ISNUMBER(F35),IF(F35>=Parameters!$B$47,1,IF(F35<=Parameters!$B$48,-1,0)),0) -> 1 | CB35: =IF(BF35="Established",BP35+BQ35+BR35+BS35+BT35+BU35,IF(BF35="Early",BV35+BW35+BX35+BY35+BZ35+CA35,0)) -> 4 | CC35: =IF(BF35="Established",BO35+CB35,IF(BF35="Early",BO35+Parameters!$B$50*CB35,BO35)) -> 10 | CD35: =IF(BF35="Established",IF(CC35>=Parameters!$B$51,6,IF(CC35>=Parameters!$B$52,5,IF(CC35>=Parameters!$B$53,4,IF(CC35>=Parameters!$B$54,3,IF(CC35>=Parameters!$B$55,2,1))))),IF(BF35="Early",IF(CC35>=Parameters!$B$56,5,IF(CC35>=Parameters!$B$57,4,IF(CC35>=Parameters!$B$58,3,IF(CC35>=Parameters!$B$59,2,1)))),IF(CC35>=Parameters!$B$60,6,IF(CC35>=Parameters!$B$61,5,IF(CC35>=Parameters!$B$62,4,IF(CC35>=Parameters!$B$63,3,IF(CC35>=Parameters!$B$64,2,1))))))) -> 5 | CE35: =IF(AND(ISNUMBER(AR35),AR35<Parameters!$B$66),1,0) -> 0 | CF35: =IF(AND(LEFT(AH35,5)="Death",ISNUMBER(AG35)),IF(BF35="Early",IF(AND(AG35<Parameters!$B$70,ISNUMBER(U35),U35<Parameters!$B$71),1,0),IF(AND(AG35<Parameters!$B$67,OR(AND(ISNUMBER(U35),U35<Parameters!$B$68),AND(ISNUMBER(V35),V35<Parameters!$B$69))),1,0)),0) -> 0 | CG35: =IF(AND(ISNUMBER(AG35),AG35<0),1,0) -> 0 | CH35: =IF(OR(AND(ISNUMBER(U35),U35>Parameters!$B$74),AND(ISNUMBER(AF35),AF35>Parameters!$B$75),AND(ISNUMBER(AE35),AE35>Parameters!$B$76)),1,0) -> 1 | CI35: =IF(AND(ISNUMBER(BC35),BC35>=0,BC35<=Parameters!$B$77),1,0) -> 0 | CJ35: =IF(CF35=1,1,MIN(CD35,IF(CE35=1,3,6),IF(CG35=1,IF(BF35="Early",Parameters!$B$73,Parameters!$B$72),6),IF(CH35=1,3,6),IF(CI35=1,3,6))) -> 3 | CK35: =INDEX(Parameters!$F$2:$F$7,CJ35) -> Hold | CL35: =IF(CF35=1,"Hard sell: breakdown; ","")&IF(CE35=1,"Insufficient history; ","")&IF(AND(CF35=0,CG35=1),"Below 200D; ","")&IF(CH35=1,"Extended - wait for pullback; ","")&IF(CI35=1,"Earnings within "&Parameters!$B$77&"d; ","") -> Extended - wait for pullback;
A36: AVGO | B36: 6 | C36: 4 | D36: 33 | E36: 5 | F36: 10 | G36: Broadcom Inc. | H36: Chips | I36: 363.63 | J36: USD | K36: Technology | L36: 1733567072547 | M36: 46176 | N36: 1.67 | O36: 46267 | P36: estimated | Q36: -0.21 | R36: -1.13 | S36: -0.98 | T36: 2.26 | U36: -12.61 | V36: -2.28 | W36: 6.46 | X36: 8.01 | AC36: -6.92 | AD36: -26.54 | AE36: 42.8 | AF36: -5.13 | AG36: -1.75 | AH36: Golden | AI36: 0.08 | AJ36: 24 | AK36: 216.1 | AL36: 85.5 | AM36: 42.94 | AN36: 44.25 | AO36: 19.12 | AP36: 0.22 | AQ36: 1.19 | AR36: 300 | AS36: 46275 | AT36: 89103998976 | AU36: 67286999040 | AV36: 75.52 | AW36: 38264999936 | AX36: 30497124352 | AY36: 34.23 | AZ36: -35444000768 | BA36: 25.41 | BB36: 35.93 | BC36: =IF(AND(ISNUMBER(O36),ISNUMBER(AS36)),O36-AS36,"") -> -8 | BD36: =IF(OR(ISNUMBER(SEARCH("ETF",H36)),AND(F36="",AO36="")),1,0) -> 0 | BE36: =IF(ISNUMBER(L36),IF(L36>=Parameters!$B$3,2,IF(L36>=Parameters!$B$4,1,0)),0)+IF(ISNUMBER(AW36),IF(AW36>0,IF(AND(ISNUMBER(AM36),AM36>=Parameters!$B$5),2,1),0),0)+IF(ISNUMBER(AX36),IF(AND(AX36>0,ISNUMBER(AY36),AY36>=Parameters!$B$6),1,0),0)+IF(ISNUMBER(AO36),IF(AND(AO36>0,AO36<=Parameters!$B$7),1,0),0)+IF(ISNUMBER(F36),IF(F36>=Parameters!$B$8,1,0),0) -> 7 | BF36: =IF(BD36=1,"ETF",IF(OR(AND(ISNUMBER(L36),L36>=Parameters!$B$10),BE36>=Parameters!$B$9),"Established","Early")) -> Established | BG36: =IF(LEFT(AH36,6)="Golden",2,IF(LEFT(AH36,5)="Death",-2,0)) -> 2 | BH36: =IF(ISNUMBER(AG36),IF(AG36>Parameters!$B$12,2,IF(AG36>0,1,IF(AG36>=Parameters!$B$13,-1,-2))),0) -> -1 | BI36: =IF(ISNUMBER(AF36),IF(AND(AF36>=Parameters!$B$14,AF36<=Parameters!$B$15),1,IF(OR(AF36>Parameters!$B$16,AF36<Parameters!$B$17),-1,0)),0) -> 0 | BJ36: =IF(ISNUMBER(AE36),IF(AND(AE36>=Parameters!$B$18,AE36<=Parameters!$B$19),1,IF(OR(AE36>Parameters!$B$20,AE36<Parameters!$B$21),-1,0)),0) -> 0 | BK36: =IF(ISNUMBER(E36),IF(E36>Parameters!$B$22,1,IF(E36<Parameters!$B$23,-1,0)),0) -> 1 | BL36: =IF(ISNUMBER(C36),IF(C36>=Parameters!$B$24,1,IF(C36<=Parameters!$B$25,-1,0)),0) -> 0 | BM36: =IF(ISNUMBER(AJ36),IF(AND(AJ36>Parameters!$B$26,ISNUMBER(U36)),IF(U36<0,-1,1),0),0) -> -1 | BN36: =IF(ISNUMBER(AD36),IF(AD36>Parameters!$B$27,1,IF(AD36<Parameters!$B$28,-1,0)),0) -> 0 | BO36: =BG36+BH36+BI36+BJ36+BK36+BL36+BM36+BN36 -> 1 | BP36: =IF(ISNUMBER(F36),IF(F36>=Parameters!$B$30,2,IF(F36>=Parameters!$B$31,1,IF(F36<=Parameters!$B$32,-1,0))),0) -> 2 | BQ36: =IF(ISNUMBER(AK36),IF(AK36>Parameters!$B$33,1,IF(AK36<0,-1,0)),0) -> 1 | BR36: =IF(ISNUMBER(AL36),IF(AL36>Parameters!$B$34,1,IF(AL36<0,-1,0)),0) -> 1 | BS36: =IF(ISNUMBER(AP36),IF(AND(AP36>0,AP36<=Parameters!$B$35),1,IF(AP36>Parameters!$B$36,-1,0)),0) -> 1 | BT36: =IF(ISNUMBER(AY36),IF(AY36>Parameters!$B$37,1,IF(AY36<0,-1,0)),0) -> 1 | BU36: =IF(ISNUMBER(AZ36),IF(AZ36>0,1,0),0) -> 0 | BV36: =IF(ISNUMBER(AL36),IF(AL36>Parameters!$B$39,2,IF(AL36>Parameters!$B$40,1,IF(AL36<0,-2,IF(AL36<Parameters!$B$41,-1,0)))),0) -> 2 | BW36: =IF(ISNUMBER(AV36),IF(AV36>Parameters!$B$42,1,IF(AV36<Parameters!$B$43,-1,0)),0) -> 1 | BX36: =IF(AND(ISNUMBER(AX36),AX36>0),1,IF(AND(ISNUMBER(AY36),AY36<Parameters!$B$44),-1,0)) -> 1 | BY36: =IF(ISNUMBER(AW36),IF(AW36>0,1,0),0) -> 1 | BZ36: =IF(ISNUMBER(AQ36),IF(AQ36>Parameters!$B$46,-2,IF(AQ36>Parameters!$B$45,-1,0)),0) -> 0 | CA36: =IF(ISNUMBER(F36),IF(F36>=Parameters!$B$47,1,IF(F36<=Parameters!$B$48,-1,0)),0) -> 1 | CB36: =IF(BF36="Established",BP36+BQ36+BR36+BS36+BT36+BU36,IF(BF36="Early",BV36+BW36+BX36+BY36+BZ36+CA36,0)) -> 6 | CC36: =IF(BF36="Established",BO36+CB36,IF(BF36="Early",BO36+Parameters!$B$50*CB36,BO36)) -> 7 | CD36: =IF(BF36="Established",IF(CC36>=Parameters!$B$51,6,IF(CC36>=Parameters!$B$52,5,IF(CC36>=Parameters!$B$53,4,IF(CC36>=Parameters!$B$54,3,IF(CC36>=Parameters!$B$55,2,1))))),IF(BF36="Early",IF(CC36>=Parameters!$B$56,5,IF(CC36>=Parameters!$B$57,4,IF(CC36>=Parameters!$B$58,3,IF(CC36>=Parameters!$B$59,2,1)))),IF(CC36>=Parameters!$B$60,6,IF(CC36>=Parameters!$B$61,5,IF(CC36>=Parameters!$B$62,4,IF(CC36>=Parameters!$B$63,3,IF(CC36>=Parameters!$B$64,2,1))))))) -> 4 | CE36: =IF(AND(ISNUMBER(AR36),AR36<Parameters!$B$66),1,0) -> 0 | CF36: =IF(AND(LEFT(AH36,5)="Death",ISNUMBER(AG36)),IF(BF36="Early",IF(AND(AG36<Parameters!$B$70,ISNUMBER(U36),U36<Parameters!$B$71),1,0),IF(AND(AG36<Parameters!$B$67,OR(AND(ISNUMBER(U36),U36<Parameters!$B$68),AND(ISNUMBER(V36),V36<Parameters!$B$69))),1,0)),0) -> 0 | CG36: =IF(AND(ISNUMBER(AG36),AG36<0),1,0) -> 1 | CH36: =IF(OR(AND(ISNUMBER(U36),U36>Parameters!$B$74),AND(ISNUMBER(AF36),AF36>Parameters!$B$75),AND(ISNUMBER(AE36),AE36>Parameters!$B$76)),1,0) -> 0 | CI36: =IF(AND(ISNUMBER(BC36),BC36>=0,BC36<=Parameters!$B$77),1,0) -> 0 | CJ36: =IF(CF36=1,1,MIN(CD36,IF(CE36=1,3,6),IF(CG36=1,IF(BF36="Early",Parameters!$B$73,Parameters!$B$72),6),IF(CH36=1,3,6),IF(CI36=1,3,6))) -> 3 | CK36: =INDEX(Parameters!$F$2:$F$7,CJ36) -> Hold | CL36: =IF(CF36=1,"Hard sell: breakdown; ","")&IF(CE36=1,"Insufficient history; ","")&IF(AND(CF36=0,CG36=1),"Below 200D; ","")&IF(CH36=1,"Extended - wait for pullback; ","")&IF(CI36=1,"Earnings within "&Parameters!$B$77&"d; ","") -> Below 200D;
A37: SNOW | B37: 6 | C37: 7 | D37: 63.4 | E37: 3.8 | F37: 5 | G37: Snowflake Inc. | H37: Software | I37: 334.34 | J37: USD | K37: Technology | L37: 116946147528 | M37: 46267 | N37: 37.78 | O37: 46358 | P37: estimated | Q37: 0.86 | R37: -1.2 | S37: 9.32 | T37: 6.01 | U37: 0.06 | V37: 39.36 | W37: 86.33 | X37: 48.22 | AC37: 34.72 | AD37: -13.06 | AE37: 55.9 | AF37: 10.62 | AG37: 51.84 | AH37: Golden (45d) | AI37: -1.2 | AJ37: 57.35 | AL37: 35.1 | AM37: -20.07 | AN37: -48.06 | AO37: 113.39 | AP37: 2.2 | AQ37: 5.49 | AR37: 300 | AS37: 46275 | AT37: 5434647040 | AU37: 3642867968 | AV37: 67.03 | AW37: -1090797952 | AX37: 1739526656 | AY37: 32.01 | AZ37: -419119872 | BA37: 182.62 | BB37: 81.14 | BC37: =IF(AND(ISNUMBER(O37),ISNUMBER(AS37)),O37-AS37,"") -> 83 | BD37: =IF(OR(ISNUMBER(SEARCH("ETF",H37)),AND(F37="",AO37="")),1,0) -> 0 | BE37: =IF(ISNUMBER(L37),IF(L37>=Parameters!$B$3,2,IF(L37>=Parameters!$B$4,1,0)),0)+IF(ISNUMBER(AW37),IF(AW37>0,IF(AND(ISNUMBER(AM37),AM37>=Parameters!$B$5),2,1),0),0)+IF(ISNUMBER(AX37),IF(AND(AX37>0,ISNUMBER(AY37),AY37>=Parameters!$B$6),1,0),0)+IF(ISNUMBER(AO37),IF(AND(AO37>0,AO37<=Parameters!$B$7),1,0),0)+IF(ISNUMBER(F37),IF(F37>=Parameters!$B$8,1,0),0) -> 3 | BF37: =IF(BD37=1,"ETF",IF(OR(AND(ISNUMBER(L37),L37>=Parameters!$B$10),BE37>=Parameters!$B$9),"Established","Early")) -> Early | BG37: =IF(LEFT(AH37,6)="Golden",2,IF(LEFT(AH37,5)="Death",-2,0)) -> 2 | BH37: =IF(ISNUMBER(AG37),IF(AG37>Parameters!$B$12,2,IF(AG37>0,1,IF(AG37>=Parameters!$B$13,-1,-2))),0) -> 2 | BI37: =IF(ISNUMBER(AF37),IF(AND(AF37>=Parameters!$B$14,AF37<=Parameters!$B$15),1,IF(OR(AF37>Parameters!$B$16,AF37<Parameters!$B$17),-1,0)),0) -> 0 | BJ37: =IF(ISNUMBER(AE37),IF(AND(AE37>=Parameters!$B$18,AE37<=Parameters!$B$19),1,IF(OR(AE37>Parameters!$B$20,AE37<Parameters!$B$21),-1,0)),0) -> 1 | BK37: =IF(ISNUMBER(E37),IF(E37>Parameters!$B$22,1,IF(E37<Parameters!$B$23,-1,0)),0) -> 1 | BL37: =IF(ISNUMBER(C37),IF(C37>=Parameters!$B$24,1,IF(C37<=Parameters!$B$25,-1,0)),0) -> 1 | BM37: =IF(ISNUMBER(AJ37),IF(AND(AJ37>Parameters!$B$26,ISNUMBER(U37)),IF(U37<0,-1,1),0),0) -> 1 | BN37: =IF(ISNUMBER(AD37),IF(AD37>Parameters!$B$27,1,IF(AD37<Parameters!$B$28,-1,0)),0) -> 0 | BO37: =BG37+BH37+BI37+BJ37+BK37+BL37+BM37+BN37 -> 8 | BP37: =IF(ISNUMBER(F37),IF(F37>=Parameters!$B$30,2,IF(F37>=Parameters!$B$31,1,IF(F37<=Parameters!$B$32,-1,0))),0) -> 0 | BQ37: =IF(ISNUMBER(AK37),IF(AK37>Parameters!$B$33,1,IF(AK37<0,-1,0)),0) -> 0 | BR37: =IF(ISNUMBER(AL37),IF(AL37>Parameters!$B$34,1,IF(AL37<0,-1,0)),0) -> 1 | BS37: =IF(ISNUMBER(AP37),IF(AND(AP37>0,AP37<=Parameters!$B$35),1,IF(AP37>Parameters!$B$36,-1,0)),0) -> 0 | BT37: =IF(ISNUMBER(AY37),IF(AY37>Parameters!$B$37,1,IF(AY37<0,-1,0)),0) -> 1 | BU37: =IF(ISNUMBER(AZ37),IF(AZ37>0,1,0),0) -> 0 | BV37: =IF(ISNUMBER(AL37),IF(AL37>Parameters!$B$39,2,IF(AL37>Parameters!$B$40,1,IF(AL37<0,-2,IF(AL37<Parameters!$B$41,-1,0)))),0) -> 2 | BW37: =IF(ISNUMBER(AV37),IF(AV37>Parameters!$B$42,1,IF(AV37<Parameters!$B$43,-1,0)),0) -> 1 | BX37: =IF(AND(ISNUMBER(AX37),AX37>0),1,IF(AND(ISNUMBER(AY37),AY37<Parameters!$B$44),-1,0)) -> 1 | BY37: =IF(ISNUMBER(AW37),IF(AW37>0,1,0),0) -> 0 | BZ37: =IF(ISNUMBER(AQ37),IF(AQ37>Parameters!$B$46,-2,IF(AQ37>Parameters!$B$45,-1,0)),0) -> 0 | CA37: =IF(ISNUMBER(F37),IF(F37>=Parameters!$B$47,1,IF(F37<=Parameters!$B$48,-1,0)),0) -> 0 | CB37: =IF(BF37="Established",BP37+BQ37+BR37+BS37+BT37+BU37,IF(BF37="Early",BV37+BW37+BX37+BY37+BZ37+CA37,0)) -> 4 | CC37: =IF(BF37="Established",BO37+CB37,IF(BF37="Early",BO37+Parameters!$B$50*CB37,BO37)) -> 10 | CD37: =IF(BF37="Established",IF(CC37>=Parameters!$B$51,6,IF(CC37>=Parameters!$B$52,5,IF(CC37>=Parameters!$B$53,4,IF(CC37>=Parameters!$B$54,3,IF(CC37>=Parameters!$B$55,2,1))))),IF(BF37="Early",IF(CC37>=Parameters!$B$56,5,IF(CC37>=Parameters!$B$57,4,IF(CC37>=Parameters!$B$58,3,IF(CC37>=Parameters!$B$59,2,1)))),IF(CC37>=Parameters!$B$60,6,IF(CC37>=Parameters!$B$61,5,IF(CC37>=Parameters!$B$62,4,IF(CC37>=Parameters!$B$63,3,IF(CC37>=Parameters!$B$64,2,1))))))) -> 5 | CE37: =IF(AND(ISNUMBER(AR37),AR37<Parameters!$B$66),1,0) -> 0 | CF37: =IF(AND(LEFT(AH37,5)="Death",ISNUMBER(AG37)),IF(BF37="Early",IF(AND(AG37<Parameters!$B$70,ISNUMBER(U37),U37<Parameters!$B$71),1,0),IF(AND(AG37<Parameters!$B$67,OR(AND(ISNUMBER(U37),U37<Parameters!$B$68),AND(ISNUMBER(V37),V37<Parameters!$B$69))),1,0)),0) -> 0 | CG37: =IF(AND(ISNUMBER(AG37),AG37<0),1,0) -> 0 | CH37: =IF(OR(AND(ISNUMBER(U37),U37>Parameters!$B$74),AND(ISNUMBER(AF37),AF37>Parameters!$B$75),AND(ISNUMBER(AE37),AE37>Parameters!$B$76)),1,0) -> 0 | CI37: =IF(AND(ISNUMBER(BC37),BC37>=0,BC37<=Parameters!$B$77),1,0) -> 0 | CJ37: =IF(CF37=1,1,MIN(CD37,IF(CE37=1,3,6),IF(CG37=1,IF(BF37="Early",Parameters!$B$73,Parameters!$B$72),6),IF(CH37=1,3,6),IF(CI37=1,3,6))) -> 5 | CK37: =INDEX(Parameters!$F$2:$F$7,CJ37) -> Buy | CL37: =IF(CF37=1,"Hard sell: breakdown; ","")&IF(CE37=1,"Insufficient history; ","")&IF(AND(CF37=0,CG37=1),"Below 200D; ","")&IF(CH37=1,"Extended - wait for pullback; ","")&IF(CI37=1,"Earnings within "&Parameters!$B$77&"d; ","")
A38: GOOGL | B38: 6 | C38: 4 | D38: 48.9 | E38: -10.5 | F38: 10 | G38: Alphabet Inc. | H38: Mag 7 | I38: 331.46 | J38: USD | K38: Communication Services | L38: 4043827829570 | M38: 46225 | N38: 214.14 | O38: 46316 | P38: estimated | Q38: 0.24 | R38: -2.28 | S38: -1.68 | T38: -3.08 | U38: -3.59 | V38: -6.99 | W38: 7.37 | X38: 38.32 | AC38: -11.63 | AD38: -18.88 | AE38: 40.18 | AF38: -4.65 | AG38: -1.53 | AH38: Golden | AI38: -0.9 | AJ38: -6.36 | AK38: 297.9 | AL38: 24.2 | AM38: 54.75 | AN38: 48.68 | AO38: 22.23 | AP38: 0.06 | AQ38: 0.67 | AR38: 300 | AS38: 46275 | AT38: 445865984000 | AU38: 271517007872 | AV38: 60.9 | AW38: 244118994944 | AX38: 22665000960 | AY38: 5.08 | AZ38: 121682993152 | BA38: 40.54 | BB38: 55.35 | BC38: =IF(AND(ISNUMBER(O38),ISNUMBER(AS38)),O38-AS38,"") -> 41 | BD38: =IF(OR(ISNUMBER(SEARCH("ETF",H38)),AND(F38="",AO38="")),1,0) -> 0 | BE38: =IF(ISNUMBER(L38),IF(L38>=Parameters!$B$3,2,IF(L38>=Parameters!$B$4,1,0)),0)+IF(ISNUMBER(AW38),IF(AW38>0,IF(AND(ISNUMBER(AM38),AM38>=Parameters!$B$5),2,1),0),0)+IF(ISNUMBER(AX38),IF(AND(AX38>0,ISNUMBER(AY38),AY38>=Parameters!$B$6),1,0),0)+IF(ISNUMBER(AO38),IF(AND(AO38>0,AO38<=Parameters!$B$7),1,0),0)+IF(ISNUMBER(F38),IF(F38>=Parameters!$B$8,1,0),0) -> 7 | BF38: =IF(BD38=1,"ETF",IF(OR(AND(ISNUMBER(L38),L38>=Parameters!$B$10),BE38>=Parameters!$B$9),"Established","Early")) -> Established | BG38: =IF(LEFT(AH38,6)="Golden",2,IF(LEFT(AH38,5)="Death",-2,0)) -> 2 | BH38: =IF(ISNUMBER(AG38),IF(AG38>Parameters!$B$12,2,IF(AG38>0,1,IF(AG38>=Parameters!$B$13,-1,-2))),0) -> -1 | BI38: =IF(ISNUMBER(AF38),IF(AND(AF38>=Parameters!$B$14,AF38<=Parameters!$B$15),1,IF(OR(AF38>Parameters!$B$16,AF38<Parameters!$B$17),-1,0)),0) -> 0 | BJ38: =IF(ISNUMBER(AE38),IF(AND(AE38>=Parameters!$B$18,AE38<=Parameters!$B$19),1,IF(OR(AE38>Parameters!$B$20,AE38<Parameters!$B$21),-1,0)),0) -> 0 | BK38: =IF(ISNUMBER(E38),IF(E38>Parameters!$B$22,1,IF(E38<Parameters!$B$23,-1,0)),0) -> -1 | BL38: =IF(ISNUMBER(C38),IF(C38>=Parameters!$B$24,1,IF(C38<=Parameters!$B$25,-1,0)),0) -> 0 | BM38: =IF(ISNUMBER(AJ38),IF(AND(AJ38>Parameters!$B$26,ISNUMBER(U38)),IF(U38<0,-1,1),0),0) -> 0 | BN38: =IF(ISNUMBER(AD38),IF(AD38>Parameters!$B$27,1,IF(AD38<Parameters!$B$28,-1,0)),0) -> 0 | BO38: =BG38+BH38+BI38+BJ38+BK38+BL38+BM38+BN38 -> 0 | BP38: =IF(ISNUMBER(F38),IF(F38>=Parameters!$B$30,2,IF(F38>=Parameters!$B$31,1,IF(F38<=Parameters!$B$32,-1,0))),0) -> 2 | BQ38: =IF(ISNUMBER(AK38),IF(AK38>Parameters!$B$33,1,IF(AK38<0,-1,0)),0) -> 1 | BR38: =IF(ISNUMBER(AL38),IF(AL38>Parameters!$B$34,1,IF(AL38<0,-1,0)),0) -> 1 | BS38: =IF(ISNUMBER(AP38),IF(AND(AP38>0,AP38<=Parameters!$B$35),1,IF(AP38>Parameters!$B$36,-1,0)),0) -> 1 | BT38: =IF(ISNUMBER(AY38),IF(AY38>Parameters!$B$37,1,IF(AY38<0,-1,0)),0) -> 0 | BU38: =IF(ISNUMBER(AZ38),IF(AZ38>0,1,0),0) -> 1 | BV38: =IF(ISNUMBER(AL38),IF(AL38>Parameters!$B$39,2,IF(AL38>Parameters!$B$40,1,IF(AL38<0,-2,IF(AL38<Parameters!$B$41,-1,0)))),0) -> 1 | BW38: =IF(ISNUMBER(AV38),IF(AV38>Parameters!$B$42,1,IF(AV38<Parameters!$B$43,-1,0)),0) -> 1 | BX38: =IF(AND(ISNUMBER(AX38),AX38>0),1,IF(AND(ISNUMBER(AY38),AY38<Parameters!$B$44),-1,0)) -> 1 | BY38: =IF(ISNUMBER(AW38),IF(AW38>0,1,0),0) -> 1 | BZ38: =IF(ISNUMBER(AQ38),IF(AQ38>Parameters!$B$46,-2,IF(AQ38>Parameters!$B$45,-1,0)),0) -> 0 | CA38: =IF(ISNUMBER(F38),IF(F38>=Parameters!$B$47,1,IF(F38<=Parameters!$B$48,-1,0)),0) -> 1 | CB38: =IF(BF38="Established",BP38+BQ38+BR38+BS38+BT38+BU38,IF(BF38="Early",BV38+BW38+BX38+BY38+BZ38+CA38,0)) -> 6 | CC38: =IF(BF38="Established",BO38+CB38,IF(BF38="Early",BO38+Parameters!$B$50*CB38,BO38)) -> 6 | CD38: =IF(BF38="Established",IF(CC38>=Parameters!$B$51,6,IF(CC38>=Parameters!$B$52,5,IF(CC38>=Parameters!$B$53,4,IF(CC38>=Parameters!$B$54,3,IF(CC38>=Parameters!$B$55,2,1))))),IF(BF38="Early",IF(CC38>=Parameters!$B$56,5,IF(CC38>=Parameters!$B$57,4,IF(CC38>=Parameters!$B$58,3,IF(CC38>=Parameters!$B$59,2,1)))),IF(CC38>=Parameters!$B$60,6,IF(CC38>=Parameters!$B$61,5,IF(CC38>=Parameters!$B$62,4,IF(CC38>=Parameters!$B$63,3,IF(CC38>=Parameters!$B$64,2,1))))))) -> 4 | CE38: =IF(AND(ISNUMBER(AR38),AR38<Parameters!$B$66),1,0) -> 0 | CF38: =IF(AND(LEFT(AH38,5)="Death",ISNUMBER(AG38)),IF(BF38="Early",IF(AND(AG38<Parameters!$B$70,ISNUMBER(U38),U38<Parameters!$B$71),1,0),IF(AND(AG38<Parameters!$B$67,OR(AND(ISNUMBER(U38),U38<Parameters!$B$68),AND(ISNUMBER(V38),V38<Parameters!$B$69))),1,0)),0) -> 0 | CG38: =IF(AND(ISNUMBER(AG38),AG38<0),1,0) -> 1 | CH38: =IF(OR(AND(ISNUMBER(U38),U38>Parameters!$B$74),AND(ISNUMBER(AF38),AF38>Parameters!$B$75),AND(ISNUMBER(AE38),AE38>Parameters!$B$76)),1,0) -> 0 | CI38: =IF(AND(ISNUMBER(BC38),BC38>=0,BC38<=Parameters!$B$77),1,0) -> 0 | CJ38: =IF(CF38=1,1,MIN(CD38,IF(CE38=1,3,6),IF(CG38=1,IF(BF38="Early",Parameters!$B$73,Parameters!$B$72),6),IF(CH38=1,3,6),IF(CI38=1,3,6))) -> 3 | CK38: =INDEX(Parameters!$F$2:$F$7,CJ38) -> Hold | CL38: =IF(CF38=1,"Hard sell: breakdown; ","")&IF(CE38=1,"Insufficient history; ","")&IF(AND(CF38=0,CG38=1),"Below 200D; ","")&IF(CH38=1,"Extended - wait for pullback; ","")&IF(CI38=1,"Earnings within "&Parameters!$B$77&"d; ","") -> Below 200D;
